Workbook
Name __I______AU__E: #REF!
Name __I______AU__E: #REF!

Sheet Шаблон
A1: Банк номи | B1: АТ "Халқ банк"
A2: Вилоят номи | B2: Фаргона вилояти
A3: Филиал номи | B3: Бешариқ филиали
A4: МФО:
A5: Бошкарувчиси в.в.б. | B5: _____________
A6: Бошкарувчи уринбосари
A7: Кредит бўлими бошлиғи | B7: _____________
A8: Бош бухгалтер в.в.б. | B8: _____________
A9: Касса мудираси
A10: ВАШ назоратчиси
A11: ВАШ кассири
A12: ВАШ раками | B12: ________
A13: Аудит ходимлари: 1 | B13: А.Ҳазратқулов
A14: 2
A15: Текшириш санаси | B15: 2024 йил 1 январ
A16: Ўтган йилги ҳолат | B16: 2023 йил 1 январ
A18: Аудит ходими лавозими | B18: бўлим бошлиғи
A20: Изоҳ: | B20: Жадвалдаги листлар бўйича қуйидагича ўзгартиришлар киритилади:
A21: Кўк рангли лист | B21: Филиалнинг текшириш санасигача бўлган 1 йиллик айланма баланси қўйилади (ҳисоб рақамлар номи ҳамда жами кўрсатилган ҳолда)
A22: Оч қизил рангли лист | B22: Текшириш бошланган кундан якунланган кунгача бўлган айланма баланс қўйилади (ҳисоб рақамлар номи ҳамда жами қўрсатилган ҳолда)
A23: Тўқ яшил рангли лист | B23: Тегинилмайди, тайёр ҳисобот
A24: Оч яшил рангли лист | B24: 4 жадвалга фақат балансдан чиқарилган ва балансга киритилган асосий воситалар бўйича маълумотлар, 17 жадвалга смета ҳамда 23 жадвалга муддати ўтган ва муаммоли кредитлар бўйича маълумотлар киритилади. Қолгани тайёр
A25: Сариқ рангли лист | B25: Жадваллар тўлдирилиши лозим

Sheet Баланс
A1: IABS
A2: БХМ: 11350-КАРШИ Ш., АТ ХАЛК БАНКИ КАРШИ ШАХАР БХМ
A3: ТОШКЕНТ Ш., АТ ХАЛК БАНКИ ХИСОБ-КИТОБ МАРКАЗИ
A4: КОЛДИКЛАР ВА АЙЛАНМАЛАР ЖАМЛАНМА БАЛАНСИ ( 01.04.2023 - 31.03.2024)
A6: Ед.изм. сум/тийин
A7: 1 - Основные счета
A8: Х/р | B8: Хисоб ракам номи | C8: 01.04.2023га КИРИМ КОЛДИКЛАР | E8: АЙЛАНМАЛАР | G8: 10.11.2023га ЧИКИМ КОЛДИКЛАР
C9: АКТИВ | D9: ПАССИВ | E9: ДЕБЕТ | F9: КРЕДИТ | G9: АКТИВ | H9: ПАССИВ
A10: 1 АКТИВЛАР
A11: 10101 | B11: Айланма кассадаги накд пуллар | C11: 3.8367082e+09 | D11: 0 | E11: 7.0998354e+11 | F11: 6.9374752e+11 | G11: 1.641973e+10 | H11: 0
A12: 10103 | B12: Пул алмаштириш шахобчаларидаги накд пуллар | C12: 0 | D12: 0 | E12: 4.6553422e+09 | F12: 4.6553422e+09 | G12: 0 | H12: 0
A13: 10107 | B13: Банкоматлар ва бошка уз-узига хизмат курсатиш ускуналаридаги накд пуллар | C13: 4529309471 | D13: 0 | E13: 209775682599 | F13: 197034191932 | G13: 12749579164 | H13: 0
A14: 10109 | B14: Йулдаги накд пуллар ва бошка тулов хужжатлари | C14: 0 | D14: 0 | E14: 1.1055696e+12 | F14: 1.1057322e+12 | G14: 0 | H14: 0
A15: 10111 | B15: Амалиёт кассаларидаги накд пуллар | C15: 0 | D15: 0 | E15: 3.0978259e+11 | F15: 3.0978287e+11 | G15: 0 | H15: 0
A16: 10113 | B16: Пенсиялар, ижтимоий нафака, компенсациялар ва бошка туловларни бериш буйича махсус кассалардаги накд пуллар | C16: 0 | D16: 0 | E16: 1.4391042e+11 | F16: 1.4391042e+11 | G16: 0 | H16: 0
A17: 10198 | C17: 1000000 | D17: 0 | E17: 6.7939824e+08 | F17: 461908083 | G17: 221975545 | H17: 0
A18: Жами | B18: 10100 | C18: 8.3670177e+09 | D18: 0 | E18: 2.4843566e+12 | F18: 2.4553245e+12 | G18: 2.9391285e+10 | H18: 0
A19: 10307 | B19: Марказий банкдан олиниши лозим булган маблаглар - Накд пуллар | C19: 0 | D19: 0 | E19: 119500000000 | F19: 119500000000 | G19: 0 | H19: 0
A20: 10311 | B20: Марказий банкдан олишини лозим булган маблаглар - топширилган накд пуллар | C20: 0 | D20: 0 | E20: 3161000000 | F20: 3161000000 | G20: 0 | H20: 0
A21: Жами | B21: 10300 | C21: 0 | D21: 0 | E21: 122661000000 | F21: 122661000000 | G21: 0 | H21: 0
A22: 10507 | B22: Бошка банклардан вакиллик хисобваракларидан олиниши лозим булган маблаглар - Накд пуллар | C22: 0 | D22: 0 | E22: 69500000000 | F22: 69500000000 | G22: 0 | H22: 0
A23: 10511 | B23: Жисм. шахс. банк карталаридан берилган накд пул м-глари б-ча бошка банклардан олиниши лозим булган м-глар | C23: 1.1008382e+08 | D23: 0 | E23: 1.7862228e+09 | F23: 1775850250 | G23: 10372539 | H23: 0
A24: 10513 | B24: Банк карталаридан амалга оширилган туловлар буйича бошка банклардан олиниши лозим булган маблаглар | C24: 1.1936612e+09 | D24: 0 | E24: 1.580008e+10 | F24: 1.4574706e+10 | G24: 1.2253741e+09 | H24: 0
A25: Жами | B25: 10500 | C25: 1.303745e+09 | D25: 0 | E25: 8.7086302e+10 | F25: 8.5850556e+10 | G25: 1.2357466e+09 | H25: 0
A26: 12503 | B26: Жисмоний шахсларга банк карталари оркали берилган киска муддатли кредитлар | C26: 15717856 | D26: 0 | E26: 6.7143841e+08 | F26: 5.3055412e+08 | G26: 1.4088429e+08 | H26: 0
A27: 12505 | B27: Жисмоний шахсларга берилган муддати утган кредитлар | C27: 2.6453235e+09 | D27: 0 | E27: 1.1983807e+10 | F27: 9.3957007e+09 | G27: 2.5881068e+09 | H27: 0
A28: 12521 | B28: Жисмоний шахсларга махсус дастурлар буйича берилган киска муддатли кредитлар | C28: 8.8098929e+08 | D28: 0 | E28: 1.2814971e+09 | F28: 8.4726169e+08 | G28: 4.3423545e+08 | H28: 0
A29: 12531 | C29: 0 | D29: 0 | E29: 5000000 | F29: 420426.5 | G29: 4579573.5 | H29: 0
A30: 12541 | C30: 0 | D30: 0 | E30: 75000000 | F30: 3279930.8 | G30: 71720069 | H30: 0
A31: 12599 | B31: Курилиши мумкин булган зарарларни копл.зах. - Жисм.шахсларга берилган киска муддатли кредитлар (контр-актив) | C31: 0 | D31: 93819686 | E31: 2.0004832e+08 | F31: 2.6791589e+08 | G31: 0 | H31: 67867569
A32: Жами | B32: 12500 | C32: 3.5420306e+09 | D32: 93819686 | E32: 1.4216791e+10 | F32: 1.1045133e+10 | G32: 3.2395262e+09 | H32: 67867569
A33: 12605 | B33: Якка тартибдаги тадбиркорларга берилган муддати утган кредитлар | C33: 68594471 | D33: 0 | E33: 2.9736457e+08 | F33: 2.4879001e+08 | G33: 48574556 | H33: 0
A34: Жами | B34: 12600 | C34: 68594471 | D34: 0 | E34: 2.9736457e+08 | F34: 2.4879001e+08 | G34: 48574556 | H34: 0
A35: 13105 | B35: Хусусий корхоналар, хужалик ширкатлари ва жамиятларга берилган муддати утган кредитлар | C35: 4.2927403e+08 | D35: 0 | E35: 1.8291472e+10 | F35: 7.3285236e+09 | G35: 1.10724e+10 | H35: 0
A36: 13199 | B36: Кур-и мумкин булган зарар. копл. зах.- Хусусий корх, хуж.ширкатлари ва жамиятларга б-ган киска муд.кр. (к-акт) | C36: 0 | D36: 225000000 | E36: 6.0301866e+08 | F36: 850549764 | G36: 0 | H36: 2.475311e+08
A37: Жами | B37: 13100 | C37: 4.2927403e+08 | D37: 225000000 | E37: 1.889449e+10 | F37: 8.1790733e+09 | G37: 1.10724e+10 | H37: 2.475311e+08
A38: 14301 | B38: Давлат эхтиёжлари учун харид килинадиган пахта хом-ашёсини етиштириш учун берилган узок муддатли кредитлар | C38: 0 | D38: 0 | E38: 50644128 | F38: 0 | G38: 50644128 | H38: 0
A39: Жами | B39: 14300 | C39: 0 | D39: 0 | E39: 50644128 | F39: 0 | G39: 50644128 | H39: 0
A40: 14901 | B40: Жисмоний шахсларга берилган узок муддатли кредитлар | C40: 4.6146272e+10 | D40: 0 | E40: 6.4506013e+10 | F40: 3.652958e+09 | G40: 6.0853055e+10 | H40: 0
A41: 14903 | B41: Жисмоний шахсларга давлат дастурлари буйича уй-жой сотиб олиш учун берилган узок муддатли ипотека кредитлари | C41: 3.7565358e+10 | D41: 0 | E41: 5.9345582e+10 | F41: 3.0418913e+09 | G41: 5.6303691e+10 | H41: 0
A42: 14913 | B42: Жисмоний шахсларга банк карталари оркали берилган узок муддатли кредитлар | C42: 2.3578996e+08 | D42: 0 | E42: 2.0225199e+08 | F42: 17730822 | G42: 1.8452116e+08 | H42: 0
... A71: 16397 | B71: Мижозларнинг бошка мажбуриятлари буйича олиниши лозим булган хисобланган фоизлар | C71: 0 | D71: 0 | E71: 0 | F71: 0 | G71: 0 | H71: 0
A72: 16399 | C72: 0 | D72: 6.5400127e+08 | E72: 8.7935067e+08 | F72: 1.4037818e+09 | G72: 0 | H72: 5.3122577e+08
A73: Жами | B73: 16300 | C73: 1.2166868e+10 | D73: 6.5400127e+08 | E73: 4.7191638e+10 | F73: 2.676569e+10 | G73: 2.1358454e+10 | H73: 5.3122577e+08
A74: 16401 | B74: Олиниши лозим булган хисобланган воситачилик хаки ва курсатилган хизматларучун туловлар | C74: 6166398.9 | D74: 0 | E74: 3.7985761e+08 | F74: 3.6602027e+08 | G74: 13874479 | H74: 0
A75: 16405 | B75: Олиниши лозим булган хисобланган жарима ва пенялар | C75: 2.0167232e+08 | D75: 0 | E75: 3.4539979e+08 | F75: 1.9582972e+08 | G75: 1.5088482e+08 | H75: 0
A76: 16413 | B76: Олиниши лозим булган хисобланган бошка фоизсиз даромадлар | C76: 1.142745e+08 | D76: 0 | E76: 1.1348593e+08 | F76: 0 | G76: 1.1348593e+08 | H76: 0
A77: 16499 | B77: Курилиши мумкин булган зарарларни копл.зах. - Олиниши лозим булган хис-н фоизсиз даромадлар (контр-актив) | C77: 0 | D77: 32146354 | E77: 36732825 | F77: 40896198 | G77: 0 | H77: 4163372.9
A78: Жами | B78: 16400 | C78: 3.2211322e+08 | D78: 32146354 | E78: 8.7547616e+08 | F78: 6.0274618e+08 | G78: 2.7824523e+08 | H78: 4163372.9
A79: 16509 | B79: Банкнинг иморатлари - Бинолар ва бошка иншоотлар | C79: 4.0168696e+09 | D79: 0 | E79: 4.5668696e+09 | F79: 398856163 | G79: 4.1680135e+09 | H79: 0
A80: 16511 | B80: Йигилган эскириш суммаси - Бинолар ва бошка иншоотлар (контр-актив) | C80: 0 | D80: 1.0239553e+09 | E80: 62155085 | F80: 1.2477154e+09 | G80: 0 | H80: 1.1855603e+09
A81: 16529 | B81: Транспорт воситалари | C81: 8.1091933e+08 | D81: 0 | E81: 2.8967759e+09 | F81: 1.7575893e+09 | G81: 1.1391866e+09 | H81: 0
A82: 16531 | B82: Йигилган эскириш суммаси - Транспорт воситалари (контр-актив) | C82: 0 | D82: 5.6485311e+08 | E82: 8.154133e+08 | F82: 1.4704157e+09 | G82: 0 | H82: 6.5500242e+08
A83: 16535 | B83: Мебель, мослама ва жихозлар | C83: 2.7487985e+09 | D83: 0 | E83: 4.1558257e+09 | F83: 4.5011138e+08 | G83: 3.7057143e+09 | H83: 0
A84: 16539 | B84: Йигилган эскириш суммаси - Мебель, мослама ва бошка жихозлар (контр-актив) | C84: 0 | D84: 1.5518074e+09 | E84: 2.235937e+09 | F84: 4.6410479e+09 | G84: 0 | H84: 2.4051109e+09
... A113: Жами | B113: АКТИВЛАР | C113: 3.6434128e+11 | D113: 1.7675513e+10 | E113: 3.6907587e+12 | F113: 3.2452316e+12 | G113: 4.7314505e+11 | H113: 2.4974937e+10
A115: 2 МАЖБУРИЯТЛАР
A116: 20206 | B116: Жисмоний шахсларнинг талаб килиб олингунча сакланадиган депозитлари | C116: 0 | D116: 20121107 | E116: 1.2786047e+10 | F116: 1.2815708e+10 | G116: 0 | H116: 30047117
A117: 20208 | B117: Хусусий корхоналар, хужалик ширкатлари ва жамиятларнинг талаб килиб олингунча сакланадиган депозитлари | C117: 0 | D117: 4.0196178e+09 | E117: 1.4824742e+11 | F117: 1.5745791e+11 | G117: 0 | H117: 9.1604637e+09
A118: 20210 | B118: Давлат корхоналари, ташкилотлари ва муассасаларининг талаб килиб олингунча сакланадиган депозитлари | C118: 0 | D118: 1.0914571e+08 | E118: 1.3410013e+08 | F118: 1.3468035e+08 | G118: 0 | H118: 580214.46
A119: 20212 | B119: Нодавлат нотижорат ташкилотларнинг талаб килиб олингунча сакланадиган депозитлари | C119: 0 | D119: 4.2367797e+09 | E119: 4.8969693e+10 | F119: 5.1401918e+10 | G119: 0 | H119: 2.4324676e+09
A120: 20218 | B120: Якка тартибдаги тадбиркорларнинг талаб килиб олингунча сакланадиган депозитлари | C120: 0 | D120: 3.7981669e+08 | E120: 7.5121938e+09 | F120: 7.9050451e+09 | G120: 0 | H120: 3.918688e+08
A121: Жами | B121: 20200 | C121: 0 | D121: 8.765481e+09 | E121: 2.1764945e+11 | F121: 2.2971526e+11 | G121: 0 | H121: 1.2015427e+10
A122: 20406 | B122: Жисмоний шахсларнинг жамгарма депозитлари | C122: 0 | D122: 1.2715184e+10 | E122: 1.9013319e+10 | F122: 2.9718067e+10 | G122: 0 | H122: 1.0711867e+10
A123: Жами | B123: 20400 | C123: 0 | D123: 1.2715184e+10 | E123: 1.9013319e+10 | F123: 2.9718067e+10 | G123: 0 | H123: 1.0711867e+10
A124: 20603 | B124: Респ. бюдж. молиялаштириладиган бюджет ташкилотларининг бюдж. ташкари маблаглари б-ча муддатли депозитлари | C124: 0 | D124: 0 | E124: 0 | F124: 16700000000 | G124: 0 | H124: 16700000000
A125: 20606 | B125: Жисмоний шахсларнинг муддатли депозитлари | C125: 0 | D125: 1.4780544e+10 | E125: 6.8115254e+09 | F125: 2.0309717e+10 | G125: 0 | H125: 1.3498238e+10
A126: 20608 | B126: Хусусий корхоналар, хужалик ширкатлари ва жамиятларнинг муддатли депозитлари | C126: 0 | D126: 2825000000 | E126: 0 | F126: 825000000 | G126: 0 | H126: 825000000
A127: 20612 | B127: Нодавлат нотижорат ташкилотларининг муддатли депозитлари | C127: 0 | D127: 18800000000 | E127: 3200000000 | F127: 6200000000 | G127: 0 | H127: 3000000000
... A172: 23106 | B172: И/х ва унга тенг.тул., ш-дек пенс., комп. ва б.ижт.тул.б-ча х.ю.с.ход. банк карт. утк.л/б мабл. б-ча трт х/в | C172: 0 | D172: 0 | E172: 1.5255049e+10 | F172: 1.5255049e+10 | G172: 0 | H172: 0
A173: 23108 | C173: 0 | D173: 0 | E173: 5617080007 | F173: 5617080007 | G173: 0 | H173: 0
A174: 23110 | B174: И/х ва унга тенг.тул.,пенс, комп ва б.ижт.тул. ДХХ,ИИВ,ИМВ,ФВВ, БК. ход.(конт.) банк карт.утк.л/б мабл. тр.х/в | C174: 0 | D174: 0 | E174: 4.7032791e+10 | F174: 4.7032791e+10 | G174: 0 | H174: 0
A175: 23112 | B175: Пенс. пенсиялари буйича жисм.шахс. банк карталарига утк. л/б мабл. б-ча тр.х/в | C175: 0 | D175: 0 | E175: 1.4044619e+11 | F175: 1.4044619e+11 | G175: 0 | H175: 0
A176: 23114 | B176: Ижт. нафакалар, комп. ва бошка туловлар б-ча жисм.шахс. банк карталарига утк.л/б маблаглари б-ча транзит х/в | C176: 0 | D176: 0 | E176: 23214239717 | F176: 23214239717 | G176: 0 | H176: 0
A177: 23116 | B177: Накд пуллар буйича жисм.шахс. банк карталарига утказилиши лозим булган мабл. б-ча транзит х/в | C177: 0 | D177: 2417317.2 | E177: 1.9813635e+10 | F177: 1.9848478e+10 | G177: 0 | H177: 34843000
A178: 23118 | B178: Жисм.шахс. депозит х/в жисм.шахс. банк карталарига утк. лозим булган маблаглар буйича транзит х/в | C178: 0 | D178: 0 | E178: 1.2968451e+09 | F178: 1.2971149e+09 | G178: 0 | H178: 269843.22
A179: 23120 | B179: Жисм. шахс. банк карталарига накд пулсиз утказилиши лозим булган бошка мабл. б-ча транзит х/в | C179: 0 | D179: 8136410 | E179: 2.8093902e+10 | F179: 2.8093902e+10 | G179: 0 | H179: 0
A180: Жами | B180: 23100 | C180: 0 | D180: 10553727 | E180: 2.8462508e+11 | F180: 2.8466019e+11 | G180: 0 | H180: 35112843
A181: 23206 | B181: Аникланиш жараёнидаги трансакциялар | C181: 0 | D181: 0 | E181: 7.1717373e+08 | F181: 7.1717373e+08 | G181: 0 | H181: 0
A182: 23210 | B182: Иктисодиёт ва молия вазирлиги хуз.фондлардан кишлок хужалиги махсулотлари учун ажратилган максадли маблаглар | C182: 0 | D182: 0 | E182: 9000 | F182: 0 | G182: 0 | H182: 0
A183: 23214 | C183: 0 | D183: 0 | E183: 374107000 | F183: 374107000 | G183: 0 | H183: 0
A184: 23230 | B184: Активларни коплаш буйича келиб тушган маблаглар | C184: 0 | D184: 0 | E184: 4.5504279e+09 | F184: 4.5504279e+09 | G184: 0 | H184: 0
A185: Жами | B185: 23200 | C185: 0 | D185: 0 | E185: 5.6417177e+09 | F185: 5.6417087e+09 | G185: 0 | H185: 0
A186: 23504 | B186: Банк карталаридан берилган накд пуллар ёки жисм.шахс. депозит х/в утк. мабл.буйича транзит х/в | C186: 0 | D186: 0 | E186: 178921025709 | F186: 178921112811 | G186: 0 | H186: 87102
A187: 23506 | B187: Ком-л тул. б-ча хужалик юритувчи субъектларнинг х/в утк.лозим булган банк карталаридан к/т тушум | C187: 0 | D187: 26049779 | E187: 191569519 | F187: 214493400 | G187: 0 | H187: 22923881
A188: 23508 | B188: Пулли хизматлар буйича хуж.юр.суб. х/в утк. лозим булган банк карталаридан келиб тушган тушум | C188: 0 | D188: 2400000 | E188: 800000 | F188: 1717550 | G188: 0 | H188: 917550
A189: 23510 | B189: Савдо ташкилотларининг хисобваракларига утказилиши лозим булган банк карталаридан келиб тушган тушум | C189: 0 | D189: 36221675 | E189: 2.8968682e+10 | F189: 2.9085379e+10 | G189: 0 | H189: 1.1673633e+08
A190: 23514 | B190: Конунчилик хуж. назарда тутилган бошка тул. б-ча олувчининг х/в утк.л/б банк карталаридан к/т пул маблаглари | C190: 0 | D190: 3.3028507e+08 | E190: 1.5171437e+10 | F190: 1.5376522e+10 | G190: 0 | H190: 2.0508533e+08
A191: 23516 | B191: Хорижий валюта сотиб олиш учун жисмоний шахсларнинг банк карталаридан утказилган пул маблаглари | C191: 0 | D191: 55130490 | E191: 1.0809482e+10 | F191: 1.0873759e+10 | G191: 0 | H191: 64277000
A192: Жами | B192: 23500 | C192: 0 | D192: 4.5008701e+08 | E192: 2.34063e+11 | F192: 2.3447298e+11 | G192: 0 | H192: 4.1002719e+08
A193: 29801 | B193: Мижозлар билан хисоб-китоблар | C193: 0 | D193: 2.1725771e+08 | E193: 3.9016888e+10 | F193: 3.9159586e+10 | G193: 0 | H193: 1.4476262e+08
A194: 29802 | B194: Туланиши лозим булган маблаглар - Товар-моддий кимматликлар ва хизматлар учун | C194: 0 | D194: 7684640.4 | E194: 7.7205252e+09 | F194: 7.7317473e+09 | G194: 0 | H194: 11222127
A195: 29803 | B195: Туланиши лозим булган маблаглар - Ходимлар билан хисоб-китоблар | C195: 0 | D195: 219404.6 | E195: 7.685479e+09 | F195: 7.685479e+09 | G195: 0 | H195: 0
... A206: Жами | B206: МАЖБУРИЯТЛАР | C206: 0 | D206: 3.7458619e+11 | E206: 2.8306843e+12 | F206: 3.2385813e+12 | G206: 0 | H206: 4.0981256e+11
A208: 3 ХУСУСИЙ КАПИТАЛ
A209: 30903 | B209: Умумий захира фонди | C209: 0 | D209: 39236635 | E209: 0 | F209: 39236635 | G209: 0 | H209: 39236635
A210: 30908 | B210: Бошлангич кийматга нисбатан бахолаш кийматининг ошган микдори | C210: 0 | D210: 110657500 | E210: 4638056.2 | F210: 1.0483544e+08 | G210: 0 | H210: 1.0019739e+08
A211: Жами | B211: 30900 | C211: 0 | D211: 1.4989413e+08 | E211: 4638056.2 | F211: 1.4407208e+08 | G211: 0 | H211: 1.3943402e+08
A212: 31203 | B212: Таксимланмаган фойда (актив-пассив) | C212: 3.288151e+10 | D212: 3.0621298e+09 | E212: 3.3056205e+10 | F212: 9.4120591e+09 | G212: 3.305168e+10 | H212: 9.4075344e+09
A213: 31206 | B213: Соф фойда (зарар) (актив-пассив) | C213: 1.4615971e+10 | D213: 1.636504e+10 | E213: 5.5987093e+10 | F213: 5.5987093e+10 | G213: 1.574246e+10 | H213: 1.5887074e+10
...

Sheet 1.активлар
G1: 1-жадвал
A2: =""&(Шаблон!B1)&"нинг "&(Шаблон!B2)&" "&(Шаблон!B3)&" бўйича "&(Шаблон!B15)&" ҳолатига активлар ТАҲЛИЛИ" -> АТ "Халқ банк"нинг Фаргона вилояти Бешариқ филиали бўйича 2024 йил 1 январ ҳолатига активлар ТАҲЛИЛИ
G3: (минг сўмда)
A4: Т/р | B4: Активлар таркиби | C4: =""&(Шаблон!B16)&" ҳолатига" -> 2023 йил 1 январ ҳолатига | E4: =""&(Шаблон!B15)&" ҳолатига" -> 2024 йил 1 январ ҳолатига | G4: фарқи (+;-)
C5: Сумма | D5: фоиз | E5: Сумма | F5: фоиз
A6: I. | B6: Даромад келтирувчи активлар | C6: =C7+C8+C10+C9+C12+C13+C14+C11 -> 3.1172742e+08 | D6: =+(C6+C32)*100/C30 -> 6.0557821 | E6: =E7+E8+E10+E9+E12+E13+E14+E11 -> 3.891274e+08 | F6: =+E6*100/E30 -> 82.242727 | G6: =G7+G8+G10+G9+G12+G13+G14+G11 -> 77399975 | H6: =+(E6+E32)-(C6+C32) -> -24680320
A7: а | B7: - факторинг | C7: =SUM(SUMIF(Баланс!$B:$B,11100,Баланс!$C:$C)/1000,0) -> 0 | D7: =C7/C6*100 -> 0 | E7: =SUM(SUMIF(Баланс!$B:$B,11100,Баланс!$G:$G)/1000,0) -> 0 | F7: =E7/E6*100 -> 0 | G7: =SUM(E7-C7) -> 0
A8: б | B8: - қисқа муддатли ва муддати утган ссудалар | C8: =SUM(SUMIF(Баланс!$B:$B,12600,Баланс!$C:$C)/1000+SUMIF(Баланс!$B:$B,12100,Баланс!$C:$C)/1000+SUMIF(Баланс!$B:$B,12300,Баланс!$C:$C)/1000+SUMIF(Баланс!$B:$B,12400,Баланс!$C:$C)/1000+SUMIF(Баланс!$B:$B,12500,Баланс!$C:$C)/1000+SUMIF(Баланс!$B:$B,12700,Баланс!$C:$C)/1000+SUMIF(Баланс!$B:$B,12900,Баланс!$C:$C)/1000+SUMIF(Баланс!$B:$B,13000,Баланс!$C:$C)/1000+SUMIF(Баланс!$B:$B,13100,Баланс!$C:$C)/1000+SUMIF(Баланс!$B:$B,13200,Баланс!$C:$C)/1000+SUMIF(Баланс!$B:$B,13300,Баланс!$C:$C)/1000,0) -> 4039899.2 | D8: =C8/C6*100 -> 1.2959717 | E8: =SUM(SUMIF(Баланс!$B:$B,12600,Баланс!$G:$G)/1000+SUMIF(Баланс!$B:$B,12100,Баланс!$G:$G)/1000+SUMIF(Баланс!$B:$B,12300,Баланс!$G:$G)/1000+SUMIF(Баланс!$B:$B,12400,Баланс!$G:$G)/1000+SUMIF(Баланс!$B:$B,12500,Баланс!$G:$G)/1000+SUMIF(Баланс!$B:$B,12700,Баланс!$G:$G)/1000+SUMIF(Баланс!$B:$B,12900,Баланс!$G:$G)/1000+SUMIF(Баланс!$B:$B,13000,Баланс!$G:$G)/1000+SUMIF(Баланс!$B:$B,13100,Баланс!$G:$G)/1000+SUMIF(Баланс!$B:$B,13200,Баланс!$G:$G)/1000+SUMIF(Баланс!$B:$B,13300,Баланс!$G:$G)/1000,0) -> 14360501 | F8: =E8/E6*100 -> 3.6904368 | G8: =SUM(E8-C8) -> 10320602
A9: в | B9: - узоқ муддатли ссудалар | C9: =SUM(SUMIF(Баланс!$B:$B,14300,Баланс!$C:$C)/1000+SUMIF(Баланс!$B:$B,14500,Баланс!$C:$C)/1000+SUMIF(Баланс!$B:$B,14700,Баланс!$C:$C)/1000+SUMIF(Баланс!$B:$B,14900,Баланс!$C:$C)/1000+SUMIF(Баланс!$B:$B,15000,Баланс!$C:$C)/1000+SUMIF(Баланс!$B:$B,15100,Баланс!$C:$C)/1000+SUMIF(Баланс!$B:$B,15200,Баланс!$C:$C)/1000+SUMIF(Баланс!$B:$B,15300,Баланс!$C:$C)/1000+SUMIF(Баланс!$B:$B,15400,Баланс!$C:$C)/1000+SUMIF(Баланс!$B:$B,15500,Баланс!$C:$C)/1000,0)+SUMIF(Баланс!$B:$B,14800,Баланс!$C:$C)/1000 -> 1.9159241e+08 | D9: =(C9+C32)/C6*100 -> -31.460595 | E9: =SUM(SUMIF(Баланс!$B:$B,14300,Баланс!$G:$G)/1000+SUMIF(Баланс!$B:$B,14500,Баланс!$G:$G)/1000+SUMIF(Баланс!$B:$B,14700,Баланс!$G:$G)/1000+SUMIF(Баланс!$B:$B,14900,Баланс!$G:$G)/1000+SUMIF(Баланс!$B:$B,15000,Баланс!$G:$G)/1000+SUMIF(Баланс!$B:$B,15100,Баланс!$G:$G)/1000+SUMIF(Баланс!$B:$B,15200,Баланс!$G:$G)/1000+SUMIF(Баланс!$B:$B,15300,Баланс!$G:$G)/1000+SUMIF(Баланс!$B:$B,15400,Баланс!$G:$G)/1000+SUMIF(Баланс!$B:$B,15500,Баланс!$G:$G)/1000,0)+SUMIF(Баланс!$B:$B,14800,Баланс!$G:$G)/1000 -> 2.4454243e+08 | F9: =(E9)/E6*100 -> 62.843797 | G9: =SUM(E9-C9) -> 52950024 | H9: =+(E9+E32)-(C9+C32) -> -49130271
A10: г | B10: - лизинг | C10: 0 | D10: =C10/C6*100 -> 0 | E10: 0 | F10: =E10/E6*100 -> 0 | G10: =SUM(E10-C10) -> 0
A11: д | B11: -Суд жараёнидаги кредитлар ва лизинг | C11: =SUM(SUMIF(Баланс!$B:$B,15700,Баланс!$C:$C)/1000) -> 59138.512 | D11: =+C11/C6*100 -> 0.018971225 | E11: =SUM(SUMIF(Баланс!$B:$B,15700,Баланс!$G:$G)/1000) -> 32804.978 | F11: =+E11/E6*100 -> 0.0084303953 | G11: =SUM(E11-C11) -> -26333.534
A12: е | B12: - сўндириш муддатигача сакланадиган карз кимматли когозларга килинган инвестициялар | C12: =SUM(SUMIF(Баланс!$B:$B,15900,Баланс!$C:$C)/1000,0) -> 0 | D12: =C12/C6*100 -> 0 | E12: =SUM(SUMIF(Баланс!$B:$B,15900,Баланс!$G:$G)/1000,0) -> 0 | F12: =E12/E6*100 -> 0 | G12: =SUM(E12-C12) -> 0
A13: ж | B13: - қўшма корхоналарга инвестиция | C13: =SUM(SUMIF(Баланс!$B:$B,15800,Баланс!$C:$C)/1000,0) -> 0 | D13: =C13/C6*100 -> 0 | E13: =SUM(SUMIF(Баланс!$B:$B,15800,Баланс!$G:$G)/1000,0) -> 0 | F13: =E13/E6*100 -> 0 | G13: =SUM(E13-C13) -> 0
A14: ё | B14: - банк филиалларига берилган молиявий ёрдам ва ресурслар | C14: =SUM(SUMIF(Баланс!$A:$A,16101,Баланс!$C:$C)/1000+SUMIF(Баланс!$A:$A,16102,Баланс!$C:$C)/1000,0) -> 1.1603598e+08 | D14: =C14/C6*100 -> 37.223539 | E14: =SUM(SUMIF(Баланс!$A:$A,16101,Баланс!$G:$G)/1000+SUMIF(Баланс!$A:$A,16102,Баланс!$G:$G)/1000,0) -> 1.3019166e+08 | F14: =E14/E6*100 -> 33.457336 | G14: =SUM(E14-C14) -> 14155682 | H14: =+E8+E9 -> 2.5890293e+08
A15: II. | B15: Даромад келтирмайдиган активлар | C15: =SUM(C16:C23) -> 52613863 | D15: =C15/C30*100 -> 14.440818 | E15: =SUM(E16:E23) -> 84017657 | F15: =E15/E30*100 -> 17.757273 | G15: =SUM(E15-C15) -> 31403794 | H15: =+H14/E14*100 -> 198.86292
A16: а | B16: - бош офисдан товар материал олиш учун ўтказилган маблағлар | C16: =SUM(SUMIF(Баланс!$A:$A,16104,Баланс!$C:$C)/1000+SUMIF(Баланс!$A:$A,16105,Баланс!$C:$C)/1000+SUMIF(Баланс!$A:$A,16107,Баланс!$C:$C)/1000+SUMIF(Баланс!$A:$A,16109,Баланс!$C:$C)/1000,0) -> 0 | D16: =C16/C15*100 -> 0 | E16: =SUM(SUMIF(Баланс!$A:$A,16104,Баланс!$G:$G)/1000+SUMIF(Баланс!$A:$A,16105,Баланс!$G:$G)/1000+SUMIF(Баланс!$A:$A,16107,Баланс!$G:$G)/1000+SUMIF(Баланс!$A:$A,16109,Баланс!$G:$G)/1000,0) -> 0 | F16: =E16/E15*100 -> 0 | G16: =SUM(E16-C16) -> 0
A17: б | B17: - ҳисобланган, лекин ундирилмаган фоизлар | C17: =SUM(SUMIF(Баланс!$B:$B,16300,Баланс!$C:$C)/1000+SUMIF(Баланс!$B:$B,16400,Баланс!$C:$C)/1000,0) -> 12488981 | D17: =C17/C15*100 -> 23.737054 | E17: =SUM(SUMIF(Баланс!$B:$B,16300,Баланс!$G:$G)/1000+SUMIF(Баланс!$B:$B,16400,Баланс!$G:$G)/1000,0) -> 21636700 | F17: =E17/E15*100 -> 25.752563 | G17: =SUM(E17-C17) -> 9147718.7
A18: в | B18: - банк мулклари | C18: =SUM(SUMIF(Баланс!$B:$B,16500,Баланс!$C:$C)/1000+SUMIF(Баланс!$B:$B,16600,Баланс!$C:$C)/1000+SUMIF(Баланс!$B:$B,16700,Баланс!$C:$C)/1000,0) -> 12169966 | D18: =C18/C15*100 -> 23.130721 | E18: =SUM(SUMIF(Баланс!$B:$B,16500,Баланс!$G:$G)/1000+SUMIF(Баланс!$B:$B,16600,Баланс!$G:$G)/1000+SUMIF(Баланс!$B:$B,16700,Баланс!$G:$G)/1000,0) -> 21895680 | F18: =E18/E15*100 -> 26.060808 | G18: =SUM(E18-C18) -> 9725714.5
A19: г | B19: - чет эл валюталарининг сўмдаги қиймати | C19: =SUM(SUMIF(Баланс!$B:$B,17100,Баланс!$C:$C)/1000,0) -> 2172324 | D19: =C19/C15*100 -> 4.1288054 | E19: =SUM(SUMIF(Баланс!$B:$B,17100,Баланс!$G:$G)/1000,0) -> 4997355.4 | F19: =E19/E15*100 -> 5.9479823 | G19: =SUM(E19-C19) -> 2825031.4
A20: д | B20: - транзит счетлар | C20: =SUM(SUMIF(Баланс!$B:$B,17300,Баланс!$C:$C)/1000,0)+SUM(SUMIF(Баланс!$B:$B,17400,Баланс!$C:$C)/1000,0) -> 605010.44 | D20: =C20/C15*100 -> 1.1499069 | E20: =SUM(SUMIF(Баланс!$B:$B,17300,Баланс!$G:$G)/1000,0)+SUM(SUMIF(Баланс!$B:$B,17400,Баланс!$G:$G)/1000,0) -> 494345.42 | F20: =E20/E15*100 -> 0.58838278 | G20: =SUM(E20-C20) -> -110665.02
A21: е | B21: - давлат ҳисоб рақамлари | C21: =SUM(SUMIF(Баланс!$B:$B,17500,Баланс!$C:$C)/1000,0)+SUM(SUMIF(Баланс!$B:$B,10700,Баланс!$C:$C)/1000,0)+SUM(SUMIF(Баланс!$B:$B,10800,Баланс!$C:$C)/1000,0) -> 0 | D21: =C21/C15*100 -> 0 | E21: =SUM(SUMIF(Баланс!$B:$B,17500,Баланс!$G:$G)/1000,0)+SUM(SUMIF(Баланс!$B:$B,10700,Баланс!$G:$G)/1000,0)+SUM(SUMIF(Баланс!$B:$B,10800,Баланс!$G:$G)/1000,0) -> 0 | F21: =E21/E15*100 -> 0 | G21: =SUM(E21-C21) -> 0
A22: ё | B22: - бошқа активлар | C22: =SUM(SUMIF(Баланс!$B:$B,19900,Баланс!$C:$C)/1000,0) -> 952064.3 | D22: =C22/C15*100 -> 1.8095313 | E22: =SUM(SUMIF(Баланс!$B:$B,19900,Баланс!$G:$G)/1000,0) -> 1019650.3 | F22: =E22/E15*100 -> 1.2136143 | G22: =SUM(E22-C22) -> 67586
A23: ж | B23: - юқори ликвидли активлар | C23: =SUM(C25:C29) -> 24225517 | D23: =C23/C15*100 -> 46.043982 | E23: =SUM(E25:E29) -> 33973926 | F23: =E23/E15*100 -> 40.43665 | G23: =SUM(G25:G28) -> 6425757.7
B24: шундан :
B25: - кассадаги нақд пуллар ва қимматбаҳо металлар | C25: =SUM(SUMIF(Баланс!$B:$B,10100,Баланс!$C:$C)/1000,0)-SUMIF(Баланс!$A:$A,10109,Баланс!$C:$C)/1000 -> 8367017.7 | D25: =C25/C23*100 -> 34.538035 | E25: =SUM(SUMIF(Баланс!$B:$B,10100,Баланс!$G:$G)/1000,0)-SUMIF(Баланс!$A:$A,10109,Баланс!$G:$G)/1000 -> 29391285 | F25: =E25/E23*100 -> 86.5113 | G25: =SUM(E25-C25) -> 21024267
B26: - йўлдаги пуллар | C26: =SUM(SUMIF(Баланс!$B:$B,10300,Баланс!$C:$C)/1000+SUMIF(Баланс!$B:$B,10500,Баланс!$C:$C)/1000+SUMIF(Баланс!$A:$A,10109,Баланс!$C:$C)/1000-SUMIF(Баланс!$A:$A,10309,Баланс!$C:$C)/1000,0) -> 1303745 | D26: =C26/C23*100 -> 5.3817013 | E26: =SUM(SUMIF(Баланс!$B:$B,10300,Баланс!$G:$G)/1000+SUMIF(Баланс!$B:$B,10500,Баланс!$G:$G)/1000,0)+SUMIF(Баланс!$A:$A,10109,Баланс!$G:$G)/1000-SUMIF(Баланс!$A:$A,10309,Баланс!$G:$G)/1000 -> 1235746.6 | F26: =E26/E23*100 -> 3.6373383 | G26: =SUM(E26-C26) -> -67998.385
B27: - мажбурий заҳира фондидаги маблағлар | C27: =SUM(SUMIF(Баланс!$A:$A,10309,Баланс!$C:$C)/1000,0) -> 0 | D27: =C27/C23*100 -> 0 | E27: =SUM(SUMIF(Баланс!$A:$A,10309,Баланс!$G:$G)/1000,0) -> 0 | F27: =E27/E23*100 -> 0 | G27: =SUM(E27-C27) -> 0
B28: - ягона вакиллик ҳисобварағидаги маблағлар | C28: =SUM(SUMIF(Баланс!$A:$A,16103,Баланс!$C:$C)/1000,0) -> 14530511 | D28: =C28/C23*100 -> 59.980189 | E28: =SUM(SUMIF(Баланс!$A:$A,16103,Баланс!$G:$G)/1000,0) -> 0 | F28: =E28/E23*100 -> 0 | G28: =SUM(E28-C28) -> -14530511
B29: -паластик картлардан амалга оширилган туловлар буйича бошка банклардан олинадиган маблаглар | C29: =SUM(SUMIF(Баланс!$A:$A,16113,Баланс!$C:$C)/1000,0)+SUM(SUMIF(Баланс!$A:$A,16111,Баланс!$C:$C)/1000,0) -> 24243.549 | D29: =+C29/C23*100 -> 0.10007443 | E29: =SUM(SUMIF(Баланс!$A:$A,16113,Баланс!$G:$G)/1000,0)+SUM(SUMIF(Баланс!$A:$A,16111,Баланс!$G:$G)/1000,0) -> 3346894.3 | F29: =+E29/E23*100 -> 9.8513616
B30: Жами активлар | C30: =C15+C6 -> 3.6434128e+08 | D30: =D15+D6 -> 20.4966 | E30: =E15+E6 -> 4.7314505e+08 | F30: =F15+F6 -> 100 | G30: =SUM(E30-C30) -> 1.0880377e+08
C31: =74677576742.35/1000 -> 74677577 | E31: =81401050229.17/1000 -> 81401050
C32: =+C31-C30 -> -2.8966371e+08 | E32: =+E31-E30 -> -3.91744e+08
B34: =""&(Шаблон!B1)&"нинг Ички аудит" -> АТ "Халқ банк"нинг Ички аудит
B35: департаменти бўлим бошлиғи: | F35: =Шаблон!B13 -> А.Ҳазратқулов
B37: =""&(Шаблон!B1)&" "&(Шаблон!B2)&"" -> АТ "Халқ банк" Фаргона вилояти
B38: =""&(Шаблон!B3)&" бошқарувчиси:" -> Бешариқ филиали бошқарувчиси: | F38: =Шаблон!B5 -> _____________
B40: Бош бухгалтери: | F40: =Шаблон!B8 -> _____________

Sheet 4.а-восита
L1: 4-жадвал
A2: =""&(Шаблон!B1)&"нинг "&(Шаблон!B2)&" вилоят "&(Шаблон!B3)&" филиали бўйича "&(Шаблон!B15)&" ҳолатига асосий воситалар ТАҲЛИЛИ" -> АТ "Халқ банк"нинг Фаргона вилояти вилоят Бешариқ филиали филиали бўйича 2024 йил 1 январ ҳолатига асосий воситалар ТАҲЛИЛИ
L3: (минг сўмда)
A4: Т\р | B4: Асосий воситалар ҳаракати | C4: Тугалланмаган қурилишлар | D4: Бино ва иншоат | E4: Ижарага олинган а/в | F4: Транспорт | G4: Мебел ва қурилма | H4: Номоддий активлар | I4: Терминаллар ва тулов карталари | J4: Ижарадаги асосий воситалар | K4: Омбордаги асосий воситалар | L4: Жами
A5: I | B5: Асосий воситалар
A6: а) | B6: =""&(Шаблон!B16)&" ҳолатига қолдиқ" -> 2023 йил 1 январ ҳолатига қолдиқ | C6: =SUM(SUMIF(Баланс!$A:$A,16505,Баланс!$C:$C)/1000,0) -> 0 | D6: =SUM(SUMIF(Баланс!$A:$A,16509,Баланс!$C:$C)/1000,0) -> 4016869.6 | E6: =SUM(SUMIF(Баланс!$A:$A,16515,Баланс!$C:$C)/1000,0) -> 0 | F6: =SUM(SUMIF(Баланс!$A:$A,16529,Баланс!$C:$C)/1000,0) -> 810919.33 | G6: =SUM(SUMIF(Баланс!$A:$A,16535,Баланс!$C:$C)/1000,0) -> 2748798.5 | H6: =SUM(SUMIF(Баланс!$A:$A,16601,Баланс!$C:$C)/1000,0) -> 0 | I6: =SUM(SUMIF(Баланс!$A:$A,16541,Баланс!$C:$C)/1000,0) -> 3208281.2 | J6: =SUM(SUMIF(Баланс!$A:$A,16549,Баланс!$C:$C)/1000,0) -> 0 | K6: =SUM(SUMIF(Баланс!$A:$A,16561,Баланс!$C:$C)/1000,0) -> 64039.594 | L6: =SUM(C6:K6) -> 10848908
A7: б) | B7: ҳисобдан чиқиши | C7: =SUM(C8:C13) -> 0 | D7: =SUM(D8:D13) -> 0 | E7: =SUM(E8:E13) -> 0 | F7: =SUM(F8:F13) -> 4274.9 | G7: =SUM(G8:G13) -> 0 | H7: =SUM(H8:H13) -> 0 | I7: =SUM(I8:I13) -> 0 | J7: =SUM(J8:J13) -> 0 | ... L7: =SUM(L8:L13) -> 103658.3
B8: ….қайта баҳолаш бўйича | L8: =SUM(D8:K8) -> 0
B9: ….балансдан чиқарилган | L9: =SUM(D9:K9) -> 0
B10: ….сотилган | F10: 4274.9 | L10: =SUM(D10:K10) -> 4274.9
B11: ….бошқа филиалга берилган | L11: =SUM(D11:K11) -> 0
B12: ….бошқа ҳисоб рақамга ўтказилган | K12: 99383.4 | L12: =SUM(D12:K12) -> 99383.4
B13: ….бошқа(нотўғри ўтказма-сторно) | L13: =SUM(D13:K13) -> 0
A14: в) | B14: кирими | C14: =SUM(C15:C18) -> 0 | E14: =SUM(E15:E18) -> 0 | F14: =SUM(F15:F18) -> 0 | G14: =SUM(G15:G18) -> 7699.3 | H14: =SUM(H15:H18) -> 0 | I14: =SUM(I15:I18) -> 91684.1 | J14: =SUM(J15:J18) -> 0 | K14: =SUM(K15:K18) -> 99383.4 | L14: =SUM(L15:L18) -> 198766.8
B15: ….қайта баҳолаш бўйича | L15: =SUM(D15:K15) -> 0
B16: ….сотиб олинган | G16: =1118.4+3610.9+2970 -> 7699.3 | I16: 91684.1 | K16: 99383.4 | L16: =SUM(D16:K16) -> 198766.8
B17: ….бошқа ҳисоб рақамдан ўтказилган | L17: =SUM(D17:K17) -> 0
B18: ….бошқа(нотўғри ўтказма-сторно) | L18: =SUM(D18:K18) -> 0
A19: г) | B19: =""&(Шаблон!B15)&" ҳолатига қолдиқ" -> 2024 йил 1 январ ҳолатига қолдиқ | C19: =SUM(C6+C14-C7) -> 0 | D19: =SUM(D6+D14-D7) -> 4016869.6 | E19: =SUM(E6+E14-E7) -> 0 | F19: =SUM(F6+F14-F7) -> 806644.43 | G19: =SUM(G6+G14-G7) -> 2756497.8 | H19: =SUM(H6+H14-H7) -> 0 | I19: =SUM(I6+I14-I7) -> 3299965.3 | J19: =SUM(J6+J14-J7) -> 0 | K19: =SUM(K6+K14-K7) -> 64039.594 | L19: =SUM(C19:K19) -> 10944017
A20: д) | B20: ўзгариш | C20: =C19-C6 -> 0 | D20: =D19-D6 -> 0 | E20: =E19-E6 -> 0 | F20: =F19-F6 -> -4274.9 | G20: =G19-G6 -> 7699.3 | H20: =H19-H6 -> 0 | I20: =I19-I6 -> 91684.1 | J20: =J19-J6 -> 0 | K20: =K19-K6 -> 0 | L20: =SUM(C20:K20) -> 95108.5
A21: II | B21: Аммортизация ажратмаси
A22: а) | B22: =""&(Шаблон!B16)&" ҳолатига қолдиқ" -> 2023 йил 1 январ ҳолатига қолдиқ | D22: =SUM(SUMIF(Баланс!$A:$A,16511,Баланс!$D:$D)/1000,0) -> 1023955.3 | E22: =SUM(SUMIF(Баланс!$A:$A,16519,Баланс!$D:$D)/1000,0) -> 0 | F22: =SUM(SUMIF(Баланс!$A:$A,16531,Баланс!$D:$D)/1000,0) -> 564853.11 | G22: =SUM(SUMIF(Баланс!$A:$A,16539,Баланс!$D:$D)/1000,0) -> 1551807.4 | H22: =SUM(SUMIF(Баланс!$A:$A,16605,Баланс!$D:$D)/1000,0) -> 0 | I22: =SUM(SUMIF(Баланс!$A:$A,16543,Баланс!$D:$D)/1000,0) -> 1063569.7 | J22: =SUM(SUMIF(Баланс!$A:$A,16551,Баланс!$D:$D)/1000,0) -> 0 | K22: 0 | L22: =SUM(D22:K22) -> 4204185.5
A23: б) | B23: =""&(Шаблон!B15)&" ҳолатига қолдиқ" -> 2024 йил 1 январ ҳолатига қолдиқ | D23: =SUM(SUMIF(Баланс!$A:$A,16511,Баланс!$H:$H)/1000,0) -> 1185560.3 | E23: =SUM(SUMIF(Баланс!$A:$A,16519,Баланс!$H:$H)/1000,0) -> 0 | F23: =SUM(SUMIF(Баланс!$A:$A,16531,Баланс!$H:$H)/1000,0) -> 655002.42 | G23: =SUM(SUMIF(Баланс!$A:$A,16539,Баланс!$H:$H)/1000,0) -> 2405110.9 | H23: =SUM(SUMIF(Баланс!$A:$A,16605,Баланс!$H:$H)/1000,0) -> 0 | I23: =SUM(SUMIF(Баланс!$A:$A,16543,Баланс!$H:$H)/1000,0) -> 3495483 | J23: =SUM(SUMIF(Баланс!$A:$A,16551,Баланс!$H:$H)/1000,0) -> 0 | K23: 0 | L23: =SUM(D23:K23) -> 7741156.7
A24: в) | B24: ўзгариш | D24: =D23-D22 -> 161605.06 | E24: =E23-E22 -> 0 | F24: =F23-F22 -> 90149.306 | G24: =G23-G22 -> 853303.47 | H24: =H23-H22 -> 0 | I24: =I23-I22 -> 2431913.3 | J24: =J23-J22 -> 0 | K24: =K23-K22 -> 0 | L24: =SUM(D24:K24) -> 3536971.2
A25: III | B25: Соф баланс қолдиғи
A26: а) | B26: =""&(Шаблон!B16)&" ҳолатига қолдиқ" -> 2023 йил 1 январ ҳолатига қолдиқ | D26: =D6-D22 -> 2992914.4 | E26: =E6-E22 -> 0 | F26: =F6-F22 -> 246066.22 | G26: =G6-G22 -> 1196991.1 | H26: =H6-H22 -> 0 | I26: =I6-I22 -> 2144711.5 | J26: =J6-J22 -> 0 | K26: =K6-K22 -> 64039.594 | L26: =SUM(D26:K26) -> 6644722.7
A27: б) | B27: =""&(Шаблон!B15)&" ҳолатига қолдиқ" -> 2024 йил 1 январ ҳолатига қолдиқ | D27: =D19-D23 -> 2831309.3 | E27: =E19-E23 -> 0 | F27: =F19-F23 -> 151642.01 | G27: =G19-G23 -> 351386.93 | H27: =H19-H23 -> 0 | I27: =I19-I23 -> -195517.76 | J27: =J19-J23 -> 0 | K27: =K19-K23 -> 64039.594 | L27: =SUM(D27:K27) -> 3202860.1
B30: =""&(Шаблон!B1)&"нинг Ички Аудит" -> АТ "Халқ банк"нинг Ички Аудит
B31: Департаменти бўлим бошлиғи: | H31: =+Шаблон!B13 -> А.Ҳазратқулов
B33: =""&(Шаблон!B1)&" "&(Шаблон!B2)&" вилояти" -> АТ "Халқ банк" Фаргона вилояти вилояти
B34: =""&(Шаблон!B3)&" филиал бошқарувчиси:" -> Бешариқ филиали филиал бошқарувчиси: | H34: =Шаблон!B5 -> _____________
B36: Бош бухгалтери: | H36: =Шаблон!B8 -> _____________

Sheet 9.мажбурият
G1: 9-жадвал
A2: =""&(Шаблон!B1&"нинг "&(Шаблон!B2)&" "&(Шаблон!B3)&" филиали бўйича "&(Шаблон!B15)&" ҳолатига мажбуриятлар ТАҲЛИЛИ") -> АТ "Халқ банк"нинг Фаргона вилояти Бешариқ филиали филиали бўйича 2024 йил 1 январ ҳолатига мажбуриятлар ТАҲЛИЛИ
G3: (минг сўмда)
A4: Т/Р | B4: Мажбуриятлар таркиби | C4: =""&(Шаблон!B16)&" ҳолатига" -> 2023 йил 1 январ ҳолатига | E4: =""&(Шаблон!B15)&" ҳолатига" -> 2024 йил 1 январ ҳолатига | G4: фарқи (+;-)
C6: Сумма | D6: Фоизи | E6: Сумма | F6: Фоизи
A7: I | B7: Талаб қилиб олингунча депозитлар | C7: =SUM(SUMIF(Баланс!$B:$B,20200,Баланс!$D:$D)/1000,0) -> 8765481 | D7: =SUM(C7/C26*100) -> 2.3400438 | E7: =SUM(SUMIF(Баланс!$B:$B,20200,Баланс!$H:$H)/1000,0) -> 12015427 | F7: =SUM(E7/E26*100) -> 2.9319325 | G7: =E7-C7 -> 3249946.4
A8: а) | B8: Шундан жисмоний шахсларнинг талаб қилиб олгунча депозитлари | C8: =SUM(SUMIF(Баланс!$A:$A,20206,Баланс!$D:$D)/1000,0) -> 20121.107 | D8: =SUM(C8/C7*100) -> 0.22954938 | E8: =SUM(SUMIF(Баланс!$A:$A,20206,Баланс!$H:$H)/1000,0) -> 30047.117 | F8: =SUM(E8/E7*100) -> 0.25007114 | G8: =E8-C8 -> 9926.0097
A9: II | B9: Жамғарма депозитлар | C9: =SUM(SUMIF(Баланс!$B:$B,20400,Баланс!$D:$D)/1000,0) -> 12715184 | D9: =SUM(C9/C26*100) -> 3.3944614 | E9: =SUM(SUMIF(Баланс!$B:$B,20400,Баланс!$H:$H)/1000,0) -> 10711867 | F9: =SUM(E9/E26*100) -> 2.6138455 | G9: =E9-C9 -> -2003316.7
A10: а) | B10: Шундан жисмоний шахсларнинг жамғарма депозитлари | C10: =SUM(SUMIF(Баланс!$A:$A,20406,Баланс!$D:$D)/1000,0) -> 12715184 | D10: =C10/C9*100 -> 100 | E10: =SUM(SUMIF(Баланс!$A:$A,20406,Баланс!$H:$H)/1000,0) -> 10711867 | F10: =E10/E9*100 -> 100 | G10: =E10-C10 -> -2003316.7
A11: III | B11: Муддатли депозитлар | C11: =SUM(SUMIF(Баланс!$B:$B,20600,Баланс!$D:$D)/1000,0) -> 37405544 | D11: =SUM(C11/C26*100) -> 9.9858311 | E11: =SUM(SUMIF(Баланс!$B:$B,20600,Баланс!$H:$H)/1000,0) -> 34323238 | F11: =SUM(E11/E26*100) -> 8.3753505 | G11: =E11-C11 -> -3082305.5
A12: а) | B12: Шундан жисмоний шахсларнинг муддатли депозитлари | C12: =SUM(SUMIF(Баланс!$A:$A,20606,Баланс!$D:$D)/1000,0) -> 14780544 | D12: =C12/C11*100 -> 39.514313 | E12: =SUM(SUMIF(Баланс!$A:$A,20606,Баланс!$H:$H)/1000,0) -> 13498238 | F12: =E12/E11*100 -> 39.32682 | G12: =E12-C12 -> -1282305.5
A13: IV | B13: Бошқа банкларга тўланиши лозим бўлган маблағлар | C13: =SUM(SUMIF(Баланс!$B:$B,21000,Баланс!$D:$D)/1000,0) -> 205551.75 | D13: =SUM(C13/C26*100) -> 0.054874354 | E13: =SUM(SUMIF(Баланс!$B:$B,21000,Баланс!$H:$H)/1000,0) -> 805969.81 | F13: =SUM(E13/E26*100) -> 0.19666791 | G13: =E13-C13 -> 600418.06
A14: V | B14: Олинган қисқа ва узоқ муддатли ссудалар | C14: =SUM(SUMIF(Баланс!$B:$B,21600,Баланс!$D:$D)/1000+SUMIF(Баланс!$B:$B,22000,Баланс!$D:$D)/1000,0) -> 13342 | D14: =SUM(C14/C26*100) -> 0.0035617971 | E14: =SUM(SUMIF(Баланс!$B:$B,21600,Баланс!$H:$H)/1000+SUMIF(Баланс!$B:$B,22000,Баланс!$H:$H)/1000,0) -> 0 | F14: =SUM(E14/E26*100) -> 0 | G14: =E14-C14 -> -13342
A15: VI | B15: Лизинг тўловлари бўйича мажбуриятлар | C15: =SUM(SUMIF(Баланс!$B:$B,22100,Баланс!$D:$D)/1000,0) -> 0 | D15: =SUM(C15/C26*100) -> 0 | E15: =SUM(SUMIF(Баланс!$B:$B,22100,Баланс!$H:$H)/1000,0) -> 0 | F15: =SUM(E15/E26*100) -> 0 | G15: =E15-C15 -> 0
A16: VII | B16: Бошқа банк(филиаллар)га тўланган маблағлар | C16: =SUM(SUMIF(Баланс!$B:$B,22200,Баланс!$D:$D)/1000,0) -> 1.7824803e+08 | D16: =SUM(C16/C26*100) -> 47.585318 | E16: =SUM(SUMIF(Баланс!$B:$B,22200,Баланс!$H:$H)/1000,0) -> 1.9170214e+08 | F16: =SUM(E16/E26*100) -> 46.778006 | G16: =E16-C16 -> 13454114
A17: VIII | B17: Мажбуриятлар бўйича ҳисобланган фоизлар | C17: =SUM(SUMIF(Баланс!$B:$B,22400,Баланс!$D:$D)/1000,0) -> 465238.6 | D17: =SUM(C17/C26*100) -> 0.12420068 | E17: =SUM(SUMIF(Баланс!$B:$B,22400,Баланс!$H:$H)/1000,0) -> 308921.65 | F17: =SUM(E17/E26*100) -> 0.075381206 | G17: =E17-C17 -> -156316.96
A18: IX | B18: Тўлаш учун ҳисобланган солиқлар | C18: =SUM(SUMIF(Баланс!$B:$B,22500,Баланс!$D:$D)/1000,0) -> 257420.33 | D18: =SUM(C18/C26*100) -> 0.068721256 | E18: =SUM(SUMIF(Баланс!$B:$B,22500,Баланс!$H:$H)/1000,0) -> 443937.65 | F18: =SUM(E18/E26*100) -> 0.108327 | G18: =E18-C18 -> 186517.32 | J18: =+E9+E11+E16+E19 -> 3.9449059e+08 | K18: =+J18/E26*100 -> 96.261226
A19: X | B19: Мижозларнинг бошқа депозитлари | C19: =SUM(SUMIF(Баланс!$B:$B,22600,Баланс!$D:$D)/1000,0) -> 1.3462847e+08 | D19: =SUM(C19/C26*100) -> 35.940586 | E19: =SUM(SUMIF(Баланс!$B:$B,22600,Баланс!$H:$H)/1000,0) -> 1.5775334e+08 | F19: =SUM(E19/E26*100) -> 38.494024 | G19: =E19-C19 -> 23124871 | J19: =+E16+E19 -> 3.4945549e+08 | K19: =+J19/J18*100 -> 88.583985
A20: XI | B20: Клиринг трансакциялари | C20: =SUM(SUMIF(Баланс!$B:$B,23200,Баланс!$D:$D)/1000,0) -> 0 | D20: =SUM(C20/C26*100) -> 0 | E20: =SUM(SUMIF(Баланс!$B:$B,23200,Баланс!$H:$H)/1000,0) -> 0 | F20: =SUM(E20/E26*100) -> 0 | G20: =E20-C20 -> 0
A21: XII | B21: Ҳукуматга тегишли даромад ва бошқа тушумлар | C21: =SUM(SUMIF(Баланс!$B:$B,23400,Баланс!$D:$D)/1000,0) -> 0 | D21: =SUM(C21/C26*100) -> 0 | E21: =SUM(SUMIF(Баланс!$B:$B,23400,Баланс!$H:$H)/1000,0) -> 0 | F21: =SUM(E21/E26*100) -> 0 | G21: =E21-C21 -> 0
A22: XIII | B22: Мижозларнинг пластик карталарига ўтказилиши лозим бўлган маблағлари | C22: =SUM(SUMIF(Баланс!$B:$B,23100,Баланс!$D:$D)/1000,0) -> 10553.727 | D22: =SUM(C22/C26*100) -> 0.0028174363 | E22: =SUM(SUMIF(Баланс!$B:$B,23100,Баланс!$H:$H)/1000,0) -> 35112.843 | F22: =SUM(E22/E26*100) -> 0.0085680252 | G22: =E22-C22 -> 24559.116
A23: XIV | B23: Хўжалик юритувчи субъектларнинг ва банкнинг транзит ҳисоб рақамларига мижозларнинг пластик карталардан келиб тушган маблағлари | C23: =SUM(SUMIF(Баланс!$B:$B,23500,Баланс!$D:$D)/1000,0) -> 450087.01 | D23: =SUM(C23/C26*100) -> 0.12015579 | E23: =SUM(SUMIF(Баланс!$B:$B,23500,Баланс!$H:$H)/1000,0) -> 410027.19 | F23: =SUM(E23/E26*100) -> 0.10005237 | G23: =E23-C23 -> -40059.816
A24: XV | B24: Чиқарилган жамғарма сертификатлари | C24: =SUM(SUMIF(Баланс!$B:$B,23600,Баланс!$D:$D)/1000,0)+SUM(SUMIF(Баланс!$B:$B,23700,Баланс!$D:$D)/1000,0)+SUM(SUMIF(Баланс!$B:$B,22300,Баланс!$D:$D)/1000,0) -> 0 | D24: =SUM(C24/C26*100) -> 0 | E24: =SUM(SUMIF(Баланс!$B:$B,23600,Баланс!$H:$H)/1000,0)+SUM(SUMIF(Баланс!$B:$B,23700,Баланс!$H:$H)/1000,0)+SUM(SUMIF(Баланс!$B:$B,22300,Баланс!$H:$H)/1000,0) -> 0 | F24: =SUM(E24/E26*100) -> 0 | G24: =E24-C24 -> 0
A25: XVI | B25: Бошқа мажбуриятлар | C25: =SUM(SUMIF(Баланс!$B:$B,29800,Баланс!$D:$D)/1000+SUMIF(Баланс!$B:$B,22800,Баланс!$D:$D)/1000,0) -> 1421283.2 | D25: =SUM(C25/C26*100) -> 0.37942756 | E25: =SUM(SUMIF(Баланс!$B:$B,29800,Баланс!$H:$H)/1000+SUMIF(Баланс!$B:$B,22800,Баланс!$H:$H)/1000,0) -> 1302569.2 | F25: =SUM(E25/E26*100) -> 0.31784511 | G25: =E25-C25 -> -118714.08
B26: Жами мажбуриятлар | C26: =C7+C9+C11+C14+C15+C16+C17+C18+C19+C20+C21+C22+C23+C24+C25+C13 -> 3.7458619e+08 | D26: =D7+D9+D11+D14+D15+D16+D17+D18+D19+D20+D21+D22+D23+D24+D25+D13 -> 100 | E26: =E7+E9+E11+E14+E15+E16+E17+E18+E19+E20+E21+E22+E23+E24+E25+E13 -> 4.0981256e+08 | F26: =F7+F9+F11+F14+F15+F16+F17+F18+F19+F20+F21+F22+F23+F24+F25+F13 -> 100 | G26: =G7+G9+G11+G14+G15+G16+G17+G18+G19+G20+G21+G22+G23+G24+G25+G13 -> 35226371
C27: =117279009877.36/1000 -> 1.1727901e+08 | E27: =128851614609.27/1000 -> 1.2885161e+08
B28: =""&(Шаблон!B1)&"нинг Ички аудит" -> АТ "Халқ банк"нинг Ички аудит | C28: =+C26-C27 -> 2.5730718e+08 | E28: =+E26-E27 -> 2.8096094e+08
B29: департаменти бош мутахассиси: | F29: =Шаблон!B13 -> А.Ҳазратқулов
B31: =""&(Шаблон!B1)&" "&(Шаблон!B2)&"" -> АТ "Халқ банк" Фаргона вилояти
B32: =""&(Шаблон!B3)&" бошқарувчиси:" -> Бешариқ филиали бошқарувчиси: | F32: =Шаблон!B5 -> _____________
B34: Бош бухгалтери: | F34: =Шаблон!B8 -> _____________

Sheet 15.капитал
H1: 15-жадвал
A2: =""&(Шаблон!B1)&"нинг "&(Шаблон!B2)&""&(Шаблон!B3)&" филиали капиталининг "&(Шаблон!B15)&" ҳолатига ТАҲЛИЛИ" -> АТ "Халқ банк"нинг Фаргона вилоятиБешариқ филиали филиали капиталининг 2024 йил 1 январ ҳолатига ТАҲЛИЛИ
H3: (минг сўмда)
A4: Т/Р | B4: Капитал таркиби | C4: =""&(Шаблон!B16)&" ҳолатига" -> 2023 йил 1 январ ҳолатига | E4: =""&(Шаблон!B15)&" ҳолатига" -> 2024 йил 1 январ ҳолатига | G4: фарқи (+;-) | H4: Изоҳ
C5: сумма | D5: фоизи | E5: сумма | F5: фоизи
A6: А | B6: Б | C6: 1 | D6: 2 | E6: 3 | F6: 4 | G6: 5 | H6: 6
A7: 1 | B7: Акционерлик капитали | C7: =SUM(SUMIF(Баланс!$B:$B,30300,Баланс!$D:$D)/1000,0) -> 0 | D7: =C7/C11*100 -> 0 | E7: =SUM(SUMIF(Баланс!$B:$B,30300,Баланс!$H:$H)/1000,0) -> 0 | F7: =E7/E11*100 -> 0 | G7: =SUM(E7-C7) -> 0
A8: =A7+1 -> 2 | B8: Қўшимча капитал | C8: =SUM(SUMIF(Баланс!$B:$B,30600,Баланс!$D:$D)/1000,0) -> 0 | D8: =C8/C11*100 -> 0 | E8: =SUM(SUMIF(Баланс!$B:$B,30600,Баланс!$H:$H)/1000,0) -> 0 | F8: =E8/E11*100 -> 0 | G8: =SUM(E8-C8) -> 0
A9: =A8+1 -> 3 | B9: Заҳира капитали | C9: =SUM(SUMIF(Баланс!$B:$B,30900,Баланс!$D:$D)/1000,0) -> 149894.13 | D9: =C9/C11*100 -> 0.76566198 | E9: =SUM(SUMIF(Баланс!$B:$B,30900,Баланс!$H:$H)/1000,0) -> 139434.02 | F9: =E9/E11*100 -> 0.54821807 | G9: =SUM(E9-C9) -> -10460.115
A10: =A9+1 -> 4 | B10: Тақсимланмаган фойда | C10: =SUM(SUMIF(Баланс!$B:$B,31200,Баланс!$D:$D)/1000,0) -> 19427170 | D10: =C10/C11*100 -> 99.234338 | E10: =SUM(SUMIF(Баланс!$B:$B,31200,Баланс!$H:$H)/1000,0) -> 25294609 | F10: =E10/E11*100 -> 99.451782 | G10: =SUM(E10-C10) -> 5867439.1
B11: Жами капитал | C11: =SUM(C7:C10) -> 19577064 | D11: =SUM(D7:D10) -> 100 | E11: =SUM(E7:E10) -> 25434043 | F11: =SUM(F7:F10) -> 100 | G11: =SUM(E11-C11) -> 5856978.9 | H11: х
E12: =+E11+'1.активлар'!E30 -> 4.985791e+08
B14: =""&(Шаблон!B1)&"нинг Ички аудит" -> АТ "Халқ банк"нинг Ички аудит
B15: департаменти бош мутахассиси: | G15: =Шаблон!B13 -> А.Ҳазратқулов
B17: =""&(Шаблон!B1)&" "&(Шаблон!B2)&"" -> АТ "Халқ банк" Фаргона вилояти
B18: =""&(Шаблон!B3)&" бошқарувчиси:" -> Бешариқ филиали бошқарувчиси: | G18: =Шаблон!B5 -> _____________
B20: Бош бухгалтери: | G20: =Шаблон!B8 -> _____________

Sheet 17.смета
I1: 17-жадвал
A2: =""&(Шаблон!B1)&"нинг "&(Шаблон!B2)&""&(Шаблон!B3)&" филиали томонидан олинган даромад ва қилинган харажатлар таҳлили, ҳамда сметасига амал қилиниши тўғрисида "&(Шаблон!B15)&" ҳолатига" -> АТ "Халқ банк"нинг Фаргона вилоятиБешариқ филиали филиали томонидан олинган даромад ва қилинган харажатлар таҳлили, ҳамда сметасига амал қилиниши тўғрисида 2024 йил 1 январ ҳолатига
C3: М А Ъ Л У М О Т
I4: (минг сўмда)
A5: Т/Р | B5: Даромад ва харажатлар таркиби | C5: =""&(Шаблон!B16)&" ҳолатига" -> 2023 йил 1 январ ҳолатига | E5: =""&(Шаблон!B15)&" ҳолатига" -> 2024 йил 1 январ ҳолатига | G5: Ўтган йилга нисбатан фарқи (+;-) | H5: =""&(Шаблон!B15)&" ҳолатига смета бўйича" -> 2024 йил 1 январ ҳолатига смета бўйича | I5: Сметага нисбатан фарқи (+;-)
C6: Сумма | D6: Фоизи | E6: Сумма | F6: Фоизи
A7: A | B7: Б | C7: 1 | D7: 2 | E7: 3 | F7: 4 | G7: 5 | H7: 6 | I7: 7
A8: 1 | B8: Фоизли даромадлар | C8: =N75 -> 8358260.3 | D8: =C8/C10*100 -> 51.073876 | E8: =O75 -> 9751091.3 | F8: =E8/E10*100 -> 61.377514 | G8: =E8-C8 -> 1392831 | H8: 0 | I8: =E8-H8 -> 9751091.3 | K8: =1371202757.93/1000 -> 1371202.8 | L8: =+K8/E8*100 -> 14.062044 | M8: =+E8-K8 -> 8379888.6
A9: 2 | B9: Фоизсиз даромадлар | C9: =Q75 -> 8006779.7 | D9: =C9/C10*100 -> 48.926124 | E9: =R75 -> 6135983.1 | F9: =E9/E10*100 -> 38.622486 | G9: =E9-C9 -> -1870796.6 | H9: 0 | I9: =E9-H9 -> 6135983.1
B10: Жами даромад | C10: =C8+C9 -> 16365040 | D10: =D8+D9 -> 100 | E10: =E8+E9 -> 15887074 | F10: =F8+F9 -> 100 | G10: =G8+G9 -> -477965.53 | H10: =H8+H9 -> 0 | I10: =I8+I9 -> 15887074 | K10: =+K8 -> 1371202.8 | L10: =+K10/E10*100 -> 8.630933 | M10: =+E10-K10 -> 14515872
A11: 3 | B11: Фоизли харажатлар | C11: =T75 -> 5246960.4 | D11: =C11/C24*100 -> 35.898816 | E11: =U75 -> 5927005.9 | F11: =E11/E24*100 -> 37.649809 | G11: =E11-C11 -> 680045.46 | H11: 0 | I11: =E11-H11 -> 5927005.9 | K11: =1371203397.23/1000 -> 1371203.4 | L11: =+K11/E11*100 -> 23.134841
A12: 4 | B12: Фоизсиз харажатлар | C12: =W75 -> 75764.996 | D12: =C12/C24*100 -> 0.51837129 | E12: =X75 -> 780288 | F12: =E12/E24*100 -> 4.9565826 | G12: =E12-C12 -> 704523 | H12: 0 | I12: =E12-H12 -> 780288
A13: 5 | B13: Операцион харажатлар | C13: =SUM(C15:C21) -> 3683732.1 | D13: =C13/C24*100 -> 25.203472 | E13: =SUM(E15:E21) -> 7184701.5 | F13: =E13/E24*100 -> 45.639003 | G13: =SUM(G15:G21) -> 3500969.4 | H13: =SUM(H15:H21) -> 0 | I13: =E13-H13 -> 7184701.5
B14: Шундан:
A15: а | B15: Иш хақи | C15: =SUM(SUMIF(Баланс!$B:$B,56100,Баланс!$C:$C)/1000,0) -> 2518462.8 | D15: =C15/C13*100 -> 68.367154 | E15: =SUM(SUMIF(Баланс!$B:$B,56100,Баланс!$G:$G)/1000,0) -> 4932721.4 | F15: =E15/E13*100 -> 68.655899 | G15: =E15-C15 -> 2414258.5 | H15: 0 | I15: =E15-H15 -> 4932721.4
A16: б | B16: Ижара ва сақлаш харажати | C16: =SUM(SUMIF(Баланс!$B:$B,56200,Баланс!$C:$C)/1000,0) -> 420490.75 | D16: =C16/C13*100 -> 11.414803 | E16: =SUM(SUMIF(Баланс!$B:$B,56200,Баланс!$G:$G)/1000,0) -> 1249884.5 | F16: =E16/E13*100 -> 17.396471 | G16: =E16-C16 -> 829393.77 | H16: 0 | I16: =E16-H16 -> 1249884.5
A17: в | B17: Транспорт ва сафар харажатлари | C17: =SUM(SUMIF(Баланс!$B:$B,56300,Баланс!$C:$C)/1000,0) -> 67783.48 | D17: =C17/C13*100 -> 1.8400763 | E17: =SUM(SUMIF(Баланс!$B:$B,56300,Баланс!$G:$G)/1000,0) -> 155556.96 | F17: =E17/E13*100 -> 2.1651137 | G17: =E17-C17 -> 87773.478 | H17: 0 | I17: =E17-H17 -> 155556.96
A18: г | B18: Маъмурий харажатлар | C18: =SUM(SUMIF(Баланс!$B:$B,56400,Баланс!$C:$C)/1000,0) -> 273379.92 | D18: =C18/C13*100 -> 7.4212759 | E18: =SUM(SUMIF(Баланс!$B:$B,56400,Баланс!$G:$G)/1000,0) -> 140311.78 | F18: =E18/E13*100 -> 1.9529243 | G18: =E18-C18 -> -133068.15 | H18: 0 | I18: =E18-H18 -> 140311.78
A19: д | B19: Тақдимот ва хайрия | C19: =SUM(SUMIF(Баланс!$B:$B,56500,Баланс!$C:$C)/1000,0) -> 0 | D19: =C19/C13*100 -> 0 | E19: =SUM(SUMIF(Баланс!$B:$B,56500,Баланс!$G:$G)/1000,0) -> 0 | F19: =E19/E13*100 -> 0 | G19: =E19-C19 -> 0 | H19: 0 | I19: =E19-H19 -> 0
A20: е | B20: Эскириш харажатлари | C20: =SUM(SUMIF(Баланс!$B:$B,56600,Баланс!$C:$C)/1000,0) -> 381650.81 | D20: =C20/C13*100 -> 10.360439 | E20: =SUM(SUMIF(Баланс!$B:$B,56600,Баланс!$G:$G)/1000,0) -> 593218.78 | F20: =E20/E13*100 -> 8.2566935 | G20: =E20-C20 -> 211567.97 | H20: 0 | I20: =E20-H20 -> 593218.78
A21: ё | B21: Суғурта, солиқ ва бошқа хар. | C21: =SUM(SUMIF(Баланс!$B:$B,56700,Баланс!$C:$C)/1000,0) -> 21964.329 | D21: =C21/C13*100 -> 0.59625206 | E21: =SUM(SUMIF(Баланс!$B:$B,56700,Баланс!$G:$G)/1000,0) -> 113008.09 | F21: =E21/E13*100 -> 1.5728989 | G21: =E21-C21 -> 91043.761 | H21: 0 | I21: =E21-H21 -> 113008.09
A22: 6 | B22: Келгуси зарарларни баҳолаш | C22: =SUM(SUMIF(Баланс!$B:$B,56800,Баланс!$C:$C)/1000,0) -> 5609513.3 | D22: =C22/C24*100 -> 38.379341 | E22: =SUM(SUMIF(Баланс!$B:$B,56800,Баланс!$G:$G)/1000,0) -> 1850464 | F22: =E22/E24*100 -> 11.754606 | G22: =E22-C22 -> -3759049.3 | H22: 0 | I22: =E22-H22 -> 1850464
A23: 7 | B23: Даромад солиғи | C23: =SUM(SUMIF(Баланс!$B:$B,56900,Баланс!$C:$C)/1000,0) -> 0 | D23: =C23/C24*100 -> 0 | E23: =SUM(SUMIF(Баланс!$B:$B,56900,Баланс!$G:$G)/1000,0) -> 0 | F23: =E23/E24*100 -> 0 | G23: =E23-C23 -> 0 | H23: 0 | I23: =E23-H23 -> 0
B24: Жами харажатлар | C24: =C11+C12+C13+C23+C22 -> 14615971 | D24: =D13+D12+D11+D22+D23 -> 100 | E24: =E11+E12+E13+E23+E22 -> 15742459 | F24: =F13+F12+F11+F22+F23 -> 100 | G24: =G11+G12+G13+G23+G22 -> 1126488.5 | H24: =H13+H12+H11+H22+H23 -> 0 | I24: =SUM(I11:I13)+I22+I23 -> 15742459 | K24: 19211519
B25: Фойда | C25: =C10-C24 -> 1749069.2 | D25: х | E25: =E10-E24 -> 144615.13 | F25: х | G25: =E25-C25 -> -1604454.1 | H25: =+H10-H24 -> 0 | I25: =I10-I24 -> 144615.13 | K25: =+K24-C10 -> 2846479.3
B26: Ҳисобланган, лекин ундирилмаган фоиз ва хизматлар | C26: =SUM(SUMIF(Баланс!$B:$B,16300,Баланс!$C:$C)/1000+SUMIF(Баланс!$B:$B,16400,Баланс!$C:$C)/1000,0) -> 12488981 | D26: х | E26: =SUM(SUMIF(Баланс!$B:$B,16300,Баланс!$G:$G)/1000+SUMIF(Баланс!$B:$B,16400,Баланс!$G:$G)/1000,0) -> 21636700 | F26: =E26/E27*100 -> -100.67288 | G26: =E26-C26 -> 9147718.7 | H26: 0 | I26: =H26-E26 -> -21636700
B27: Реал соф фойда | C27: =C25-C26 -> -10739912 | D27: =C27/C25*100 -> -614.03583 | E27: =E25-E26 -> -21492085 | F27: =E27/E25*100 -> -14861.574 | G27: =E27-C27 -> -10752173 | H27: =H25-H26 -> 0 | I27: =E27-H27 -> -21492085
B28: Харажатнинг даромаддаги улуши | C28: =C24/C10*100 -> 89.31216 | D28: =SUM(D26:D27) -> -614.03583 | E28: =E24/E10*100 -> 99.089731 | F28: =SUM(F26:F27) -> -14962.246 | G28: =G24/G10*100 -> -235.68405 | H28: =H24/H10*100 -> #DIV/0! | I28: =+I27/E27*100 -> 100
B29: НПС | C29: =97156801.41/1000 -> 97156.801 | E29: =+K8 -> 1371202.8
C30: =+C27-C29 -> -10837069 | E30: =+K11 -> 1371203.4
E31: =+E25-E29+E30 -> 144615.77
E32: =+E31-E26 -> -21492084
C33: 11674206 | E33: =+E25-E26 -> -21492085
B34: =""&(Шаблон!B1)&"нинг Самарқанд вилоят филиали" -> АТ "Халқ банк"нинг Самарқанд вилоят филиали | C34: =+C33-C24 -> -2941765.2 | E34: =+E10-E24 -> 144615.13
B35: Якуний назорат бўлим бош мутахассиси: | C35: =+C24/C10*100 -> 89.31216 | E35: =+E24/E10*100 -> 99.089731 | F35: =Шаблон!B13 -> А.Ҳазратқулов
B37: =""&(Шаблон!B1)&" "&(Шаблон!B2)&"" -> АТ "Халқ банк" Фаргона вилояти
B38: =""&(Шаблон!B3)&" филиал бошқарувчиси:" -> Бешариқ филиали филиал бошқарувчиси: | F38: =Шаблон!B5 -> _____________
B40: Бош бухгалтери: | F40: =Шаблон!B8 -> _____________
M42: Фоизли даромадлар | P42: Фоизсиз даромадлар | S42: Фоизли харажатлар | V42: Фоизсиз харажатлар
M43: 40200 | N43: =SUM(SUMIF(Баланс!$B:$B,M43,Баланс!$D:$D)/1000,0) -> 0 | O43: =SUM(SUMIF(Баланс!$B:$B,M43,Баланс!$H:$H)/1000,0) -> 0 | P43: 45200 | Q43: =SUM(SUMIF(Баланс!$B:$B,P43,Баланс!$D:$D)/1000,0) -> 1138018.1 | R43: =SUM(SUMIF(Баланс!$B:$B,P43,Баланс!$H:$H)/1000,0) -> 2364709.9 | S43: 50100 | T43: =SUM(SUMIF(Баланс!$B:$B,S43,Баланс!$C:$C)/1000,0) -> 0 | U43: =SUM(SUMIF(Баланс!$B:$B,S43,Баланс!$G:$G)/1000,0) -> 0 | V43: 55100 | W43: =SUM(SUMIF(Баланс!$B:$B,V43,Баланс!$C:$C)/1000,0) -> 56173.453 | X43: =ROUND(SUMIF(Баланс!$B:$B,V43,Баланс!$G:$G)/1000,0) -> 264575
M44: 40400 | N44: =SUM(SUMIF(Баланс!$B:$B,M44,Баланс!$D:$D)/1000,0) -> 0 | O44: =SUM(SUMIF(Баланс!$B:$B,M44,Баланс!$H:$H)/1000,0) -> 0 | P44: 45400 | Q44: =SUM(SUMIF(Баланс!$B:$B,P44,Баланс!$D:$D)/1000,0) -> 392225.58 | R44: =SUM(SUMIF(Баланс!$B:$B,P44,Баланс!$H:$H)/1000,0) -> 1072503 | S44: 50600 | T44: =SUM(SUMIF(Баланс!$B:$B,S44,Баланс!$C:$C)/1000,0) -> 503195.54 | U44: =SUM(SUMIF(Баланс!$B:$B,S44,Баланс!$G:$G)/1000,0) -> 430572.98 | V44: 55300 | W44: =SUM(SUMIF(Баланс!$B:$B,V44,Баланс!$C:$C)/1000,0) -> 16931.417 | X44: =ROUND(SUMIF(Баланс!$B:$B,V44,Баланс!$G:$G)/1000,0) -> 494087
M45: 40600 | N45: =SUM(SUMIF(Баланс!$B:$B,M45,Баланс!$D:$D)/1000,0) -> 0 | O45: =SUM(SUMIF(Баланс!$B:$B,M45,Баланс!$H:$H)/1000,0) -> 0 | P45: 45600 | Q45: =SUM(SUMIF(Баланс!$B:$B,P45,Баланс!$D:$D)/1000,0) -> 0 | R45: =SUM(SUMIF(Баланс!$B:$B,P45,Баланс!$H:$H)/1000,0) -> 0 | S45: 51100 | T45: =SUM(SUMIF(Баланс!$B:$B,S45,Баланс!$C:$C)/1000,0) -> 1687138.7 | U45: =SUM(SUMIF(Баланс!$B:$B,S45,Баланс!$G:$G)/1000,0) -> 1632087.7 | V45: 55600 | W45: =SUM(SUMIF(Баланс!$B:$B,V45,Баланс!$C:$C)/1000,0) -> 0 | X45: =ROUND(SUMIF(Баланс!$B:$B,V45,Баланс!$G:$G)/1000,0) -> 0
M46: 40700 | N46: =SUM(SUMIF(Баланс!$B:$B,M46,Баланс!$D:$D)/1000,0) -> 0 | O46: =SUM(SUMIF(Баланс!$B:$B,M46,Баланс!$H:$H)/1000,0) -> 0 | P46: 45700 | Q46: =SUM(SUMIF(Баланс!$B:$B,P46,Баланс!$D:$D)/1000,0) -> 0 | R46: =SUM(SUMIF(Баланс!$B:$B,P46,Баланс!$H:$H)/1000,0) -> 0 | S46: 51600 | T46: =SUM(SUMIF(Баланс!$B:$B,S46,Баланс!$C:$C)/1000,0) -> 0 | U46: =SUM(SUMIF(Баланс!$B:$B,S46,Баланс!$G:$G)/1000,0) -> 0 | V46: 55700 | W46: =SUM(SUMIF(Баланс!$B:$B,V46,Баланс!$C:$C)/1000,0) -> 0 | X46: =ROUND(SUMIF(Баланс!$B:$B,V46,Баланс!$G:$G)/1000,0) -> 0
M47: 40800 | N47: =SUM(SUMIF(Баланс!$B:$B,M47,Баланс!$D:$D)/1000,0) -> 0 | O47: =SUM(SUMIF(Баланс!$B:$B,M47,Баланс!$H:$H)/1000,0) -> 0 | P47: 45800 | Q47: =SUM(SUMIF(Баланс!$B:$B,P47,Баланс!$D:$D)/1000,0) -> 0 | R47: =SUM(SUMIF(Баланс!$B:$B,P47,Баланс!$H:$H)/1000,0) -> 0 | S47: 52100 | T47: =SUM(SUMIF(Баланс!$B:$B,S47,Баланс!$C:$C)/1000,0) -> 0 | U47: =SUM(SUMIF(Баланс!$B:$B,S47,Баланс!$G:$G)/1000,0) -> 0 | V47: 55800 | W47: =SUM(SUMIF(Баланс!$B:$B,V47,Баланс!$C:$C)/1000,0) -> 0 | X47: =ROUND(SUMIF(Баланс!$B:$B,V47,Баланс!$G:$G)/1000,0) -> 0
M48: 41000 | N48: =SUM(SUMIF(Баланс!$B:$B,M48,Баланс!$D:$D)/1000,0) -> 0 | O48: =SUM(SUMIF(Баланс!$B:$B,M48,Баланс!$H:$H)/1000,0) -> 0 | P48: 45900 | Q48: =SUM(SUMIF(Баланс!$B:$B,P48,Баланс!$D:$D)/1000,0) -> 6476536.1 | R48: =SUM(SUMIF(Баланс!$B:$B,P48,Баланс!$H:$H)/1000,0) -> 2698770.3 | S48: 52600 | T48: =SUM(SUMIF(Баланс!$B:$B,S48,Баланс!$C:$C)/1000,0) -> 0 | U48: =SUM(SUMIF(Баланс!$B:$B,S48,Баланс!$G:$G)/1000,0) -> 0 | V48: 55900 | W48: =SUM(SUMIF(Баланс!$B:$B,V48,Баланс!$C:$C)/1000,0) -> 2660.1262 | X48: =ROUND(SUMIF(Баланс!$B:$B,V48,Баланс!$G:$G)/1000,0) -> 21626
M49: 41200 | N49: =SUM(SUMIF(Баланс!$B:$B,M49,Баланс!$D:$D)/1000,0) -> 0 | O49: =SUM(SUMIF(Баланс!$B:$B,M49,Баланс!$H:$H)/1000,0) -> 0 | S49: 53100 | T49: =SUM(SUMIF(Баланс!$B:$B,S49,Баланс!$C:$C)/1000,0) -> 0 | U49: =SUM(SUMIF(Баланс!$B:$B,S49,Баланс!$G:$G)/1000,0) -> 0
M50: 41400 | N50: =SUM(SUMIF(Баланс!$B:$B,M50,Баланс!$D:$D)/1000,0) -> 0 | O50: =SUM(SUMIF(Баланс!$B:$B,M50,Баланс!$H:$H)/1000,0) -> 0 | S50: 54100 | T50: =SUM(SUMIF(Баланс!$B:$B,S50,Баланс!$C:$C)/1000,0) -> 477.39247 | U50: =SUM(SUMIF(Баланс!$B:$B,S50,Баланс!$G:$G)/1000,0) -> 6334.0852
M51: 41600 | N51: =SUM(SUMIF(Баланс!$B:$B,M51,Баланс!$D:$D)/1000,0) -> 0 | O51: =SUM(SUMIF(Баланс!$B:$B,M51,Баланс!$H:$H)/1000,0) -> 0 | S51: 54200 | T51: =SUM(SUMIF(Баланс!$B:$B,S51,Баланс!$C:$C)/1000,0) -> 0 | U51: =SUM(SUMIF(Баланс!$B:$B,S51,Баланс!$G:$G)/1000,0) -> 0
M52: 41800 | N52: =SUM(SUMIF(Баланс!$B:$B,M52,Баланс!$D:$D)/1000,0) -> 0 | O52: =SUM(SUMIF(Баланс!$B:$B,M52,Баланс!$H:$H)/1000,0) -> 0 | S52: 54300 | T52: =SUM(SUMIF(Баланс!$B:$B,S52,Баланс!$C:$C)/1000,0) -> 0 | U52: =SUM(SUMIF(Баланс!$B:$B,S52,Баланс!$G:$G)/1000,0) -> 0
M53: 41900 | N53: =SUM(SUMIF(Баланс!$B:$B,M53,Баланс!$D:$D)/1000,0) -> 0 | O53: =SUM(SUMIF(Баланс!$B:$B,M53,Баланс!$H:$H)/1000,0) -> 0 | S53: 54900 | T53: =SUM(SUMIF(Баланс!$B:$B,S53,Баланс!$C:$C)/1000,0) -> 3056148.8 | U53: =SUM(SUMIF(Баланс!$B:$B,S53,Баланс!$G:$G)/1000,0) -> 3858011.1
M54: 42000 | N54: =SUM(SUMIF(Баланс!$B:$B,M54,Баланс!$D:$D)/1000,0) -> 654240.39 | O54: =SUM(SUMIF(Баланс!$B:$B,M54,Баланс!$H:$H)/1000,0) -> 503157.2
M55: 42100 | N55: =SUM(SUMIF(Баланс!$B:$B,M55,Баланс!$D:$D)/1000,0) -> 4887.8999 | O55: =SUM(SUMIF(Баланс!$B:$B,M55,Баланс!$H:$H)/1000,0) -> 2904.4506
M56: 42200 | N56: =SUM(SUMIF(Баланс!$B:$B,M56,Баланс!$D:$D)/1000,0) -> 0 | O56: =SUM(SUMIF(Баланс!$B:$B,M56,Баланс!$H:$H)/1000,0) -> 0
M57: 42300 | N57: =SUM(SUMIF(Баланс!$B:$B,M57,Баланс!$D:$D)/1000,0) -> 0 | O57: =SUM(SUMIF(Баланс!$B:$B,M57,Баланс!$H:$H)/1000,0) -> 0
M58: 42400 | N58: =SUM(SUMIF(Баланс!$B:$B,M58,Баланс!$D:$D)/1000,0) -> 380.95607 | O58: =SUM(SUMIF(Баланс!$B:$B,M58,Баланс!$H:$H)/1000,0) -> 0
M59: 42500 | N59: =SUM(SUMIF(Баланс!$B:$B,M59,Баланс!$D:$D)/1000,0) -> 0 | O59: =SUM(SUMIF(Баланс!$B:$B,M59,Баланс!$H:$H)/1000,0) -> 0
M60: 42600 | N60: =SUM(SUMIF(Баланс!$B:$B,M60,Баланс!$D:$D)/1000,0) -> 2591638.7 | O60: =SUM(SUMIF(Баланс!$B:$B,M60,Баланс!$H:$H)/1000,0) -> 384946.23
M61: 43600 | N61: =SUM(SUMIF(Баланс!$B:$B,M61,Баланс!$D:$D)/1000,0) -> 0 | O61: =SUM(SUMIF(Баланс!$B:$B,M61,Баланс!$H:$H)/1000,0) -> 0
M62: 43700 | N62: =SUM(SUMIF(Баланс!$B:$B,M62,Баланс!$D:$D)/1000,0) -> 0 | O62: =SUM(SUMIF(Баланс!$B:$B,M62,Баланс!$H:$H)/1000,0) -> 0
M63: 43900 | N63: =SUM(SUMIF(Баланс!$B:$B,M63,Баланс!$D:$D)/1000,0) -> 0 | O63: =SUM(SUMIF(Баланс!$B:$B,M63,Баланс!$H:$H)/1000,0) -> 0
M64: 44000 | N64: =SUM(SUMIF(Баланс!$B:$B,M64,Баланс!$D:$D)/1000,0) -> 0 | O64: =SUM(SUMIF(Баланс!$B:$B,M64,Баланс!$H:$H)/1000,0) -> 0
M65: 44100 | N65: =SUM(SUMIF(Баланс!$B:$B,M65,Баланс!$D:$D)/1000,0) -> 42903.027 | O65: =SUM(SUMIF(Баланс!$B:$B,M65,Баланс!$H:$H)/1000,0) -> 48243.2
... M74: 45100 | N74: =SUM(SUMIF(Баланс!$B:$B,M74,Баланс!$D:$D)/1000,0) -> 0 | O74: =SUM(SUMIF(Баланс!$B:$B,M74,Баланс!$H:$H)/1000,0) -> 0
N75: =SUM(N43:N74) -> 8358260.3 | O75: =SUM(O43:O74) -> 9751091.3 | Q75: =SUM(Q43:Q74) -> 8006779.7 | R75: =SUM(R43:R74) -> 6135983.1 | T75: =SUM(T43:T74) -> 5246960.4 | U75: =SUM(U43:U74) -> 5927005.9 | W75: =SUM(W43:W74) -> 75764.996 | X75: =SUM(X43:X74) -> 780288

Sheet 2.Мол.ёр.16102-1
L1: 2-жадвал
B2: =""&(Шаблон!B1)&"нинг "&(Шаблон!B2)&" вилоят "&(Шаблон!B3)&" филиали томонидан Халқ банк филиалларига берилган молиявий ёрдам ва унга ҳисобланган фоизларнинг ундирилиши бўйича 2016 йил 1 сентябр холатига" -> АТ "Халқ банк"нинг Фаргона вилояти вилоят Бешариқ филиали филиали томонидан Халқ банк филиалларига берилган молиявий ёрдам ва унга ҳисобланган фоизларнинг ундирилиши бўйича 2016 йил 1 сентябр холатига
B3: МАЪЛУМОТ
J4: сўмда
A5: Т.Р | B5: Санаси | C5: Қайтарилган ресурс маблағи | D5: Олинган ресурс маблағи | E5: Кун якунига колдик сумма | F5: Фоизи | G5: Кунлар сони | H5: Хисобланиши лозим фоиз суммаси | I5: Тўлаб берилган | J5: Фарқ(+,-)
A6: а | B6: 2 | C6: 3 | D6: 4 | E6: 5 | F6: 6 | G6: 7 | H6: 8 | I6: 9 | J6: 10
A7: Фаргон вилоят филиалига берилган ресурси
A8: 1 | B8: 26.01.2015 | C8: 0 | D8: 1700000000 | E8: =+D8-C8 -> 1700000000 | F8: 1 | G8: 1 | H8: =E8*F8%/365*G8 -> 46575.342
A9: =+A8+1 -> 2 | B9: 31.03.2015 | C9: 200000000 | D9: 0 | E9: =E8-C9+D9 -> 1500000000 | F9: 5 | G9: =+B10-B9 -> 7 | H9: =E9*F9%/365*G9 -> 1438356.2
A10: =+A9+1 -> 3 | B10: 07.04.2015 | C10: 200000000 | D10: 0 | E10: =E9-C10+D10 -> 1300000000 | F10: 5 | G10: =+B11-B10 -> 323 | H10: =E10*F10%/365*G10 -> 57520548
A11: =+A10+1 -> 4 | B11: 24.02.2016 | C11: 0 | D11: 2000000000 | E11: =E10-C11+D11 -> 3300000000 | F11: 5 | G11: =+B12-B11 -> 0 | H11: =E11*F11%/365*G11 -> 0
A12: =+A11+1 -> 5 | B12: 24.02.2016 | C12: 1300000000 | D12: 0 | E12: =E11-C12+D12 -> 2000000000 | F12: 5 | G12: =+B13-B12 -> 2 | H12: =E12*F12%/365*G12 -> 547945.21
A13: =+A12+1 -> 6 | B13: 26.02.2016 | C13: 0 | D13: 500000000 | E13: =E12-C13+D13 -> 2500000000 | F13: 5 | G13: =+B14-B13 -> 1 | H13: =E13*F13%/365*G13 -> 342465.75
A14: =+A13+1 -> 7 | B14: 27.02.2016 | C14: 0 | D14: 200000000 | E14: =E13-C14+D14 -> 2700000000 | F14: 5 | G14: =+B15-B14 -> 5 | H14: =E14*F14%/365*G14 -> 1849315.1
A15: =+A14+1 -> 8 | B15: 03.03.2016 | C15: 100000000 | D15: 0 | E15: =E14-C15+D15 -> 2600000000 | F15: 5 | G15: =+B16-B15 -> 2 | H15: =E15*F15%/365*G15 -> 712328.77
A16: =+A15+1 -> 9 | B16: 05.03.2016 | C16: 100000000 | D16: 0 | E16: =E15-C16+D16 -> 2500000000 | F16: 5 | G16: =+B17-B16 -> 4 | H16: =E16*F16%/365*G16 -> 1369863
A17: =+A16+1 -> 10 | B17: 09.03.2016 | C17: 0 | D17: 200000000 | E17: =E16-C17+D17 -> 2700000000 | F17: 5 | G17: =+B18-B17 -> 7 | H17: =E17*F17%/365*G17 -> 2589041.1
A18: =+A17+1 -> 11 | B18: 16.03.2016 | C18: 50000000 | D18: 0 | E18: =E17-C18+D18 -> 2650000000 | F18: 5 | G18: =+B19-B18 -> 11 | H18: =E18*F18%/365*G18 -> 3993150.7
A19: =+A18+1 -> 12 | B19: 27.03.2016 | C19: 0 | D19: 350000000 | E19: =E18-C19+D19 -> 3000000000 | F19: 5 | G19: =+B20-B19 -> 29 | H19: =E19*F19%/365*G19 -> 11917808
A20: =+A19+1 -> 13 | B20: 25.04.2016 | C20: 0 | D20: 500000000 | E20: =E19-C20+D20 -> 3500000000 | F20: 5 | G20: =+B21-B20 -> 5 | H20: =E20*F20%/365*G20 -> 2397260.3
... A33: =+A32+1 -> 26 | B33: 06.09.2016 | C33: 200000000 | D33: 0 | E33: =E32-C33+D33 -> 500000000 | F33: 5 | G33: =+B34-B33 -> 30 | H33: =E33*F33%/365*G33 -> 2054794.5
A34: =+A33+1 -> 27 | B34: 06.10.2016 | C34: 500000000 | D34: 0 | E34: =E33-C34+D34 -> 0 | F34: 5 | H34: =E34*F34%/365*G34 -> 0
A35: ЖАМИ Фаргон вилоят филиали ресурси | H35: =SUM(H8:H34) -> 1.1049178e+08 | I35: 66258904 | J35: =I35-H35 -> -44232877
A36: ХАММАСИ | H36: =+H35 -> 1.1049178e+08 | I36: =+I35 -> 66258904 | J36: =+J35 -> -44232877 | L36: -1402736.7
B38: =+'1.активлар'!B34 -> АТ "Халқ банк"нинг Ички аудит
B39: =+'1.активлар'!B35 -> департаменти бўлим бошлиғи: | F39: =+'1.активлар'!F35 -> А.Ҳазратқулов
B41: =+'1.активлар'!B37 -> АТ "Халқ банк" Фаргона вилояти
B42: =+'1.активлар'!B38 -> Бешариқ филиали бошқарувчиси: | F42: =+'1.активлар'!F38 -> _____________
B44: =+'1.активлар'!B40 -> Бош бухгалтери: | F44: =+'1.активлар'!F40 -> _____________

Sheet 2,1.Мол.ёр.22203-1
L1: 2-жадвал
B2: =""&(Шаблон!B1)&"нинг "&(Шаблон!B2)&" вилоят "&(Шаблон!B3)&" филиали томонидан Халқ банк филиалларидан олинган молиявий ёрдам ва унга ҳисобланган фоизларнинг ундирилиши бўйича 2020 йил 1 январ ҳолатига" -> АТ "Халқ банк"нинг Фаргона вилояти вилоят Бешариқ филиали филиали томонидан Халқ банк филиалларидан олинган молиявий ёрдам ва унга ҳисобланган фоизларнинг ундирилиши бўйича 2020 йил 1 январ ҳолатига
B3: МАЪЛУМОТ
J4: сўмда
A5: Т.Р | B5: Санаси | C5: Қайтарилган ресурс маблағи | D5: Олинган ресурс маблағи | E5: Кун якунига колдик сумма | F5: Фоизи | G5: Кунлар сони | H5: Хисобланиши лозим фоиз суммаси | I5: Тўлаб берилган | J5: Фарқ(+,-)
A6: а | B6: 2 | C6: 3 | D6: 4 | E6: 5 | F6: 6 | G6: 7 | H6: 8 | I6: 9 | J6: 10
A7: Бош банкдан олинган 8 фоизли ресурс маблаглари
A8: 1 | B8: 01.12.2017 | C8: 0 | D8: 4191220000 | E8: =+D8-C8 -> 4191220000 | F8: 8 | G8: =B9-B8 -> 3 | H8: =E8*F8%/365*G8 -> 2755870.7
A9: =+A8+1 -> 2 | B9: 04.12.2017 | C9: 0 | D9: 1500000000 | E9: =E8-C9+D9 -> 5691220000 | F9: 8 | G9: =B10-B9 -> 1 | H9: =E9*F9%/365*G9 -> 1247390.7
A10: =+A9+1 -> 3 | B10: 05.12.2017 | C10: 0 | D10: 600000000 | E10: =E9-C10+D10 -> 6291220000 | F10: 8 | G10: =B11-B10 -> 1 | H10: =E10*F10%/365*G10 -> 1378897.5
A11: =+A10+1 -> 4 | B11: 06.12.2017 | C11: 3000000000 | D11: 0 | E11: =E10-C11+D11 -> 3291220000 | F11: 8 | G11: =B12-B11 -> 0 | H11: =E11*F11%/365*G11 -> 0
A12: =+A11+1 -> 5 | B12: 06.12.2017 | C12: 500000000 | D12: 0 | E12: =E11-C12+D12 -> 2791220000 | F12: 8 | G12: =B13-B12 -> 1 | H12: =E12*F12%/365*G12 -> 611774.25
A13: =+A12+1 -> 6 | B13: 07.12.2017 | C13: 1500000000 | D13: 0 | E13: =E12-C13+D13 -> 1291220000 | F13: 8 | G13: =B14-B13 -> 4 | H13: =E13*F13%/365*G13 -> 1132028.5
A14: =+A13+1 -> 7 | B14: 11.12.2017 | C14: 0 | D14: 500000000 | E14: =E13-C14+D14 -> 1791220000 | F14: 8 | G14: =B15-B14 -> 1 | H14: =E14*F14%/365*G14 -> 392596.16
A15: =+A14+1 -> 8 | B15: 12.12.2017 | C15: 0 | D15: 100000000 | E15: =E14-C15+D15 -> 1891220000 | F15: 8 | G15: =B16-B15 -> 1 | H15: =E15*F15%/365*G15 -> 414513.97
A16: =+A15+1 -> 9 | B16: 13.12.2017 | C16: 0 | D16: 400000000 | E16: =E15-C16+D16 -> 2291220000 | F16: 8 | G16: =B17-B16 -> 1 | H16: =E16*F16%/365*G16 -> 502185.21
A17: =+A16+1 -> 10 | B17: 14.12.2017 | C17: 0 | D17: 300000000 | E17: =E16-C17+D17 -> 2591220000 | F17: 8 | G17: =B18-B17 -> 1 | H17: =E17*F17%/365*G17 -> 567938.63
A18: =+A17+1 -> 11 | B18: 15.12.2017 | C18: 0 | D18: 900000000 | E18: =E17-C18+D18 -> 3491220000 | F18: 8 | G18: =B19-B18 -> 2 | H18: =E18*F18%/365*G18 -> 1530397.8
A19: =+A18+1 -> 12 | B19: 17.12.2017 | C19: 0 | D19: 700000000 | E19: =E18-C19+D19 -> 4191220000 | F19: 8 | G19: =B20-B19 -> 1 | H19: =E19*F19%/365*G19 -> 918623.56
A20: =+A19+1 -> 13 | B20: 18.12.2017 | C20: 0 | D20: 200000000 | E20: =E19-C20+D20 -> 4391220000 | F20: 8 | G20: =B21-B20 -> 1 | H20: =E20*F20%/365*G20 -> 962459.18
... A96: =+A95+1 -> 89 | B96: 30.03.2018 | C96: 0 | D96: 200000000 | E96: =E95-C96+D96 -> 5879520000 | F96: 8 | G96: =B97-B96 -> 1 | H96: =E96*F96%/365*G96 -> 1288661.9
A97: =+A96+1 -> 90 | B97: 31.03.2018 | C97: 0 | D97: 300000000 | E97: =E96-C97+D97 -> 6179520000 | F97: 8 | G97: 1 | H97: =E97*F97%/365*G97 -> 1354415.3
A98: =+A60+1 -> 54 | H98: =E98*F98%/365*G98 -> 0
A99: ЖАМИ Бош банкдан олинган 8 фоиз ресурс маблаги | H99: =SUM(H8:H97) -> 1.2804255e+08 | I99: 1.2804255e+08 | J99: =I99-H99 -> 0.00068488717
B102: =+'2.Мол.ёр.16102-1'!B38 -> АТ "Халқ банк"нинг Ички аудит
B103: =+'2.Мол.ёр.16102-1'!B39 -> департаменти бўлим бошлиғи: | F103: =+'2.Мол.ёр.16102-1'!F39 -> А.Ҳазратқулов
B105: =+'2.Мол.ёр.16102-1'!B41 -> АТ "Халқ банк" Фаргона вилояти
B106: =+'2.Мол.ёр.16102-1'!B42 -> Бешариқ филиали бошқарувчиси: | F106: =+'2.Мол.ёр.16102-1'!F42 -> _____________
B108: =+'2.Мол.ёр.16102-1'!B44 -> Бош бухгалтери: | F108: =+'2.Мол.ёр.16102-1'!F44 -> _____________

Sheet 22203
L1: 2.1-жадвал
A2: "Агробанк" ОАТБ нинг вилоят бошқармаси Ҳудудий филиали томонидан олинган молиявий ёрдам маблаги ва унга ҳисобланган фоизларнинг тўланиши бўйича 2013 йил 1 июн холатига
B3: МАЪЛУМОТ
L4: сўмда
A5: Т/р | B5: Банк филиалининг номи | C5: Молиявий ёрдам олинган сана | D5: Сумма | E5: Фоиз ставка | F5: Бир кунлик фоиз суммаси | G5: Фоиз хисобланган кун | H5: Умумий фоиз ( сум) | I5: Филиалларга тўланди фоиз | J5: Фарқи (+;-) | K5: Молиявий ёрдам қайтарилган сана | L5: 2013 йил 1 июн холатига колдик
A9: А | B9: Б | C9: 1 | D9: =+C9+1 -> 2 | E9: =+D9+1 -> 3 | F9: =+E9+1 -> 4 | G9: =+F9+1 -> 5 | H9: =+G9+1 -> 6 | I9: =+H9+1 -> 7 | J9: 8 | K9: 9 | L9: 10
A10: Тошкент шахар Бектимир филиалига берилган ресурси
A11: 1 | B11: 12.02.15 | C11: 0 | D11: 500000000 | E11: =+D11-C11 -> 500000000 | F11: 6 | G11: =+B12-B11 -> 68 | H11: =E11*F11%/365*G11 -> 5589041.1
A12: =+A11+1 -> 2 | B12: 21.04.15 | C12: 300000000 | D12: 0 | E12: =E11-C12+D12 -> 200000000 | F12: 6 | G12: =+B13-B12 -> 64 | H12: =E12*F12%/365*G12 -> 2104109.6
A13: =+A12+1 -> 3 | B13: 24.06.15 | C13: 100000000 | D13: 0 | E13: =E12-C13+D13 -> 100000000 | F13: 6 | G13: =+B14-B13 -> 5 | H13: =E13*F13%/365*G13 -> 82191.781
A14: =+A13+1 -> 4 | B14: 29.06.15 | C14: 100000000 | D14: 0 | E14: =E13-C14+D14 -> 0 | F14: 6 | H14: =E14*F14%/365*G14 -> 0
A16: 3 | B16: Батош филиали бўйича жами: | E16: х | F16: =SUM(#REF!) -> #REF! | G16: =SUM(#REF!) -> #REF! | H16: =SUM(#REF!) -> #REF! | I16: =SUM(#REF!) -> #REF! | J16: =SUM(#REF!) -> #REF! | K16: х | L16: =SUM(#REF!) -> #REF!
A17: =+A16+#REF!+#REF!+#REF!+#REF!+#REF!+#REF! -> #REF! | B17: Жами вилоят бўйича | F17: =+F16+#REF!+#REF!+#REF!+#REF!+#REF!+#REF! -> #REF! | G17: =+G16+#REF!+#REF!+#REF!+#REF!+#REF!+#REF! -> #REF! | H17: =+H16+#REF!+#REF!+#REF!+#REF!+#REF!+#REF! -> #REF! | I17: =+I16+#REF!+#REF!+#REF!+#REF!+#REF!+#REF! -> #REF! | J17: =+J16+#REF!+#REF!+#REF!+#REF!+#REF!+#REF! -> #REF! | L17: =+L16+#REF!+#REF!+#REF! -> #REF!
C19: "Агробанк" ОАТБнинг Ички Аудит
C20: Департаменти бош мутахассиси: | I20: У.Р.Очилов
C22: Сурхондарё вилоят бошқармаси
C23: Ҳудудий филиал бошқарувчиси: | I23: А.Х.Бўронов
C25: Бош бухгалтери: | I25: У.Б.Тўрақулов

Sheet 3.Д-т фоиз
G1: 3-жадвал
A2: =""&(Шаблон!B1)&"нинг "&(Шаблон!B2)&" шахар "&(Шаблон!B3)&" филиалида мижозлар ҳисобварақлари орқали амалга оширилган дебет айланма учун улар билан тузилган Банк ҳисобварақ шартномасида белгиланган фоиз ставкасидан кам ёки ортиқча фоиз ҳисобланган ҳолатлар бўйича" -> АТ "Халқ банк"нинг Фаргона вилояти шахар Бешариқ филиали филиалида мижозлар ҳисобварақлари орқали амалга оширилган дебет айланма учун улар билан тузилган Банк ҳисобварақ шартномасида белгиланган фоиз ставкасидан кам ёки ортиқча фоиз ҳисобланган ҳолатлар бўйича
D3: М А Ъ Л У М О Т
G4: (минг сўмда)
A5: т/р | B5: Мижоз номи | C5: Фоиз ҳисобланиши | G5: Изоҳ
C6: белгиланган фоиз ставкаси | D6: ҳисобланиши керак бўлган фоиз суммаси | E6: ҳақиқатда ҳисобланган фоиз суммаси | F6: фарқи
F7: +; -
A8: А | B8: Б | C8: 1 | D8: 2 | E8: 3 | F8: 4 | G8: 5
A9: 1 | B9: Самарқанд Қудуқ Толаси фх | C9: 0.03 | D9: =(450000*3%)/1000 -> 13.5 | E9: =(450000*0.7%)/1000 -> 3.15 | F9: =+E9-D9 -> -10.35 | G9: ОКО модулига фоиз ставкаси кам киритилган
A10: =+A9+1 -> 2 | B10: Жобборов Тиркаш ктхф | C10: 0.02 | D10: =(24894367.74*C10)/1000 -> 497.88735 | E10: =(24894367.74*0.7%)/1000 -> 174.26057 | F10: =+E10-D10 -> -323.62678
A11: =+A10+1 -> 3 | B11: Мусобақа Ғолиби фх | C11: 0.01 | D11: =(10441439.13*C11)/1000 -> 104.41439 | E11: =(10441439.13*0.7%)/1000 -> 73.090074 | F11: =+E11-D11 -> -31.324317
A12: 4 | B12: Комилжон Даласи фх | C12: 0.03 | D12: =2682700*3%/1000 -> 80.481 | E12: =2682.7*0.7% -> 18.7789 | F12: =+E12-D12 -> -61.7021
A13: 5 | B13: Отабек-Феруза Савдо х\к | C13: 0.02 | D13: =48291749.69*2%/1000 -> 965.83499 | E13: =48291749.69*0.7%/1000 -> 338.04225 | F13: =+E13-D13 -> -627.79275
A14: 6 | B14: Солиха Умида фх | C14: 0.03 | D14: =2809.2*3% -> 84.276 | E14: 0 | F14: =+E14-D14 -> -84.276
A15: цуывяч | B15: жами | D15: =SUM(D9:D14) -> 1746.3937 | E15: =SUM(E9:E14) -> 607.3218 | F15: =SUM(F9:F14) -> -1139.0719
B18: =""&(Шаблон!B1)&"нинг Ички Аудит" -> АТ "Халқ банк"нинг Ички Аудит
B19: Департаменти бош мутахассиси: | F19: =Шаблон!B13 -> А.Ҳазратқулов
B21: =""&(Шаблон!B1)&" "&(Шаблон!B2)&" вилояти" -> АТ "Халқ банк" Фаргона вилояти вилояти
B22: =""&(Шаблон!B3)&" филиали бошқарувчиси:" -> Бешариқ филиали филиали бошқарувчиси: | F22: =Шаблон!B5 -> _____________
B24: Бош бухгалтери: | F24: =Шаблон!B8 -> _____________

Sheet 3а.Абонент тулов
C2: ДТ "Халқ банк"нинг Жиззах вилояти филиалида мижозлардан ойлик абонент тeловларини хисобланиши ва ундирилши буйича бўйича маълумот
A4: № | B4: БХ | C4: Уникал коди | D4: Мижоз номи | E4: жами | F4: Январ | H4: феврал | J4: март | L4: апрел | N4: май | P4: июн | R4: июл | T4: август | V4: сентябр | X4: октябр | Z4: ноябр | AB4: декабр | AD4: январ | AF4: феврал | AH4: март | AJ4: апрел | AL4: май | AN4: июн | AP4: июл | AR4: август | AT4: Ундирилмаган мабла- | AU4: Ундирилмасдан қолган маблағ | AV4: Фарки
A5: 1 | C5: 00252797 | D5: YATT ALIQULOVA ZULAYXO ABDUXALIL QIZI хисобварак а 602874818 | E5: =+SUM(F5:AR5) -> 450000 | F5: 50000 | H5: 50000 | J5: 50000 | L5: 50000 | N5: 50000 | P5: 50000 | R5: 50000 | T5: 50000 | V5: 50000 | X5: 0 | Z5: 0 | AB5: 0 | AD5: 0 | AF5: 0 | AJ5: 0 | AL5: 0 | AN5: 0 | AP5: 0 | AR5: 0 | AT5: =+AS5+AQ5+AO5+AM5+AK5+AI5+AG5+AE5+AC5+AA5+Y5+W5+U5+S5+Q5+O5+M5+K5+I5+G5 -> 0 | AU5: =+E5-AT5 -> 450000 | AV5: =+AT5-AW5 -> 0 | AW5: =SUMIF(AX:AX,C5,AY:AY) -> 0 | AX5: 04680109 | AY5: 40000
A6: =+A5+1 -> 2 | C6: 00255041 | D6: YATT ALIYEV ZAYNIDDIN OCHILOVICH 602867216 | E6: =+SUM(F6:AR6) -> 960000 | F6: 50000 | H6: 50000 | J6: 50000 | L6: 50000 | N6: 50000 | P6: 50000 | R6: 50000 | T6: 50000 | V6: 50000 | X6: 50000 | Z6: 50000 | AB6: 50000 | AD6: 150000 | AF6: 50000 | AH6: 0 | AJ6: 0 | AL6: 40000 | AN6: 40000 | AP6: 40000 | AR6: 40000 | AT6: =+AS6+AQ6+AO6+AM6+AK6+AI6+AG6+AE6+AC6+AA6+Y6+W6+U6+S6+Q6+O6+M6+K6+I6+G6 -> 0 | AU6: =+E6-AT6 -> 960000 | AV6: =+AT6-AW6 -> 0 | AW6: =SUMIF(AX:AX,C6,AY:AY) -> 0 | AX6: 04980506 | AY6: 40000
A7: =+A6+1 -> 3 | C7: 00268724 | D7: ЯТТ Окилов Олим Узганбаевич хисобланган хисобракам 463089620 | E7: =+SUM(F7:AR7) -> 1010000 | F7: 50000 | H7: 50000 | J7: 50000 | L7: 50000 | N7: 50000 | P7: 50000 | R7: 50000 | T7: 50000 | V7: 50000 | X7: 50000 | Z7: 50000 | AB7: 50000 | AD7: 150000 | AF7: 50000 | AH7: 0 | AJ7: 50000 | AL7: 40000 | AN7: 40000 | AP7: 40000 | AR7: 40000 | AT7: =+AS7+AQ7+AO7+AM7+AK7+AI7+AG7+AE7+AC7+AA7+Y7+W7+U7+S7+Q7+O7+M7+K7+I7+G7 -> 0 | AU7: =+E7-AT7 -> 1010000 | AV7: =+AT7-AW7 -> 0 | AW7: =SUMIF(AX:AX,C7,AY:AY) -> 0 | AX7: 04879712 | AY7: 40000
A8: =+A7+1 -> 4 | C8: 00294738 | D8: FORISH-NARVON MCHJ Хисобланган бошка фоизсиз даром 302781927 | E8: =+SUM(F8:AR8) -> 970000 | F8: 50000 | H8: 50000 | J8: 50000 | L8: 50000 | N8: 50000 | P8: 50000 | R8: 50000 | T8: 50000 | V8: 50000 | X8: 50000 | Z8: 50000 | AB8: 50000 | AD8: 150000 | AF8: 50000 | AH8: 0 | AJ8: 50000 | AL8: 40000 | AN8: 40000 | AP8: 40000 | AR8: 0 | AT8: =+AS8+AQ8+AO8+AM8+AK8+AI8+AG8+AE8+AC8+AA8+Y8+W8+U8+S8+Q8+O8+M8+K8+I8+G8 -> 0 | AU8: =+E8-AT8 -> 970000 | AV8: =+AT8-AW8 -> 0 | AW8: =SUMIF(AX:AX,C8,AY:AY) -> 0 | AX8: 00408323 | AY8: 40000
A9: =+A8+1 -> 5 | C9: 00298068 | D9: YATT ULASHBAYEV AMRULLO ULASHBAY O'G'LI 603045898 | E9: =+SUM(F9:AR9) -> 350000 | F9: 50000 | H9: 50000 | J9: 50000 | L9: 50000 | N9: 0 | P9: 50000 | R9: 50000 | T9: 50000 | V9: 0 | X9: 0 | Z9: 0 | AB9: 0 | AD9: 0 | AF9: 0 | AJ9: 0 | AL9: 0 | AN9: 0 | AP9: 0 | AR9: 0 | AT9: =+AS9+AQ9+AO9+AM9+AK9+AI9+AG9+AE9+AC9+AA9+Y9+W9+U9+S9+Q9+O9+M9+K9+I9+G9 -> 0 | AU9: =+E9-AT9 -> 350000 | AV9: =+AT9-AW9 -> 0 | AW9: =SUMIF(AX:AX,C9,AY:AY) -> 0 | AX9: 00599137 | AY9: 40000
A10: =+A9+1 -> 6 | C10: 00299893 | D10: YATT MANSUROVA IHBOL 603045914 | E10: =+SUM(F10:AR10) -> 400000 | F10: 50000 | H10: 50000 | J10: 50000 | L10: 50000 | N10: 50000 | P10: 50000 | R10: 50000 | T10: 50000 | V10: 0 | X10: 0 | Z10: 0 | AB10: 0 | AD10: 0 | AF10: 0 | AJ10: 0 | AL10: 0 | AN10: 0 | AP10: 0 | AR10: 0 | AT10: =+AS10+AQ10+AO10+AM10+AK10+AI10+AG10+AE10+AC10+AA10+Y10+W10+U10+S10+Q10+O10+M10+K10+I10+G10 -> 0 | AU10: =+E10-AT10 -> 400000 | AV10: =+AT10-AW10 -> 0 | AW10: =SUMIF(AX:AX,C10,AY:AY) -> 0 | AX10: 04838884 | AY10: 40000
A11: =+A10+1 -> 7 | C11: 04352777 | D11: КУШ ТЕПА БОКИЙ ХУСУСИЙ КОРХОНАСИ Хисобварак абонте 205197237 | E11: =+SUM(F11:AR11) -> 960000 | F11: 50000 | H11: 50000 | J11: 50000 | L11: 50000 | N11: 50000 | P11: 50000 | R11: 50000 | T11: 50000 | V11: 50000 | X11: 50000 | Z11: 50000 | AB11: 50000 | AD11: 150000 | AF11: 50000 | AH11: 0 | AJ11: 0 | AL11: 40000 | AN11: 40000 | AP11: 40000 | AR11: 40000 | AT11: =+AS11+AQ11+AO11+AM11+AK11+AI11+AG11+AE11+AC11+AA11+Y11+W11+U11+S11+Q11+O11+M11+K11+I11+G11 -> 0 | AU11: =+E11-AT11 -> 960000 | AV11: =+AT11-AW11 -> 0 | AW11: =SUMIF(AX:AX,C11,AY:AY) -> 0 | AX11: 04767059 | AY11: 50000
A12: =+A11+1 -> 8 | C12: 04359000 | D12: НУР ва ТИБ МЧЖ Хисобварак абонтент тулв. буй. Хис 205259063 | E12: =+SUM(F12:AR12) -> 400000 | F12: 50000 | H12: 50000 | J12: 50000 | L12: 50000 | N12: 50000 | P12: 50000 | R12: 50000 | T12: 0 | V12: 0 | X12: 0 | Z12: 0 | AB12: 0 | AD12: 0 | AE12: 50000 | AF12: 0 | AJ12: 0 | AL12: 0 | AN12: 0 | AP12: 0 | AR12: 0 | AT12: =+AS12+AQ12+AO12+AM12+AK12+AI12+AG12+AE12+AC12+AA12+Y12+W12+U12+S12+Q12+O12+M12+K12+I12+G12 -> 50000 | AU12: =+E12-AT12 -> 350000 | AV12: =+AT12-AW12 -> 50000 | AW12: =SUMIF(AX:AX,C12,AY:AY) -> 0 | AX12: 04943627 | AY12: 50000
A13: =+A12+1 -> 9 | C13: 00258107 | D13: YATT QARSHIBOEV TO'LQIN XAITBOEVICH 456500935 | E13: =+SUM(F13:AR13) -> 960000 | F13: 50000 | H13: 50000 | J13: 50000 | L13: 50000 | N13: 50000 | P13: 50000 | R13: 50000 | T13: 50000 | V13: 50000 | X13: 50000 | Z13: 50000 | AB13: 50000 | AD13: 150000 | AF13: 50000 | AH13: 0 | AJ13: 0 | AL13: 40000 | AN13: 40000 | AP13: 40000 | AR13: 40000 | AT13: =+AS13+AQ13+AO13+AM13+AK13+AI13+AG13+AE13+AC13+AA13+Y13+W13+U13+S13+Q13+O13+M13+K13+I13+G13 -> 0 | AU13: =+E13-AT13 -> 960000 | AV13: =+AT13-AW13 -> 0 | AW13: =SUMIF(AX:AX,C13,AY:AY) -> 0 | AX13: 04780246 | AY13: 50000
A14: =+A13+1 -> 10 | C14: 00290290 | D14: YATT UMAROVA DONOHON QUCHQAROVNA | E14: =+SUM(F14:AR14) -> 550000 | F14: 50000 | H14: 50000 | J14: 50000 | L14: 50000 | N14: 50000 | P14: 50000 | R14: 50000 | T14: 50000 | V14: 0 | X14: 0 | Z14: 50000 | AB14: 0 | AD14: 0 | AE14: 50000 | AF14: 0 | AG14: 50000 | AJ14: 0 | AL14: 0 | AN14: 0 | AP14: 0 | AR14: 0 | AT14: =+AS14+AQ14+AO14+AM14+AK14+AI14+AG14+AE14+AC14+AA14+Y14+W14+U14+S14+Q14+O14+M14+K14+I14+G14 -> 100000 | AU14: =+E14-AT14 -> 450000 | AV14: =+AT14-AW14 -> 100000 | AW14: =SUMIF(AX:AX,C14,AY:AY) -> 0 | AX14: 04202843 | AY14: 50000
A15: =+A14+1 -> 11 | C15: 04721465 | D15: ХУСУСИЙ ТАДБИРКОР БОСТАТОВА РУХСАТ 477793466 | E15: =+SUM(F15:AR15) -> 400000 | F15: 50000 | H15: 50000 | J15: 50000 | L15: 50000 | N15: 50000 | P15: 50000 | R15: 0 | S15: 50000 | T15: 0 | V15: 0 | X15: 0 | Z15: 50000 | AB15: 0 | AD15: 0 | AF15: 0 | AJ15: 0 | AL15: 0 | AN15: 0 | AP15: 0 | AR15: 0 | AT15: =+AS15+AQ15+AO15+AM15+AK15+AI15+AG15+AE15+AC15+AA15+Y15+W15+U15+S15+Q15+O15+M15+K15+I15+G15 -> 50000 | AU15: =+E15-AT15 -> 350000 | AV15: =+AT15-AW15 -> 50000 | AW15: =SUMIF(AX:AX,C15,AY:AY) -> 0 | AX15: 04662092 | AY15: 50000
A16: =+A15+1 -> 12 | C16: 04767059 | D16: Хузуров Норпулат хусусий корхонаси Хисобварак абон 301126933 | E16: =+SUM(F16:AR16) -> 960000 | F16: 50000 | H16: 50000 | J16: 50000 | L16: 50000 | N16: 50000 | P16: 50000 | R16: 50000 | T16: 50000 | V16: 50000 | X16: 50000 | Z16: 50000 | AB16: 50000 | AD16: 100000 | AF16: 50000 | AH16: 0 | AJ16: 0 | AK16: 50000 | AL16: 40000 | AN16: 40000 | AP16: 40000 | AR16: 40000 | AT16: =+AS16+AQ16+AO16+AM16+AK16+AI16+AG16+AE16+AC16+AA16+Y16+W16+U16+S16+Q16+O16+M16+K16+I16+G16 -> 50000 | AU16: =+E16-AT16 -> 910000 | AV16: =+AT16-AW16 -> 0 | AW16: =SUMIF(AX:AX,C16,AY:AY) -> 50000 | AX16: 00312114 | AY16: 50000
A17: =+A16+1 -> 13 | C17: 04787575 | D17: Х.Т Омонликов Фарход хисобварак абонет тулови хис. 412065162 | E17: =+SUM(F17:AR17) -> 550000 | F17: 50000 | H17: 50000 | J17: 50000 | L17: 50000 | N17: 50000 | P17: 50000 | R17: 50000 | T17: 50000 | V17: 0 | W17: 50000 | X17: 0 | Y17: 50000 | Z17: 50000 | AB17: 0 | AD17: 0 | AF17: 0 | AJ17: 0 | AL17: 0 | AN17: 0 | AP17: 0 | AR17: 0 | AT17: =+AS17+AQ17+AO17+AM17+AK17+AI17+AG17+AE17+AC17+AA17+Y17+W17+U17+S17+Q17+O17+M17+K17+I17+G17 -> 100000 | AU17: =+E17-AT17 -> 450000 | AV17: =+AT17-AW17 -> 100000 | AW17: =SUMIF(AX:AX,C17,AY:AY) -> 0 | AX17: 00379149 | AY17: 50000
A18: =+A17+1 -> 14 | C18: 04877067 | D18: Шифобахш Чашма х.к Хисобварак абонтент тулв. буй. 207098034 | E18: =+SUM(F18:AR18) -> 960000 | F18: 50000 | H18: 50000 | J18: 50000 | L18: 50000 | N18: 50000 | P18: 50000 | R18: 50000 | T18: 50000 | V18: 50000 | X18: 50000 | Z18: 100000 | AB18: 100000 | AD18: 0 | AF18: 0 | AH18: 0 | AI18: 50000 | AJ18: 0 | AK18: 50000 | AL18: 40000 | AN18: 40000 | AP18: 40000 | AR18: 40000 | AT18: =+AS18+AQ18+AO18+AM18+AK18+AI18+AG18+AE18+AC18+AA18+Y18+W18+U18+S18+Q18+O18+M18+K18+I18+G18 -> 100000 | AU18: =+E18-AT18 -> 860000 | AV18: =+AT18-AW18 -> 0 | AW18: =SUMIF(AX:AX,C18,AY:AY) -> 100000 | AX18: 04950772 | AY18: 50000
A19: =+A18+1 -> 15 | C19: 00240424 | D19: YATT KARIMOV FAZIL NODIRBEKOVICH хисобварак абонет 600983454 | E19: =+SUM(F19:AR19) -> 600000 | F19: 50000 | H19: 50000 | J19: 50000 | L19: 50000 | N19: 50000 | P19: 50000 | R19: 50000 | T19: 50000 | V19: 50000 | X19: 50000 | Z19: 50000 | AB19: 50000 | AD19: 0 | AF19: 0 | AJ19: 0 | AL19: 0 | AN19: 0 | AP19: 0 | AR19: 0 | AT19: =+AS19+AQ19+AO19+AM19+AK19+AI19+AG19+AE19+AC19+AA19+Y19+W19+U19+S19+Q19+O19+M19+K19+I19+G19 -> 0 | AU19: =+E19-AT19 -> 600000 | AV19: =+AT19-AW19 -> 0 | AW19: =SUMIF(AX:AX,C19,AY:AY) -> 0 | AX19: 04963108 | AY19: 50000
A20: =+A19+1 -> 16 | C20: 04902249 | D20: "Гараша - Пахтакор" масъулияти чекланган жамият Хи 301913405 | E20: =+SUM(F20:AR20) -> 960000 | F20: 50000 | H20: 50000 | J20: 50000 | L20: 50000 | N20: 50000 | P20: 50000 | R20: 50000 | T20: 50000 | V20: 50000 | X20: 50000 | Z20: 50000 | AB20: 50000 | AD20: 150000 | AF20: 50000 | AH20: 0 | AJ20: 0 | AL20: 40000 | AN20: 40000 | AP20: 40000 | AR20: 40000 | AT20: =+AS20+AQ20+AO20+AM20+AK20+AI20+AG20+AE20+AC20+AA20+Y20+W20+U20+S20+Q20+O20+M20+K20+I20+G20 -> 0 | AU20: =+E20-AT20 -> 960000 | AV20: =+AT20-AW20 -> 0 | AW20: =SUMIF(AX:AX,C20,AY:AY) -> 0 | AX20: 04148607 | AY20: 50000
A21: =+A20+1 -> 17 | C21: 04943627 | D21: ЯТТ Суванов Уткир Атамуратович хисобварак абонет т 602165654 | E21: =+SUM(F21:AR21) -> 960000 | F21: 50000 | H21: 50000 | J21: 50000 | L21: 50000 | N21: 50000 | P21: 50000 | R21: 50000 | T21: 50000 | V21: 50000 | X21: 50000 | Z21: 50000 | AB21: 50000 | AD21: 100000 | AF21: 50000 | AJ21: 0 | AK21: 50000 | AL21: 40000 | AN21: 40000 | AP21: 40000 | AR21: 40000 | AT21: =+AS21+AQ21+AO21+AM21+AK21+AI21+AG21+AE21+AC21+AA21+Y21+W21+U21+S21+Q21+O21+M21+K21+I21+G21 -> 50000 | AU21: =+E21-AT21 -> 910000 | AV21: =+AT21-AW21 -> 0 | AW21: =SUMIF(AX:AX,C21,AY:AY) -> 50000 | AX21: 04503679 | AY21: 50000
A22: =+A21+1 -> 18 | C22: 04946503 | D22: ЯТТ Кадирова Феруза Салибаевна хисобварак абонет т 477742046 | E22: =+SUM(F22:AR22) -> 960000 | F22: 50000 | H22: 50000 | J22: 50000 | L22: 50000 | N22: 50000 | P22: 50000 | R22: 50000 | T22: 50000 | V22: 50000 | X22: 50000 | Z22: 50000 | AB22: 50000 | AD22: 150000 | AF22: 50000 | AH22: 0 | AJ22: 0 | AL22: 40000 | AN22: 40000 | AP22: 40000 | AR22: 40000 | AT22: =+AS22+AQ22+AO22+AM22+AK22+AI22+AG22+AE22+AC22+AA22+Y22+W22+U22+S22+Q22+O22+M22+K22+I22+G22 -> 0 | AU22: =+E22-AT22 -> 960000 | AV22: =+AT22-AW22 -> 0 | AW22: =SUMIF(AX:AX,C22,AY:AY) -> 0 | AX22: 00252979 | AY22: 50000
A23: =+A22+1 -> 19 | C23: 04960423 | D23: ЯТТ Миралиева Ольга Валерьевна хисобварак абонет т 602289341 | E23: =+SUM(F23:AR23) -> 150000 | F23: 50000 | H23: 0 | I23: 50000 | J23: 0 | K23: 50000 | L23: 0 | N23: 0 | P23: 0 | R23: 0 | T23: 0 | V23: 0 | X23: 0 | Z23: 0 | AB23: 0 | AD23: 0 | AF23: 0 | AJ23: 0 | AL23: 0 | AN23: 0 | AP23: 0 | AR23: 0 | AT23: =+AS23+AQ23+AO23+AM23+AK23+AI23+AG23+AE23+AC23+AA23+Y23+W23+U23+S23+Q23+O23+M23+K23+I23+G23 -> 100000 | AU23: =+E23-AT23 -> 50000 | AV23: =+AT23-AW23 -> 0 | AW23: =SUMIF(AX:AX,C23,AY:AY) -> 100000 | AX23: 04702555 | AY23: 50000
A24: =+A23+1 -> 20 | C24: 04680109 | D24: УРОЛ-ШЕРБЕК ХК Хисобварак абонтент тулв. буй. Хис 300716824 | E24: =+SUM(F24:AR24) -> 920000 | F24: 50000 | H24: 50000 | J24: 50000 | L24: 50000 | N24: 50000 | P24: 50000 | R24: 50000 | T24: 50000 | V24: 50000 | X24: 50000 | Z24: 50000 | AB24: 50000 | AD24: 150000 | AF24: 50000 | AH24: 0 | AJ24: 0 | AL24: 40000 | AN24: 40000 | AP24: 0 | AQ24: 40000 | AR24: 0 | AS24: 40000 | AT24: =+AS24+AQ24+AO24+AM24+AK24+AI24+AG24+AE24+AC24+AA24+Y24+W24+U24+S24+Q24+O24+M24+K24+I24+G24 -> 80000 | AU24: =+E24-AT24 -> 840000 | AV24: =+AT24-AW24 -> 40000 | AW24: =SUMIF(AX:AX,C24,AY:AY) -> 40000 | AX24: 00208829 | AY24: 50000
A25: =+A24+1 -> 21 | C25: 04780246 | D25: ЯТТ Каршиев Ш.Ш. хисобварак абонет тулови хис. % л 600016524 | E25: =+SUM(F25:AR25) -> 960000 | F25: 50000 | H25: 50000 | J25: 50000 | L25: 50000 | N25: 50000 | P25: 50000 | R25: 50000 | T25: 50000 | V25: 50000 | X25: 50000 | Z25: 50000 | AB25: 50000 | AD25: 100000 | AF25: 50000 | AH25: 0 | AJ25: 0 | AK25: 50000 | AL25: 40000 | AN25: 40000 | AP25: 40000 | AR25: 40000 | AT25: =+AS25+AQ25+AO25+AM25+AK25+AI25+AG25+AE25+AC25+AA25+Y25+W25+U25+S25+Q25+O25+M25+K25+I25+G25 -> 50000 | AU25: =+E25-AT25 -> 910000 | AV25: =+AT25-AW25 -> 0 | AW25: =SUMIF(AX:AX,C25,AY:AY) -> 50000 | AX25: 04188351 | AY25: 50000
A26: =+A25+1 -> 22 | C26: 04881598 | D26: ЯТТ Пакиров Хусан Сориевич хисобварак абонет тулов 454930268 | E26: =+SUM(F26:AR26) -> 960000 | F26: 50000 | H26: 50000 | J26: 50000 | L26: 50000 | N26: 50000 | P26: 50000 | R26: 50000 | T26: 50000 | V26: 50000 | X26: 50000 | Z26: 50000 | AB26: 50000 | AD26: 150000 | AF26: 50000 | AH26: 0 | AJ26: 0 | AL26: 40000 | AN26: 40000 | AP26: 40000 | AR26: 40000 | AT26: =+AS26+AQ26+AO26+AM26+AK26+AI26+AG26+AE26+AC26+AA26+Y26+W26+U26+S26+Q26+O26+M26+K26+I26+G26 -> 0 | AU26: =+E26-AT26 -> 960000 | AV26: =+AT26-AW26 -> 0 | AW26: =SUMIF(AX:AX,C26,AY:AY) -> 0 | AX26: 00300956 | AY26: 50000
A27: =+A26+1 -> 23 | C27: 00271938 | D27: YATT TOKABAYEVA SANOBAR XATAMOVNA 601936004 | E27: =+SUM(F27:AR27) -> 640000 | F27: 50000 | H27: 50000 | J27: 50000 | L27: 50000 | N27: 50000 | P27: 50000 | R27: 50000 | T27: 50000 | V27: 50000 | X27: 50000 | Z27: 50000 | AB27: 50000 | AD27: 0 | AF27: 0 | AJ27: 0 | AL27: 0 | AN27: 0 | AO27: 40000 | AP27: 0 | AR27: 0 | AT27: =+AS27+AQ27+AO27+AM27+AK27+AI27+AG27+AE27+AC27+AA27+Y27+W27+U27+S27+Q27+O27+M27+K27+I27+G27 -> 40000 | AU27: =+E27-AT27 -> 600000 | AV27: =+AT27-AW27 -> 40000 | AW27: =SUMIF(AX:AX,C27,AY:AY) -> 0 | AX27: 04874757 | AY27: 50000
A28: =+A27+1 -> 24 | C28: 00287381 | D28: YATT DEXQONOV MAMASOLI 602628314 | E28: =+SUM(F28:AR28) -> 1010000 | F28: 50000 | H28: 50000 | J28: 50000 | L28: 50000 | N28: 50000 | P28: 50000 | R28: 50000 | T28: 50000 | V28: 50000 | X28: 50000 | Z28: 50000 | AB28: 50000 | AD28: 150000 | AF28: 50000 | AH28: 0 | AJ28: 50000 | AL28: 40000 | AN28: 40000 | AP28: 0 | AQ28: 40000 | AR28: 40000 | AT28: =+AS28+AQ28+AO28+AM28+AK28+AI28+AG28+AE28+AC28+AA28+Y28+W28+U28+S28+Q28+O28+M28+K28+I28+G28 -> 40000 | AU28: =+E28-AT28 -> 970000 | AV28: =+AT28-AW28 -> 40000 | AW28: =SUMIF(AX:AX,C28,AY:AY) -> 0 | AX28: 04702942 | AY28: 50000
A29: =+A28+1 -> 25 | C29: 04287813 | D29: ЯТТ Шодманова З. А. хисобварак абонет тулови хис. 459710695 | E29: =+SUM(F29:AR29) -> 960000 | F29: 50000 | H29: 50000 | J29: 50000 | L29: 50000 | N29: 50000 | P29: 50000 | R29: 50000 | T29: 50000 | V29: 50000 | X29: 50000 | Z29: 50000 | AB29: 50000 | AD29: 50000 | AF29: 0 | AG29: 50000 | AH29: 0 | AI29: 50000 | AJ29: 0 | AK29: 50000 | AL29: 40000 | AN29: 40000 | AP29: 40000 | AR29: 40000 | AT29: =+AS29+AQ29+AO29+AM29+AK29+AI29+AG29+AE29+AC29+AA29+Y29+W29+U29+S29+Q29+O29+M29+K29+I29+G29 -> 150000 | AU29: =+E29-AT29 -> 810000 | AV29: =+AT29-AW29 -> 0 | AW29: =SUMIF(AX:AX,C29,AY:AY) -> 150000 | AX29: 04816842 | AY29: 50000
A30: =+A29+1 -> 26 | C30: 04668617 | D30: Пахтакор Лайло Фарм хусусий корхонаси Хисобварак а 300648649 | E30: =+SUM(F30:AR30) -> 960000 | F30: 50000 | H30: 50000 | J30: 50000 | L30: 50000 | N30: 50000 | P30: 50000 | R30: 50000 | T30: 50000 | V30: 50000 | X30: 50000 | Z30: 50000 | AB30: 50000 | AD30: 150000 | AF30: 50000 | AH30: 0 | AJ30: 0 | AL30: 40000 | AN30: 40000 | AP30: 40000 | AR30: 40000 | AT30: =+AS30+AQ30+AO30+AM30+AK30+AI30+AG30+AE30+AC30+AA30+Y30+W30+U30+S30+Q30+O30+M30+K30+I30+G30 -> 0 | AU30: =+E30-AT30 -> 960000 | AV30: =+AT30-AW30 -> 0 | AW30: =SUMIF(AX:AX,C30,AY:AY) -> 0 | AX30: 00273229 | AY30: 50000
A31: =+A30+1 -> 27 | C31: 04768782 | D31: Х Т Турабекова Ойшакар хисобварак абонет тулови хи 601152632 | E31: =+SUM(F31:AR31) -> 960000 | F31: 50000 | H31: 50000 | J31: 50000 | L31: 50000 | N31: 50000 | P31: 50000 | R31: 50000 | T31: 50000 | V31: 50000 | X31: 50000 | Z31: 50000 | AB31: 50000 | AD31: 150000 | AF31: 50000 | AH31: 0 | AJ31: 0 | AL31: 40000 | AN31: 40000 | AP31: 40000 | AR31: 40000 | AT31: =+AS31+AQ31+AO31+AM31+AK31+AI31+AG31+AE31+AC31+AA31+Y31+W31+U31+S31+Q31+O31+M31+K31+I31+G31 -> 0 | AU31: =+E31-AT31 -> 960000 | AV31: =+AT31-AW31 -> 0 | AW31: =SUMIF(AX:AX,C31,AY:AY) -> 0 | AX31: 00284049 | AY31: 50000
A32: =+A31+1 -> 28 | C32: 04202843 | D32: Акраб-Бек ХФ Хисобварак абонтент тулв. буй. Хис % 204104486 | E32: =+SUM(F32:AR32) -> 650000 | F32: 50000 | H32: 50000 | J32: 50000 | L32: 50000 | N32: 50000 | P32: 50000 | R32: 50000 | T32: 50000 | V32: 50000 | X32: 50000 | Z32: 50000 | AB32: 50000 | AD32: 0 | AE32: 50000 | AF32: 0 | AH32: 0 | AJ32: 0 | AL32: 0 | AN32: 0 | AP32: 0 | AR32: 0 | AT32: =+AS32+AQ32+AO32+AM32+AK32+AI32+AG32+AE32+AC32+AA32+Y32+W32+U32+S32+Q32+O32+M32+K32+I32+G32 -> 50000 | AU32: =+E32-AT32 -> 600000 | AV32: =+AT32-AW32 -> 0 | AW32: =SUMIF(AX:AX,C32,AY:AY) -> 50000 | AX32: 04974220 | AY32: 50000
A33: =+A32+1 -> 29 | C33: 04662092 | D33: Кумуш кузгу хусусий корхонаси 300635926 | E33: =+SUM(F33:AR33) -> 250000 | F33: 50000 | H33: 50000 | J33: 50000 | L33: 50000 | N33: 0 | O33: 50000 | P33: 0 | R33: 0 | T33: 0 | V33: 0 | X33: 0 | Z33: 0 | AB33: 0 | AD33: 0 | AF33: 0 | AJ33: 0 | AL33: 0 | AN33: 0 | AP33: 0 | AR33: 0 | AT33: =+AS33+AQ33+AO33+AM33+AK33+AI33+AG33+AE33+AC33+AA33+Y33+W33+U33+S33+Q33+O33+M33+K33+I33+G33 -> 50000 | AU33: =+E33-AT33 -> 200000 | AV33: =+AT33-AW33 -> 0 | AW33: =SUMIF(AX:AX,C33,AY:AY) -> 50000 | AX33: 04665383 | AY33: 50000
A34: =+A33+1 -> 30 | C34: 04713981 | D34: ЯТТ ОТАЖОНОВА МАХПУЗА ШАМСИЕВНА хисобварак абонет 600832657 | E34: =+SUM(F34:AR34) -> 960000 | F34: 50000 | H34: 50000 | J34: 50000 | L34: 50000 | N34: 50000 | P34: 50000 | R34: 50000 | T34: 50000 | V34: 50000 | X34: 50000 | Z34: 50000 | AB34: 50000 | AD34: 100000 | AF34: 50000 | AH34: 0 | AJ34: 50000 | AL34: 40000 | AN34: 40000 | AP34: 40000 | AR34: 40000 | AT34: =+AS34+AQ34+AO34+AM34+AK34+AI34+AG34+AE34+AC34+AA34+Y34+W34+U34+S34+Q34+O34+M34+K34+I34+G34 -> 0 | AU34: =+E34-AT34 -> 960000 | AV34: =+AT34-AW34 -> 0 | AW34: =SUMIF(AX:AX,C34,AY:AY) -> 0 | AX34: 00338189 | AY34: 50000
A35: =+A34+1 -> 31 | C35: 04852372 | D35: PAXTAKOR TILSIMI ХУСУСИЙ КОРХОНАСИ Хисобварак абон 301623821 | E35: =+SUM(F35:AR35) -> 960000 | F35: 50000 | H35: 50000 | J35: 50000 | L35: 50000 | N35: 50000 | P35: 50000 | R35: 50000 | T35: 50000 | V35: 50000 | X35: 50000 | Z35: 50000 | AB35: 50000 | AD35: 100000 | AF35: 50000 | AH35: 0 | AJ35: 50000 | AL35: 40000 | AN35: 40000 | AP35: 40000 | AR35: 40000 | AT35: =+AS35+AQ35+AO35+AM35+AK35+AI35+AG35+AE35+AC35+AA35+Y35+W35+U35+S35+Q35+O35+M35+K35+I35+G35 -> 0 | AU35: =+E35-AT35 -> 960000 | AV35: =+AT35-AW35 -> 0 | AW35: =SUMIF(AX:AX,C35,AY:AY) -> 0 | AX35: 05008930 | AY35: 50000
A36: =+A35+1 -> 32 | C36: 04966319 | D36: ЯТТ Исломов Хуршиджон Убайдуллаевич хисобварак або 488696920 | E36: =+SUM(F36:AR36) -> 920000 | F36: 50000 | H36: 50000 | J36: 50000 | L36: 50000 | N36: 50000 | P36: 50000 | R36: 50000 | T36: 50000 | V36: 50000 | X36: 50000 | Z36: 50000 | AB36: 50000 | AD36: 100000 | AF36: 50000 | AH36: 0 | AJ36: 50000 | AL36: 40000 | AN36: 40000 | AP36: 40000 | AR36: 0 | AT36: =+AS36+AQ36+AO36+AM36+AK36+AI36+AG36+AE36+AC36+AA36+Y36+W36+U36+S36+Q36+O36+M36+K36+I36+G36 -> 0 | AU36: =+E36-AT36 -> 920000 | AV36: =+AT36-AW36 -> 0 | AW36: =SUMIF(AX:AX,C36,AY:AY) -> 0 | AX36: 00421659 | AY36: 50000
A37: =+A36+1 -> 33 | C37: 00269826 | D37: ЯТТ Аминханов Сайд лукмонхон ХР абонент тулови 517824080 | E37: =+SUM(F37:AR37) -> 250000 | F37: 50000 | H37: 50000 | J37: 50000 | L37: 50000 | N37: 50000 | P37: 0 | R37: 0 | T37: 0 | V37: 0 | X37: 0 | Z37: 0 | AB37: 0 | AD37: 0 | AF37: 0 | AJ37: 0 | AL37: 0 | AN37: 0 | AP37: 0 | AR37: 0 | AT37: =+AS37+AQ37+AO37+AM37+AK37+AI37+AG37+AE37+AC37+AA37+Y37+W37+U37+S37+Q37+O37+M37+K37+I37+G37 -> 0 | AU37: =+E37-AT37 -> 250000 | AV37: =+AT37-AW37 -> 0 | AW37: =SUMIF(AX:AX,C37,AY:AY) -> 0 | AX37: 04830180 | AY37: 50000
A38: =+A37+1 -> 34 | C38: 00312114 | D38: ЯТТ Наврузов Отабек Хисобланган бошка фоизсиз даро 411975771 | E38: =+SUM(F38:AR38) -> 300000 | F38: 50000 | H38: 50000 | J38: 0 | L38: 0 | N38: 0 | O38: 50000 | P38: 50000 | R38: 50000 | T38: 50000 | V38: 0 | X38: 0 | Z38: 0 | AB38: 0 | AD38: 0 | AF38: 0 | AJ38: 0 | AL38: 0 | AN38: 0 | AP38: 0 | AR38: 0 | AT38: =+AS38+AQ38+AO38+AM38+AK38+AI38+AG38+AE38+AC38+AA38+Y38+W38+U38+S38+Q38+O38+M38+K38+I38+G38 -> 50000 | AU38: =+E38-AT38 -> 250000 | AV38: =+AT38-AW38 -> 0 | AW38: =SUMIF(AX:AX,C38,AY:AY) -> 50000 | AX38: 04998449 | AY38: 50000
A39: =+A38+1 -> 35 | C39: 00379149 | D39: ЯТТ Садуллаев Санжар 495197921 | E39: =+SUM(F39:AR39) -> 960000 | F39: 50000 | H39: 50000 | J39: 50000 | L39: 50000 | N39: 50000 | P39: 50000 | R39: 50000 | T39: 50000 | V39: 50000 | X39: 50000 | Z39: 50000 | AB39: 50000 | AD39: 100000 | AF39: 50000 | AH39: 0 | AJ39: 0 | AK39: 50000 | AL39: 40000 | AN39: 40000 | AP39: 40000 | AR39: 40000 | AT39: =+AS39+AQ39+AO39+AM39+AK39+AI39+AG39+AE39+AC39+AA39+Y39+W39+U39+S39+Q39+O39+M39+K39+I39+G39 -> 50000 | AU39: =+E39-AT39 -> 910000 | AV39: =+AT39-AW39 -> 0 | AW39: =SUMIF(AX:AX,C39,AY:AY) -> 50000 | AX39: 00289175 | AY39: 50000
A40: =+A39+1 -> 36 | C40: 04706107 | D40: RABBI UL MARXAMAT XUSUSIY KORXONASI 300837911 | E40: =+SUM(F40:AR40) -> 960000 | F40: 50000 | H40: 50000 | J40: 50000 | L40: 50000 | N40: 50000 | P40: 50000 | R40: 50000 | T40: 50000 | V40: 50000 | X40: 50000 | Z40: 50000 | AB40: 50000 | AD40: 100000 | AF40: 50000 | AH40: 0 | AJ40: 50000 | AL40: 40000 | AN40: 40000 | AP40: 40000 | AR40: 40000 | AT40: =+AS40+AQ40+AO40+AM40+AK40+AI40+AG40+AE40+AC40+AA40+Y40+W40+U40+S40+Q40+O40+M40+K40+I40+G40 -> 0 | AU40: =+E40-AT40 -> 960000 | AV40: =+AT40-AW40 -> 0 | AW40: =SUMIF(AX:AX,C40,AY:AY) -> 0 | AX40: 04703595 | AY40: 50000
A41: =+A40+1 -> 37 | C41: 04842463 | D41: Шурик даласи МЧЖ Хисобварак абонтент тулв. буй. Хи 301565482 | E41: =+SUM(F41:AR41) -> 860000 | F41: 50000 | H41: 50000 | J41: 0 | L41: 0 | N41: 0 | O41: 50000 | P41: 50000 | R41: 50000 | T41: 50000 | V41: 50000 | X41: 50000 | Z41: 50000 | AB41: 50000 | AD41: 100000 | AF41: 50000 | AH41: 0 | AJ41: 0 | AK41: 50000 | AL41: 40000 | AN41: 40000 | AP41: 40000 | AR41: 40000 | AT41: =+AS41+AQ41+AO41+AM41+AK41+AI41+AG41+AE41+AC41+AA41+Y41+W41+U41+S41+Q41+O41+M41+K41+I41+G41 -> 100000 | AU41: =+E41-AT41 -> 760000 | AV41: =+AT41-AW41 -> 0 | AW41: =SUMIF(AX:AX,C41,AY:AY) -> 100000 | AX41: 04961636 | AY41: 50000
A42: =+A41+1 -> 38 | C42: 04950772 | D42: Х Т Холиков Шавкат Бердиевич хисобварак абонет тул 410521016 | E42: =+SUM(F42:AR42) -> 960000 | F42: 50000 | H42: 50000 | J42: 50000 | L42: 50000 | N42: 50000 | P42: 50000 | R42: 50000 | T42: 50000 | V42: 50000 | X42: 50000 | Z42: 50000 | AB42: 50000 | AD42: 100000 | AF42: 50000 | AH42: 0 | AJ42: 0 | AK42: 50000 | AL42: 40000 | AN42: 40000 | AP42: 40000 | AR42: 40000 | AT42: =+AS42+AQ42+AO42+AM42+AK42+AI42+AG42+AE42+AC42+AA42+Y42+W42+U42+S42+Q42+O42+M42+K42+I42+G42 -> 50000 | AU42: =+E42-AT42 -> 910000 | AV42: =+AT42-AW42 -> 0 | AW42: =SUMIF(AX:AX,C42,AY:AY) -> 50000 | AX42: 00348893 | AY42: 50000
A43: =+A42+1 -> 39 | C43: 04963108 | D43: ЯТТ Нормуродов Аллаёр Рахмонович хисобварак абонет 602289405 | E43: =+SUM(F43:AR43) -> 960000 | F43: 50000 | H43: 50000 | J43: 50000 | L43: 50000 | N43: 50000 | P43: 50000 | R43: 50000 | T43: 50000 | V43: 50000 | X43: 50000 | Z43: 50000 | AB43: 50000 | AD43: 100000 | AF43: 50000 | AH43: 0 | AJ43: 0 | AK43: 50000 | AL43: 40000 | AN43: 40000 | AP43: 40000 | AR43: 40000 | AT43: =+AS43+AQ43+AO43+AM43+AK43+AI43+AG43+AE43+AC43+AA43+Y43+W43+U43+S43+Q43+O43+M43+K43+I43+G43 -> 50000 | AU43: =+E43-AT43 -> 910000 | AV43: =+AT43-AW43 -> 0 | AW43: =SUMIF(AX:AX,C43,AY:AY) -> 50000 | AX43: 00482550 | AY43: 50000
A44: =+A43+1 -> 40 | C44: 04148607 | D44: YATT BERDINIYAZOV MUZAFFAR XASANOVICH 445795757 | E44: =+SUM(F44:AR44) -> 960000 | F44: 50000 | H44: 50000 | J44: 50000 | L44: 50000 | N44: 50000 | P44: 50000 | R44: 50000 | T44: 50000 | V44: 50000 | X44: 50000 | Z44: 50000 | AB44: 50000 | AD44: 100000 | AF44: 50000 | AH44: 0 | AJ44: 0 | AK44: 50000 | AL44: 40000 | AN44: 40000 | AP44: 40000 | AR44: 40000 | AT44: =+AS44+AQ44+AO44+AM44+AK44+AI44+AG44+AE44+AC44+AA44+Y44+W44+U44+S44+Q44+O44+M44+K44+I44+G44 -> 50000 | AU44: =+E44-AT44 -> 910000 | AV44: =+AT44-AW44 -> 0 | AW44: =SUMIF(AX:AX,C44,AY:AY) -> 50000 | AX44: 00475353 | AY44: 50000
A45: =+A44+1 -> 41 | C45: 04503679 | D45: Хотира-Темирйул хусусий корхонаси Хисобварак абонт 206413235 | E45: =+SUM(F45:AR45) -> 960000 | F45: 50000 | H45: 50000 | J45: 50000 | L45: 50000 | N45: 50000 | P45: 50000 | R45: 50000 | T45: 50000 | V45: 50000 | X45: 50000 | Z45: 50000 | AB45: 50000 | AD45: 100000 | AF45: 50000 | AH45: 0 | AJ45: 0 | AK45: 50000 | AL45: 40000 | AN45: 40000 | AP45: 40000 | AR45: 40000 | AT45: =+AS45+AQ45+AO45+AM45+AK45+AI45+AG45+AE45+AC45+AA45+Y45+W45+U45+S45+Q45+O45+M45+K45+I45+G45 -> 50000 | AU45: =+E45-AT45 -> 910000 | AV45: =+AT45-AW45 -> 0 | AW45: =SUMIF(AX:AX,C45,AY:AY) -> 50000 | AX45: 00476854 | AY45: 50000
A46: =+A45+1 -> 42 | C46: 00252979 | D46: YATT XAMIDOV UCHQUN ABDUGAFFAROVICH 602245056 | E46: =+SUM(F46:AR46) -> 960000 | F46: 50000 | H46: 50000 | J46: 50000 | L46: 50000 | N46: 50000 | P46: 50000 | R46: 50000 | T46: 50000 | V46: 50000 | X46: 50000 | Z46: 50000 | AB46: 50000 | AD46: 100000 | AF46: 50000 | AH46: 0 | AJ46: 0 | AK46: 50000 | AL46: 40000 | AN46: 40000 | AP46: 40000 | AR46: 40000 | AT46: =+AS46+AQ46+AO46+AM46+AK46+AI46+AG46+AE46+AC46+AA46+Y46+W46+U46+S46+Q46+O46+M46+K46+I46+G46 -> 50000 | AU46: =+E46-AT46 -> 910000 | AV46: =+AT46-AW46 -> 0 | AW46: =SUMIF(AX:AX,C46,AY:AY) -> 50000 | AX46: 00479820 | AY46: 50000
A47: =+A46+1 -> 43 | C47: 04702555 | D47: YATT RAXMATULLAYEV M 600778028 | E47: =+SUM(F47:AR47) -> 960000 | F47: 50000 | H47: 50000 | J47: 50000 | L47: 50000 | N47: 50000 | P47: 50000 | R47: 50000 | T47: 50000 | V47: 50000 | X47: 50000 | Z47: 50000 | AB47: 50000 | AD47: 100000 | AF47: 50000 | AH47: 0 | AJ47: 0 | AK47: 50000 | AL47: 40000 | AN47: 40000 | AP47: 40000 | AR47: 40000 | AT47: =+AS47+AQ47+AO47+AM47+AK47+AI47+AG47+AE47+AC47+AA47+Y47+W47+U47+S47+Q47+O47+M47+K47+I47+G47 -> 50000 | AU47: =+E47-AT47 -> 910000 | AV47: =+AT47-AW47 -> 0 | AW47: =SUMIF(AX:AX,C47,AY:AY) -> 50000 | AX47: 00485584 | AY47: 50000
A48: =+A47+1 -> 44 | C48: 04748581 | D48: Х.Т Байзакова Гулчехра Ахатовна хисобварак абонет 601022137 | E48: =+SUM(F48:AR48) -> 960000 | F48: 50000 | H48: 50000 | J48: 50000 | L48: 50000 | N48: 50000 | P48: 50000 | R48: 50000 | T48: 50000 | V48: 50000 | X48: 50000 | Z48: 50000 | AB48: 50000 | AD48: 100000 | AF48: 50000 | AH48: 0 | AJ48: 50000 | AL48: 40000 | AN48: 40000 | AP48: 40000 | AR48: 40000 | AT48: =+AS48+AQ48+AO48+AM48+AK48+AI48+AG48+AE48+AC48+AA48+Y48+W48+U48+S48+Q48+O48+M48+K48+I48+G48 -> 0 | AU48: =+E48-AT48 -> 960000 | AV48: =+AT48-AW48 -> 0 | AW48: =SUMIF(AX:AX,C48,AY:AY) -> 0 | AX48: 00267809 | AY48: 50000
A49: =+A48+1 -> 45 | C49: 04932668 | D49: ЯТТ Хушмуратова Шахло Бегмуродова хисобварак абон 601996753 | E49: =+SUM(F49:AR49) -> 960000 | F49: 50000 | H49: 50000 | J49: 50000 | L49: 50000 | N49: 50000 | P49: 50000 | R49: 50000 | T49: 50000 | V49: 50000 | X49: 50000 | Z49: 50000 | AB49: 50000 | AD49: 100000 | AF49: 50000 | AH49: 0 | AJ49: 50000 | AL49: 40000 | AN49: 40000 | AP49: 40000 | AR49: 40000 | AT49: =+AS49+AQ49+AO49+AM49+AK49+AI49+AG49+AE49+AC49+AA49+Y49+W49+U49+S49+Q49+O49+M49+K49+I49+G49 -> 0 | AU49: =+E49-AT49 -> 960000 | AV49: =+AT49-AW49 -> 0 | AW49: =SUMIF(AX:AX,C49,AY:AY) -> 0 | AX49: 04969839 | AY49: 50000
A50: =+A49+1 -> 46 | C50: 04938134 | D50: Мафтуна-Сабина хусусий корхонаси Хисобварак абонте 302112333 | E50: =+SUM(F50:AR50) -> 640000 | F50: 50000 | H50: 50000 | J50: 50000 | L50: 50000 | N50: 50000 | P50: 50000 | R50: 50000 | T50: 50000 | V50: 50000 | X50: 50000 | Z50: 50000 | AB50: 50000 | AD50: 0 | AF50: 0 | AJ50: 0 | AL50: 0 | AM50: 40000 | AN50: 0 | AP50: 0 | AR50: 0 | AT50: =+AS50+AQ50+AO50+AM50+AK50+AI50+AG50+AE50+AC50+AA50+Y50+W50+U50+S50+Q50+O50+M50+K50+I50+G50 -> 40000 | AU50: =+E50-AT50 -> 600000 | AV50: =+AT50-AW50 -> 40000 | AW50: =SUMIF(AX:AX,C50,AY:AY) -> 0 | AX50: 00520750 | AY50: 50000
A51: =+A50+1 -> 47 | C51: 00208829 | D51: YATT DAVEROV ESON TUYMAEVICH хисобварак абонет тул 602639317 | E51: =+SUM(F51:AR51) -> 960000 | F51: 50000 | H51: 50000 | J51: 50000 | L51: 50000 | N51: 50000 | P51: 50000 | R51: 50000 | T51: 50000 | V51: 50000 | X51: 50000 | Z51: 50000 | AB51: 50000 | AD51: 100000 | AF51: 50000 | AH51: 0 | AJ51: 0 | AK51: 50000 | AL51: 40000 | AN51: 40000 | AP51: 40000 | AR51: 40000 | AT51: =+AS51+AQ51+AO51+AM51+AK51+AI51+AG51+AE51+AC51+AA51+Y51+W51+U51+S51+Q51+O51+M51+K51+I51+G51 -> 50000 | AU51: =+E51-AT51 -> 910000 | AV51: =+AT51-AW51 -> 0 | AW51: =SUMIF(AX:AX,C51,AY:AY) -> 50000 | AX51: 00606994 | AY51: 50000
A52: =+A51+1 -> 48 | C52: 00255635 | D52: Paxtakorning baxti 302705647 | E52: =+SUM(F52:AR52) -> 960000 | F52: 50000 | H52: 50000 | J52: 50000 | L52: 50000 | N52: 50000 | P52: 50000 | R52: 50000 | T52: 50000 | V52: 50000 | X52: 50000 | Z52: 50000 | AB52: 50000 | AD52: 100000 | AF52: 50000 | AH52: 0 | AJ52: 50000 | AL52: 40000 | AN52: 40000 | AP52: 40000 | AR52: 40000 | AT52: =+AS52+AQ52+AO52+AM52+AK52+AI52+AG52+AE52+AC52+AA52+Y52+W52+U52+S52+Q52+O52+M52+K52+I52+G52 -> 0 | AU52: =+E52-AT52 -> 960000 | AV52: =+AT52-AW52 -> 0 | AW52: =SUMIF(AX:AX,C52,AY:AY) -> 0 | AX52: 00606463 | AY52: 50000
A53: =+A52+1 -> 49 | C53: 00369222 | D53: ЯТТ Тулакова Муборак хисобланган бошка фоизсиз дар 506042998 | E53: =+SUM(F53:AR53) -> 960000 | F53: 50000 | H53: 50000 | J53: 50000 | L53: 50000 | N53: 50000 | P53: 50000 | R53: 50000 | T53: 50000 | V53: 50000 | X53: 50000 | Z53: 50000 | AB53: 50000 | AD53: 100000 | AF53: 50000 | AH53: 0 | AJ53: 50000 | AL53: 40000 | AN53: 40000 | AP53: 40000 | AR53: 40000 | AT53: =+AS53+AQ53+AO53+AM53+AK53+AI53+AG53+AE53+AC53+AA53+Y53+W53+U53+S53+Q53+O53+M53+K53+I53+G53 -> 0 | AU53: =+E53-AT53 -> 960000 | AV53: =+AT53-AW53 -> 0 | AW53: =SUMIF(AX:AX,C53,AY:AY) -> 0 | AX53: 00602990 | AY53: 50000
A54: =+A53+1 -> 50 | C54: 00409158 | D54: Олга Мобиле ХК Хисобланган бошка фоизсиз даромадла 303111738 | E54: =+SUM(F54:AR54) -> 450000 | F54: 50000 | H54: 50000 | J54: 50000 | L54: 50000 | N54: 50000 | P54: 50000 | R54: 50000 | T54: 0 | U54: 50000 | V54: 0 | W54: 50000 | X54: 0 | Z54: 0 | AB54: 0 | AD54: 0 | AF54: 0 | AJ54: 0 | AL54: 0 | AN54: 0 | AP54: 0 | AR54: 0 | AT54: =+AS54+AQ54+AO54+AM54+AK54+AI54+AG54+AE54+AC54+AA54+Y54+W54+U54+S54+Q54+O54+M54+K54+I54+G54 -> 100000 | AU54: =+E54-AT54 -> 350000 | AV54: =+AT54-AW54 -> 0 | AW54: =SUMIF(AX:AX,C54,AY:AY) -> 100000 | AX54: 00603444 | AY54: 50000
A55: =+A54+1 -> 51 | C55: 04122009 | D55: ЯТТ СУВАНОВ АТАМУРАД хисобварак абонет тулови хис. 400858265 | E55: =+SUM(F55:AR55) -> 960000 | F55: 50000 | H55: 50000 | J55: 50000 | L55: 50000 | N55: 50000 | P55: 50000 | R55: 50000 | T55: 50000 | V55: 50000 | X55: 50000 | Z55: 50000 | AB55: 50000 | AD55: 150000 | AF55: 50000 | AH55: 0 | AJ55: 0 | AL55: 40000 | AN55: 40000 | AP55: 40000 | AR55: 40000 | AT55: =+AS55+AQ55+AO55+AM55+AK55+AI55+AG55+AE55+AC55+AA55+Y55+W55+U55+S55+Q55+O55+M55+K55+I55+G55 -> 0 | AU55: =+E55-AT55 -> 960000 | AV55: =+AT55-AW55 -> 0 | AW55: =SUMIF(AX:AX,C55,AY:AY) -> 0 | AX55: 04827790 | AY55: 50000
A56: =+A55+1 -> 52 | C56: 04188351 | D56: Х Т Худойназаров Мухиддин хисобварак абонет тулови 447102381 | E56: =+SUM(F56:AR56) -> 250000 | F56: 50000 | H56: 50000 | J56: 50000 | L56: 50000 | N56: 0 | O56: 50000 | P56: 0 | R56: 0 | T56: 0 | V56: 0 | X56: 0 | Z56: 0 | AB56: 0 | AD56: 0 | AF56: 0 | AJ56: 0 | AL56: 0 | AN56: 0 | AP56: 0 | AR56: 0 | AT56: =+AS56+AQ56+AO56+AM56+AK56+AI56+AG56+AE56+AC56+AA56+Y56+W56+U56+S56+Q56+O56+M56+K56+I56+G56 -> 50000 | AU56: =+E56-AT56 -> 200000 | AV56: =+AT56-AW56 -> 0 | AW56: =SUMIF(AX:AX,C56,AY:AY) -> 50000 | AX56: 00397164 | AY56: 50000
A57: =+A56+1 -> 53 | C57: 04434785 | D57: ЖИЗЗАХ БАХОРИ МЧЖ Хисобварак абонтент тулв. буй. Х 205783480 | E57: =+SUM(F57:AR57) -> 1060000 | F57: 50000 | H57: 50000 | J57: 50000 | L57: 50000 | N57: 50000 | P57: 50000 | R57: 50000 | T57: 50000 | V57: 50000 | X57: 50000 | Z57: 100000 | AB57: 100000 | AD57: 150000 | AF57: 50000 | AH57: 0 | AJ57: 0 | AL57: 40000 | AN57: 40000 | AP57: 40000 | AR57: 40000 | AT57: =+AS57+AQ57+AO57+AM57+AK57+AI57+AG57+AE57+AC57+AA57+Y57+W57+U57+S57+Q57+O57+M57+K57+I57+G57 -> 0 | AU57: =+E57-AT57 -> 1060000 | AV57: =+AT57-AW57 -> 0 | AW57: =SUMIF(AX:AX,C57,AY:AY) -> 0 | AX57: 00513654 | AY57: 80000
A58: =+A57+1 -> 54 | C58: 04715738 | D58: ХТ Ботирова Озода хисобварак абонет тулови хис. % 600763925 | E58: =+SUM(F58:AR58) -> 910000 | F58: 50000 | H58: 50000 | J58: 50000 | L58: 50000 | N58: 50000 | P58: 50000 | R58: 50000 | T58: 50000 | V58: 50000 | X58: 50000 | Z58: 50000 | AB58: 50000 | AD58: 100000 | AF58: 0 | AH58: 0 | AJ58: 0 | AK58: 50000 | AL58: 40000 | AN58: 40000 | AP58: 40000 | AR58: 40000 | AT58: =+AS58+AQ58+AO58+AM58+AK58+AI58+AG58+AE58+AC58+AA58+Y58+W58+U58+S58+Q58+O58+M58+K58+I58+G58 -> 50000 | AU58: =+E58-AT58 -> 860000 | AV58: =+AT58-AW58 -> -50000 | AW58: =SUMIF(AX:AX,C58,AY:AY) -> 100000 | AX58: 04783313 | AY58: 90000
A59: =+A58+1 -> 55 | C59: 04728262 | D59: ХТ БЕГМАТОВ ШЕРАЛИ РУСТАМОВИЧ хисобварак абонет ту 470158129 | E59: =+SUM(F59:AR59) -> 960000 | F59: 50000 | H59: 50000 | J59: 50000 | L59: 50000 | N59: 50000 | P59: 50000 | R59: 50000 | T59: 50000 | V59: 50000 | X59: 50000 | Z59: 50000 | AB59: 50000 | AD59: 150000 | AF59: 50000 | AH59: 0 | AJ59: 0 | AL59: 40000 | AN59: 40000 | AP59: 40000 | AR59: 40000 | AT59: =+AS59+AQ59+AO59+AM59+AK59+AI59+AG59+AE59+AC59+AA59+Y59+W59+U59+S59+Q59+O59+M59+K59+I59+G59 -> 0 | AU59: =+E59-AT59 -> 960000 | AV59: =+AT59-AW59 -> 0 | AW59: =SUMIF(AX:AX,C59,AY:AY) -> 0 | AX59: 04833670 | AY59: 90000
A60: =+A59+1 -> 56 | C60: 04855539 | D60: "Хожиакбар Хайдар" хусусий корхонаси Хисобварак аб 301642538 | E60: =+SUM(F60:AR60) -> 880000 | F60: 50000 | H60: 50000 | J60: 50000 | L60: 50000 | N60: 50000 | P60: 50000 | R60: 50000 | T60: 0 | U60: 50000 | V60: 0 | W60: 50000 | X60: 0 | Y60: 50000 | Z60: 0 | AA60: 50000 | AB60: 50000 | AD60: 100000 | AF60: 50000 | AH60: 0 | AJ60: 50000 | AL60: 0 | AM60: 40000 | AN60: 40000 | AP60: 0 | AR60: 0 | AT60: =+AS60+AQ60+AO60+AM60+AK60+AI60+AG60+AE60+AC60+AA60+Y60+W60+U60+S60+Q60+O60+M60+K60+I60+G60 -> 240000 | AU60: =+E60-AT60 -> 640000 | AV60: =+AT60-AW60 -> 40000 | AW60: =SUMIF(AX:AX,C60,AY:AY) -> 200000 | AX60: 00461351 | AY60: 90000
A61: =+A60+1 -> 57 | C61: 00227505 | D61: YATT NORMURATOVA MARZIYA BEKTEMIROVNA хисобварак а 602747246 | E61: =+SUM(F61:AR61) -> 960000 | F61: 50000 | H61: 50000 | J61: 50000 | L61: 50000 | N61: 50000 | P61: 50000 | R61: 50000 | T61: 50000 | V61: 50000 | X61: 50000 | Z61: 50000 | AB61: 50000 | AD61: 150000 | AF61: 50000 | AH61: 0 | AJ61: 0 | AL61: 40000 | AN61: 40000 | AP61: 40000 | AR61: 40000 | AT61: =+AS61+AQ61+AO61+AM61+AK61+AI61+AG61+AE61+AC61+AA61+Y61+W61+U61+S61+Q61+O61+M61+K61+I61+G61 -> 0 | AU61: =+E61-AT61 -> 960000 | AV61: =+AT61-AW61 -> 0 | AW61: =SUMIF(AX:AX,C61,AY:AY) -> 0 | AX61: 00603443 | AY61: 90000
A62: =+A61+1 -> 58 | C62: 00267959 | D62: ЯТТ Окилов Жасур ХР абонент тулови 453248253 | E62: =+SUM(F62:AR62) -> 610000 | F62: 50000 | H62: 50000 | J62: 50000 | L62: 50000 | N62: 50000 | P62: 50000 | R62: 50000 | T62: 50000 | V62: 0 | X62: 0 | Z62: 0 | AB62: 0 | AD62: 0 | AF62: 0 | AJ62: 50000 | AL62: 40000 | AN62: 40000 | AP62: 40000 | AR62: 40000 | AT62: =+AS62+AQ62+AO62+AM62+AK62+AI62+AG62+AE62+AC62+AA62+Y62+W62+U62+S62+Q62+O62+M62+K62+I62+G62 -> 0 | AU62: =+E62-AT62 -> 610000 | AV62: =+AT62-AW62 -> 0 | AW62: =SUMIF(AX:AX,C62,AY:AY) -> 0 | AX62: 00604054 | AY62: 90000
A63: =+A62+1 -> 59 | C63: 00300956 | D63: Комиссионные обязательства CHASHMA TOMCHI MCHJ 302907617 | E63: =+SUM(F63:AR63) -> 250000 | F63: 50000 | H63: 50000 | J63: 50000 | L63: 50000 | N63: 0 | O63: 50000 | P63: 0 | R63: 0 | T63: 0 | V63: 0 | X63: 0 | Z63: 0 | AB63: 0 | AD63: 0 | AF63: 0 | AJ63: 0 | AL63: 0 | AN63: 0 | AP63: 0 | AR63: 0 | AT63: =+AS63+AQ63+AO63+AM63+AK63+AI63+AG63+AE63+AC63+AA63+Y63+W63+U63+S63+Q63+O63+M63+K63+I63+G63 -> 50000 | AU63: =+E63-AT63 -> 200000 | AV63: =+AT63-AW63 -> 0 | AW63: =SUMIF(AX:AX,C63,AY:AY) -> 50000 | AX63: 00549123 | AY63: 90000
A64: =+A63+1 -> 60 | C64: 04145381 | D64: ХТ АШРАПОВА ХОСИЯТ ФАРСАХОНОВНА хисобварак абонет 406715486 | E64: =+SUM(F64:AR64) -> 910000 | F64: 50000 | H64: 50000 | J64: 50000 | L64: 50000 | N64: 50000 | P64: 50000 | R64: 50000 | T64: 50000 | V64: 50000 | X64: 50000 | Z64: 50000 | AB64: 50000 | AD64: 150000 | AF64: 0 | AH64: 0 | AJ64: 0 | AL64: 40000 | AN64: 40000 | AP64: 40000 | AR64: 40000 | AT64: =+AS64+AQ64+AO64+AM64+AK64+AI64+AG64+AE64+AC64+AA64+Y64+W64+U64+S64+Q64+O64+M64+K64+I64+G64 -> 0 | AU64: =+E64-AT64 -> 910000 | AV64: =+AT64-AW64 -> 0 | AW64: =SUMIF(AX:AX,C64,AY:AY) -> 0 | AX64: 04877067 | AY64: 100000
A65: =+A64+1 -> 61 | C65: 04348484 | D65: "Улуг Жамшид" МЧЖ УУХБ Хисобварак абонтент тулв. б 205199051 | E65: =+SUM(F65:AR65) -> 1010000 | F65: 50000 | H65: 50000 | J65: 50000 | L65: 50000 | N65: 50000 | P65: 50000 | R65: 50000 | T65: 50000 | V65: 50000 | X65: 50000 | Z65: 50000 | AB65: 50000 | AD65: 150000 | AF65: 50000 | AH65: 0 | AJ65: 50000 | AL65: 40000 | AN65: 40000 | AP65: 40000 | AR65: 40000 | AT65: =+AS65+AQ65+AO65+AM65+AK65+AI65+AG65+AE65+AC65+AA65+Y65+W65+U65+S65+Q65+O65+M65+K65+I65+G65 -> 0 | AU65: =+E65-AT65 -> 1010000 | AV65: =+AT65-AW65 -> 0 | AW65: =SUMIF(AX:AX,C65,AY:AY) -> 0 | AX65: 04960423 | AY65: 100000
A66: =+A65+1 -> 62 | C66: 04405147 | D66: АЗИЗ-ОЙЛ-ЖАХОН ХУСУСИЙ КОРХОНАСИ Хисобварак абонте 205659791 | E66: =+SUM(F66:AR66) -> 870000 | F66: 50000 | H66: 50000 | J66: 50000 | L66: 50000 | N66: 50000 | P66: 50000 | R66: 50000 | T66: 50000 | V66: 0 | W66: 50000 | X66: 0 | Y66: 50000 | Z66: 0 | AA66: 50000 | AB66: 0 | AC66: 50000 | AD66: 0 | AE66: 50000 | AF66: 0 | AH66: 0 | AI66: 50000 | AJ66: 0 | AK66: 50000 | AL66: 40000 | AN66: 40000 | AP66: 0 | AQ66: 40000 | AR66: 0 | AS66: 40000 | AT66: =+AS66+AQ66+AO66+AM66+AK66+AI66+AG66+AE66+AC66+AA66+Y66+W66+U66+S66+Q66+O66+M66+K66+I66+G66 -> 430000 | AU66: =+E66-AT66 -> 440000 | AV66: =+AT66-AW66 -> -50000 | AW66: =SUMIF(AX:AX,C66,AY:AY) -> 480000 | AX66: 04842463 | AY66: 100000
A67: =+A66+1 -> 63 | C67: 04836229 | D67: Пулат Курилиш инвест МЧЖ Хисобварак абонтент тулв. 301536185 | E67: =+SUM(F67:AR67) -> 960000 | F67: 50000 | H67: 50000 | J67: 50000 | L67: 50000 | N67: 50000 | P67: 50000 | R67: 50000 | T67: 50000 | V67: 50000 | X67: 50000 | Z67: 50000 | AB67: 50000 | AD67: 150000 | AF67: 50000 | AH67: 0 | AJ67: 0 | AL67: 40000 | AN67: 40000 | AP67: 40000 | AR67: 40000 | AT67: =+AS67+AQ67+AO67+AM67+AK67+AI67+AG67+AE67+AC67+AA67+Y67+W67+U67+S67+Q67+O67+M67+K67+I67+G67 -> 0 | AU67: =+E67-AT67 -> 960000 | AV67: =+AT67-AW67 -> 0 | AW67: =SUMIF(AX:AX,C67,AY:AY) -> 0 | AX67: 00409158 | AY67: 100000
A68: =+A67+1 -> 64 | C68: 04980506 | D68: YATT JURAEV SHERALI BOZORBOEVICH 602412251 | E68: =+SUM(F68:AR68) -> 420000 | F68: 50000 | H68: 50000 | J68: 50000 | L68: 0 | N68: 0 | P68: 50000 | R68: 50000 | T68: 50000 | V68: 0 | X68: 0 | Z68: 0 | AB68: 0 | AD68: 0 | AF68: 0 | AJ68: 0 | AL68: 0 | AN68: 0 | AO68: 40000 | AP68: 40000 | AR68: 40000 | AT68: =+AS68+AQ68+AO68+AM68+AK68+AI68+AG68+AE68+AC68+AA68+Y68+W68+U68+S68+Q68+O68+M68+K68+I68+G68 -> 40000 | AU68: =+E68-AT68 -> 380000 | AV68: =+AT68-AW68 -> 0 | AW68: =SUMIF(AX:AX,C68,AY:AY) -> 40000 | AX68: 04715738 | AY68: 100000
A69: =+A68+1 -> 65 | C69: 04987755 | D69: "TOZA MARJON SADOSI" hususiy korxonasi Хисобварак 302338289 | E69: =+SUM(F69:AR69) -> 960000 | F69: 50000 | H69: 50000 | J69: 50000 | L69: 50000 | N69: 50000 | P69: 50000 | R69: 50000 | T69: 50000 | V69: 50000 | X69: 50000 | Z69: 50000 | AB69: 50000 | AD69: 150000 | AF69: 50000 | AH69: 0 | AJ69: 0 | AL69: 40000 | AN69: 40000 | AP69: 40000 | AR69: 40000 | AT69: =+AS69+AQ69+AO69+AM69+AK69+AI69+AG69+AE69+AC69+AA69+Y69+W69+U69+S69+Q69+O69+M69+K69+I69+G69 -> 0 | AU69: =+E69-AT69 -> 960000 | AV69: =+AT69-AW69 -> 0 | AW69: =SUMIF(AX:AX,C69,AY:AY) -> 0 | AX69: 00276806 | AY69: 100000
A70: =+A69+1 -> 66 | C70: 00217328 | D70: YATT RASULOVA MOHIRA BATIRXANOVNA хисобварак абоне 602659577 | E70: =+SUM(F70:AR70) -> 960000 | F70: 50000 | H70: 50000 | J70: 50000 | L70: 50000 | N70: 50000 | P70: 50000 | R70: 50000 | T70: 50000 | V70: 50000 | X70: 50000 | Z70: 50000 | AB70: 50000 | AD70: 150000 | AF70: 50000 | AH70: 0 | AJ70: 0 | AL70: 40000 | AN70: 40000 | AP70: 40000 | AR70: 40000 | AT70: =+AS70+AQ70+AO70+AM70+AK70+AI70+AG70+AE70+AC70+AA70+Y70+W70+U70+S70+Q70+O70+M70+K70+I70+G70 -> 0 | AU70: =+E70-AT70 -> 960000 | AV70: =+AT70-AW70 -> 0 | AW70: =SUMIF(AX:AX,C70,AY:AY) -> 0 | AX70: 00236930 | AY70: 100000
A71: =+A70+1 -> 67 | C71: 00267605 | D71: ЯТТ Шералиев Отабек ХР абонент тулови 515683710 | E71: =+SUM(F71:AR71) -> 960000 | F71: 50000 | H71: 50000 | J71: 50000 | L71: 50000 | N71: 50000 | P71: 50000 | R71: 50000 | T71: 50000 | V71: 50000 | X71: 50000 | Z71: 50000 | AB71: 50000 | AD71: 150000 | AF71: 50000 | AH71: 0 | AJ71: 0 | AL71: 40000 | AN71: 40000 | AP71: 40000 | AR71: 40000 | AT71: =+AS71+AQ71+AO71+AM71+AK71+AI71+AG71+AE71+AC71+AA71+Y71+W71+U71+S71+Q71+O71+M71+K71+I71+G71 -> 0 | AU71: =+E71-AT71 -> 960000 | AV71: =+AT71-AW71 -> 0 | AW71: =SUMIF(AX:AX,C71,AY:AY) -> 0 | AX71: 00420388 | AY71: 100000
A72: =+A71+1 -> 68 | C72: 00268896 | D72: ЯТТ Шодмонкулов Илхом 602179597 | E72: =+SUM(F72:AR72) -> 1010000 | F72: 50000 | H72: 50000 | J72: 50000 | L72: 50000 | N72: 50000 | P72: 50000 | R72: 50000 | T72: 50000 | V72: 50000 | X72: 50000 | Z72: 50000 | AB72: 50000 | AD72: 150000 | AF72: 50000 | AH72: 0 | AJ72: 50000 | AL72: 40000 | AN72: 40000 | AP72: 40000 | AR72: 40000 | AT72: =+AS72+AQ72+AO72+AM72+AK72+AI72+AG72+AE72+AC72+AA72+Y72+W72+U72+S72+Q72+O72+M72+K72+I72+G72 -> 0 | AU72: =+E72-AT72 -> 1010000 | AV72: =+AT72-AW72 -> 0 | AW72: =SUMIF(AX:AX,C72,AY:AY) -> 0 | AX72: 04634303 | AY72: 100000
A73: =+A72+1 -> 69 | C73: 00278717 | D73: YATT MAMANOV KAMOL ABDUNAZAR O' G' LI 602974273 | E73: =+SUM(F73:AR73) -> 960000 | F73: 50000 | H73: 50000 | J73: 50000 | L73: 50000 | N73: 50000 | P73: 50000 | R73: 50000 | T73: 50000 | V73: 50000 | X73: 50000 | Z73: 50000 | AB73: 50000 | AD73: 150000 | AF73: 50000 | AH73: 0 | AJ73: 0 | AL73: 40000 | AN73: 40000 | AP73: 40000 | AR73: 40000 | AT73: =+AS73+AQ73+AO73+AM73+AK73+AI73+AG73+AE73+AC73+AA73+Y73+W73+U73+S73+Q73+O73+M73+K73+I73+G73 -> 0 | AU73: =+E73-AT73 -> 960000 | AV73: =+AT73-AW73 -> 0 | AW73: =SUMIF(AX:AX,C73,AY:AY) -> 0 | AX73: 00293575 | AY73: 100000
A74: =+A73+1 -> 70 | C74: 00387255 | D74: O'ZAGROSUG'URTA DASK (OAJ) PAXTAKOR TUMAN ХР абоне 202155615 | E74: =+SUM(F74:AR74) -> 960000 | F74: 50000 | H74: 50000 | J74: 50000 | L74: 50000 | N74: 50000 | P74: 50000 | R74: 50000 | T74: 50000 | V74: 50000 | X74: 50000 | Z74: 50000 | AB74: 50000 | AD74: 100000 | AF74: 50000 | AH74: 0 | AJ74: 50000 | AL74: 40000 | AN74: 40000 | AP74: 40000 | AR74: 40000 | AT74: =+AS74+AQ74+AO74+AM74+AK74+AI74+AG74+AE74+AC74+AA74+Y74+W74+U74+S74+Q74+O74+M74+K74+I74+G74 -> 0 | AU74: =+E74-AT74 -> 960000 | AV74: =+AT74-AW74 -> 0 | AW74: =SUMIF(AX:AX,C74,AY:AY) -> 0 | AX74: 00266942 | AY74: 100000
A75: =+A74+1 -> 71 | C75: 04667395 | D75: ХТ Суванов Бахтиёр ХР абоент тулови 444691849 | E75: =+SUM(F75:AR75) -> 960000 | F75: 50000 | H75: 50000 | J75: 50000 | L75: 50000 | N75: 50000 | P75: 50000 | R75: 50000 | T75: 50000 | V75: 50000 | X75: 50000 | Z75: 50000 | AB75: 50000 | AD75: 150000 | AF75: 50000 | AH75: 0 | AJ75: 0 | AL75: 40000 | AN75: 40000 | AP75: 40000 | AR75: 40000 | AT75: =+AS75+AQ75+AO75+AM75+AK75+AI75+AG75+AE75+AC75+AA75+Y75+W75+U75+S75+Q75+O75+M75+K75+I75+G75 -> 0 | AU75: =+E75-AT75 -> 960000 | AV75: =+AT75-AW75 -> 0 | AW75: =SUMIF(AX:AX,C75,AY:AY) -> 0 | AX75: 00448127 | AY75: 100000
A76: =+A75+1 -> 72 | C76: 04967280 | D76: ЯТТ УРДУШЕВА САНОБАР ЖАЛОЛОВНА хисобварак абонет т 500626116 | E76: =+SUM(F76:AR76) -> 960000 | F76: 50000 | H76: 50000 | J76: 50000 | L76: 50000 | N76: 50000 | P76: 50000 | R76: 50000 | T76: 50000 | V76: 50000 | X76: 50000 | Z76: 50000 | AB76: 50000 | AD76: 150000 | AF76: 50000 | AH76: 0 | AJ76: 0 | AL76: 40000 | AN76: 40000 | AP76: 40000 | AR76: 40000 | AT76: =+AS76+AQ76+AO76+AM76+AK76+AI76+AG76+AE76+AC76+AA76+Y76+W76+U76+S76+Q76+O76+M76+K76+I76+G76 -> 0 | AU76: =+E76-AT76 -> 960000 | AV76: =+AT76-AW76 -> 0 | AW76: =SUMIF(AX:AX,C76,AY:AY) -> 0 | AX76: 00452093 | AY76: 100000
A77: =+A76+1 -> 73 | C77: 04993948 | D77: YATT KAMALOVA FERUZA INATULLAEVNA 601988525 | E77: =+SUM(F77:AR77) -> 960000 | F77: 50000 | H77: 50000 | J77: 50000 | L77: 50000 | N77: 50000 | P77: 50000 | R77: 50000 | T77: 50000 | V77: 50000 | X77: 50000 | Z77: 50000 | AB77: 50000 | AD77: 150000 | AF77: 50000 | AH77: 0 | AJ77: 0 | AL77: 40000 | AN77: 40000 | AP77: 40000 | AR77: 40000 | AT77: =+AS77+AQ77+AO77+AM77+AK77+AI77+AG77+AE77+AC77+AA77+Y77+W77+U77+S77+Q77+O77+M77+K77+I77+G77 -> 0 | AU77: =+E77-AT77 -> 960000 | AV77: =+AT77-AW77 -> 0 | AW77: =SUMIF(AX:AX,C77,AY:AY) -> 0 | AX77: 00475667 | AY77: 100000
A78: =+A77+1 -> 74 | C78: 05029087 | D78: ЯТТ СУВАНОВ ЖУРАМУРАТ МАЛИКОВИЧ хисобварак абонет 444692174 | E78: =+SUM(F78:AR78) -> 960000 | F78: 50000 | H78: 50000 | J78: 50000 | L78: 50000 | N78: 50000 | P78: 50000 | R78: 50000 | T78: 50000 | V78: 50000 | X78: 50000 | Z78: 50000 | AB78: 50000 | AD78: 150000 | AF78: 50000 | AH78: 0 | AJ78: 0 | AL78: 40000 | AN78: 40000 | AP78: 40000 | AR78: 40000 | AT78: =+AS78+AQ78+AO78+AM78+AK78+AI78+AG78+AE78+AC78+AA78+Y78+W78+U78+S78+Q78+O78+M78+K78+I78+G78 -> 0 | AU78: =+E78-AT78 -> 960000 | AV78: =+AT78-AW78 -> 0 | AW78: =SUMIF(AX:AX,C78,AY:AY) -> 0 | AX78: 00491160 | AY78: 100000
A79: =+A78+1 -> 75 | C79: 00268891 | D79: YATT OQILOV G'AYRAT 453254760 | E79: =+SUM(F79:AR79) -> 100000 | F79: 50000 | H79: 0 | I79: 50000 | J79: 0 | L79: 0 | N79: 0 | P79: 0 | R79: 0 | T79: 0 | V79: 0 | X79: 0 | Z79: 0 | AB79: 0 | AD79: 0 | AF79: 0 | AJ79: 0 | AL79: 0 | AN79: 0 | AP79: 0 | AR79: 0 | AT79: =+AS79+AQ79+AO79+AM79+AK79+AI79+AG79+AE79+AC79+AA79+Y79+W79+U79+S79+Q79+O79+M79+K79+I79+G79 -> 50000 | AU79: =+E79-AT79 -> 50000 | AV79: =+AT79-AW79 -> 50000 | AW79: =SUMIF(AX:AX,C79,AY:AY) -> 0 | AX79: 00496975 | AY79: 100000
A80: =+A79+1 -> 76 | C80: 00276806 | D80: "FORISH MAYSASI" XUSUSIY KORXONASI 302809604 | E80: =+SUM(F80:AR80) -> 500000 | F80: 50000 | H80: 50000 | J80: 50000 | L80: 50000 | N80: 50000 | P80: 50000 | R80: 50000 | T80: 50000 | V80: 0 | W80: 50000 | X80: 0 | Y80: 50000 | Z80: 0 | AB80: 0 | AD80: 0 | AF80: 0 | AJ80: 0 | AL80: 0 | AN80: 0 | AP80: 0 | AR80: 0 | AT80: =+AS80+AQ80+AO80+AM80+AK80+AI80+AG80+AE80+AC80+AA80+Y80+W80+U80+S80+Q80+O80+M80+K80+I80+G80 -> 100000 | AU80: =+E80-AT80 -> 400000 | AV80: =+AT80-AW80 -> 0 | AW80: =SUMIF(AX:AX,C80,AY:AY) -> 100000 | AX80: 00501654 | AY80: 100000
A81: =+A80+1 -> 77 | C81: 00295740 | D81: NAVRO'Z TAOMLARI XUSUSIY KORXONASI 302874184 | E81: =+SUM(F81:AR81) -> 450000 | F81: 50000 | H81: 50000 | J81: 50000 | L81: 50000 | N81: 50000 | P81: 50000 | R81: 50000 | T81: 50000 | V81: 50000 | X81: 0 | Z81: 0 | AB81: 0 | AD81: 0 | AF81: 0 | AJ81: 0 | AL81: 0 | AN81: 0 | AP81: 0 | AR81: 0 | AT81: =+AS81+AQ81+AO81+AM81+AK81+AI81+AG81+AE81+AC81+AA81+Y81+W81+U81+S81+Q81+O81+M81+K81+I81+G81 -> 0 | AU81: =+E81-AT81 -> 450000 | AV81: =+AT81-AW81 -> 0 | AW81: =SUMIF(AX:AX,C81,AY:AY) -> 0 | AX81: 00346318 | AY81: 100000
A82: =+A81+1 -> 78 | C82: 04567573 | D82: Х Т Абдуалимова Каромат хисобварак абонет тулови х 444709276 | E82: =+SUM(F82:AR82) -> 960000 | F82: 50000 | H82: 50000 | J82: 50000 | L82: 50000 | N82: 50000 | P82: 50000 | R82: 50000 | T82: 50000 | V82: 50000 | X82: 50000 | Z82: 50000 | AB82: 50000 | AD82: 150000 | AF82: 50000 | AH82: 0 | AJ82: 0 | AL82: 40000 | AN82: 40000 | AP82: 40000 | AR82: 40000 | AT82: =+AS82+AQ82+AO82+AM82+AK82+AI82+AG82+AE82+AC82+AA82+Y82+W82+U82+S82+Q82+O82+M82+K82+I82+G82 -> 0 | AU82: =+E82-AT82 -> 960000 | AV82: =+AT82-AW82 -> 0 | AW82: =SUMIF(AX:AX,C82,AY:AY) -> 0 | AX82: 00515858 | AY82: 100000
A83: =+A82+1 -> 79 | C83: 04570336 | D83: XT URAKBOEVA ZULFIYA MAMADIYAROVNA Комиссионные об 444598614 | E83: =+SUM(F83:AR83) -> 960000 | F83: 50000 | H83: 50000 | J83: 50000 | L83: 50000 | N83: 50000 | P83: 50000 | R83: 50000 | T83: 50000 | V83: 50000 | X83: 50000 | Z83: 50000 | AB83: 50000 | AD83: 150000 | AF83: 50000 | AH83: 0 | AJ83: 0 | AL83: 40000 | AN83: 40000 | AP83: 40000 | AR83: 40000 | AT83: =+AS83+AQ83+AO83+AM83+AK83+AI83+AG83+AE83+AC83+AA83+Y83+W83+U83+S83+Q83+O83+M83+K83+I83+G83 -> 0 | AU83: =+E83-AT83 -> 960000 | AV83: =+AT83-AW83 -> 0 | AW83: =SUMIF(AX:AX,C83,AY:AY) -> 0 | AX83: 00445654 | AY83: 100000
A84: =+A83+1 -> 80 | C84: 04803299 | D84: ЯТТ Ахмедов Дилшод Шералиевич хисобварак абонет ту 480311606 | E84: =+SUM(F84:AR84) -> 960000 | F84: 50000 | H84: 50000 | J84: 50000 | L84: 50000 | N84: 50000 | P84: 50000 | R84: 50000 | T84: 50000 | V84: 50000 | X84: 50000 | Z84: 50000 | AB84: 50000 | AD84: 150000 | AF84: 50000 | AH84: 0 | AJ84: 0 | AL84: 40000 | AN84: 40000 | AP84: 40000 | AR84: 40000 | AT84: =+AS84+AQ84+AO84+AM84+AK84+AI84+AG84+AE84+AC84+AA84+Y84+W84+U84+S84+Q84+O84+M84+K84+I84+G84 -> 0 | AU84: =+E84-AT84 -> 960000 | AV84: =+AT84-AW84 -> 0 | AW84: =SUMIF(AX:AX,C84,AY:AY) -> 0 | AX84: 00550076 | AY84: 100000
A85: =+A84+1 -> 81 | C85: 04807842 | D85: "Жахонгирбек-Бобурбек" хусусий корхонаси Хисобвара 301347491 | E85: =+SUM(F85:AR85) -> 1010000 | F85: 50000 | H85: 50000 | J85: 50000 | L85: 50000 | N85: 50000 | P85: 50000 | R85: 50000 | T85: 50000 | V85: 50000 | X85: 50000 | Z85: 50000 | AB85: 50000 | AD85: 150000 | AF85: 50000 | AH85: 0 | AJ85: 50000 | AL85: 40000 | AN85: 40000 | AP85: 40000 | AR85: 40000 | AT85: =+AS85+AQ85+AO85+AM85+AK85+AI85+AG85+AE85+AC85+AA85+Y85+W85+U85+S85+Q85+O85+M85+K85+I85+G85 -> 0 | AU85: =+E85-AT85 -> 1010000 | AV85: =+AT85-AW85 -> 0 | AW85: =SUMIF(AX:AX,C85,AY:AY) -> 0 | AX85: 00522709 | AY85: 100000
A86: =+A85+1 -> 82 | C86: 04874757 | D86: Х.Т Сариев Санжар Эшонкулович хисобварак абонет ту 601707184 | E86: =+SUM(F86:AR86) -> 960000 | F86: 50000 | H86: 50000 | J86: 50000 | L86: 50000 | N86: 50000 | P86: 50000 | R86: 50000 | T86: 50000 | V86: 50000 | X86: 50000 | Z86: 50000 | AB86: 50000 | AD86: 100000 | AF86: 50000 | AH86: 0 | AJ86: 0 | AK86: 50000 | AL86: 40000 | AN86: 40000 | AP86: 40000 | AR86: 40000 | AT86: =+AS86+AQ86+AO86+AM86+AK86+AI86+AG86+AE86+AC86+AA86+Y86+W86+U86+S86+Q86+O86+M86+K86+I86+G86 -> 50000 | AU86: =+E86-AT86 -> 910000 | AV86: =+AT86-AW86 -> 0 | AW86: =SUMIF(AX:AX,C86,AY:AY) -> 50000 | AX86: 00548018 | AY86: 100000
A87: =+A86+1 -> 83 | C87: 00236930 | D87: ЯТТ Курбанова Рано Эрйигитовна хисобварак абонет т 602128557 | E87: =+SUM(F87:AR87) -> 860000 | F87: 50000 | H87: 50000 | J87: 50000 | L87: 50000 | N87: 50000 | P87: 50000 | R87: 50000 | T87: 50000 | V87: 50000 | X87: 50000 | Z87: 50000 | AB87: 50000 | AD87: 0 | AE87: 50000 | AF87: 0 | AH87: 0 | AJ87: 50000 | AL87: 40000 | AN87: 40000 | AP87: 40000 | AR87: 40000 | AT87: =+AS87+AQ87+AO87+AM87+AK87+AI87+AG87+AE87+AC87+AA87+Y87+W87+U87+S87+Q87+O87+M87+K87+I87+G87 -> 50000 | AU87: =+E87-AT87 -> 810000 | AV87: =+AT87-AW87 -> -50000 | AW87: =SUMIF(AX:AX,C87,AY:AY) -> 100000 | AX87: 00448858 | AY87: 100000
A88: =+A87+1 -> 84 | C88: 00351332 | D88: YATT NORMURODOV ORIFJON SOBIR O'G'LI 602772106 | E88: =+SUM(F88:AR88) -> 400000 | F88: 50000 | H88: 50000 | J88: 50000 | L88: 50000 | N88: 50000 | P88: 50000 | R88: 50000 | T88: 50000 | V88: 0 | X88: 0 | Z88: 0 | AB88: 0 | AD88: 0 | AF88: 0 | AJ88: 0 | AL88: 0 | AN88: 0 | AP88: 0 | AR88: 0 | AT88: =+AS88+AQ88+AO88+AM88+AK88+AI88+AG88+AE88+AC88+AA88+Y88+W88+U88+S88+Q88+O88+M88+K88+I88+G88 -> 0 | AU88: =+E88-AT88 -> 400000 | AV88: =+AT88-AW88 -> 0 | AW88: =SUMIF(AX:AX,C88,AY:AY) -> 0 | AX88: 04405841 | AY88: 100000
A89: =+A88+1 -> 85 | C89: 04698452 | D89: Х Т Эшкуватов Кахрамон Шукурович хисобварак абонет 600755658 | E89: =+SUM(F89:AR89) -> 960000 | F89: 50000 | H89: 50000 | J89: 50000 | L89: 50000 | N89: 50000 | P89: 50000 | R89: 50000 | T89: 50000 | V89: 50000 | X89: 50000 | Z89: 50000 | AB89: 50000 | AD89: 150000 | AF89: 50000 | AH89: 0 | AJ89: 0 | AL89: 40000 | AN89: 40000 | AP89: 40000 | AR89: 40000 | AT89: =+AS89+AQ89+AO89+AM89+AK89+AI89+AG89+AE89+AC89+AA89+Y89+W89+U89+S89+Q89+O89+M89+K89+I89+G89 -> 0 | AU89: =+E89-AT89 -> 960000 | AV89: =+AT89-AW89 -> 0 | AW89: =SUMIF(AX:AX,C89,AY:AY) -> 0 | AX89: 00519448 | AY89: 100000
A90: =+A89+1 -> 86 | C90: 05004183 | D90: ЯТТ Седиёров Шерзод Абдумизамович 504077679 | E90: =+SUM(F90:AR90) -> 860000 | F90: 50000 | H90: 50000 | J90: 50000 | L90: 50000 | N90: 50000 | P90: 50000 | R90: 50000 | T90: 50000 | V90: 0 | X90: 0 | Y90: 50000 | Z90: 0 | AB90: 0 | AC90: 50000 | AD90: 0 | AE90: 50000 | AF90: 0 | AG90: 50000 | AH90: 0 | AI90: 50000 | AJ90: 0 | AK90: 50000 | AL90: 40000 | AN90: 40000 | AP90: 40000 | AR90: 40000 | AT90: =+AS90+AQ90+AO90+AM90+AK90+AI90+AG90+AE90+AC90+AA90+Y90+W90+U90+S90+Q90+O90+M90+K90+I90+G90 -> 300000 | AU90: =+E90-AT90 -> 560000 | AV90: =+AT90-AW90 -> 0 | AW90: =SUMIF(AX:AX,C90,AY:AY) -> 300000 | AX90: 00598115 | AY90: 100000
A91: =+A90+1 -> 87 | C91: 04702942 | D91: Х Т Курбонов Хикматулла Мардиевич хисобварак абоне 409561725 | E91: =+SUM(F91:AR91) -> 350000 | F91: 0 | G91: 50000 | H91: 50000 | J91: 50000 | L91: 50000 | N91: 0 | P91: 50000 | R91: 50000 | T91: 50000 | V91: 0 | X91: 0 | Z91: 0 | AB91: 0 | AD91: 0 | AF91: 0 | AJ91: 0 | AL91: 0 | AN91: 0 | AP91: 0 | AR91: 0 | AT91: =+AS91+AQ91+AO91+AM91+AK91+AI91+AG91+AE91+AC91+AA91+Y91+W91+U91+S91+Q91+O91+M91+K91+I91+G91 -> 50000 | AU91: =+E91-AT91 -> 300000 | AV91: =+AT91-AW91 -> 0 | AW91: =SUMIF(AX:AX,C91,AY:AY) -> 50000 | AX91: 04565617 | AY91: 100000
A92: =+A91+1 -> 88 | C92: 04816842 | D92: Зиё-Ислохат адвокатлик фирмаси Хисобварак абонтент 207042128 | E92: =+SUM(F92:AR92) -> 960000 | F92: 50000 | H92: 50000 | J92: 50000 | L92: 50000 | N92: 50000 | P92: 50000 | R92: 50000 | T92: 50000 | V92: 50000 | X92: 50000 | Z92: 50000 | AB92: 50000 | AD92: 100000 | AF92: 50000 | AH92: 0 | AJ92: 0 | AK92: 50000 | AL92: 40000 | AN92: 40000 | AP92: 40000 | AR92: 40000 | AT92: =+AS92+AQ92+AO92+AM92+AK92+AI92+AG92+AE92+AC92+AA92+Y92+W92+U92+S92+Q92+O92+M92+K92+I92+G92 -> 50000 | AU92: =+E92-AT92 -> 910000 | AV92: =+AT92-AW92 -> 0 | AW92: =SUMIF(AX:AX,C92,AY:AY) -> 50000 | AX92: 00391187 | AY92: 140000
A93: =+A92+1 -> 89 | C93: 00273229 | D93: "YONG'INNI OLDINI OLISH SERVIS" SHO'BA KORXONASI 302784337 | E93: =+SUM(F93:AR93) -> 350000 | F93: 0 | H93: 50000 | J93: 50000 | L93: 50000 | N93: 50000 | P93: 50000 | R93: 50000 | T93: 0 | V93: 0 | X93: 0 | Z93: 0 | AB93: 0 | AD93: 0 | AE93: 50000 | AF93: 0 | AJ93: 0 | AL93: 0 | AN93: 0 | AP93: 0 | AR93: 0 | AT93: =+AS93+AQ93+AO93+AM93+AK93+AI93+AG93+AE93+AC93+AA93+Y93+W93+U93+S93+Q93+O93+M93+K93+I93+G93 -> 50000 | AU93: =+E93-AT93 -> 300000 | AV93: =+AT93-AW93 -> 0 | AW93: =SUMIF(AX:AX,C93,AY:AY) -> 50000 | AX93: 05005098 | AY93: 140000
A94: =+A93+1 -> 90 | C94: 00284049 | D94: YATT JABBAROV XONDAMIR OYBEK O'G'LI 602986495 | E94: =+SUM(F94:AR94) -> 440000 | F94: 50000 | H94: 50000 | J94: 50000 | L94: 50000 | N94: 50000 | P94: 50000 | R94: 50000 | T94: 50000 | V94: 0 | X94: 0 | Z94: 0 | AB94: 0 | AD94: 0 | AF94: 0 | AJ94: 0 | AL94: 0 | AN94: 0 | AO94: 40000 | AP94: 0 | AR94: 0 | AT94: =+AS94+AQ94+AO94+AM94+AK94+AI94+AG94+AE94+AC94+AA94+Y94+W94+U94+S94+Q94+O94+M94+K94+I94+G94 -> 40000 | AU94: =+E94-AT94 -> 400000 | AV94: =+AT94-AW94 -> -10000 | AW94: =SUMIF(AX:AX,C94,AY:AY) -> 50000 | AX94: 04287813 | AY94: 150000
A95: =+A94+1 -> 91 | C95: 00420388 | D95: ЖАХОН ГАЗ СЕРВИС Хисобланган бошка фоизсиз даромад 302909241 | E95: =+SUM(F95:AR95) -> 400000 | F95: 0 | H95: 0 | I95: 50000 | J95: 50000 | L95: 50000 | N95: 0 | P95: 50000 | R95: 50000 | T95: 50000 | V95: 0 | W95: 50000 | X95: 50000 | Z95: 0 | AB95: 0 | AD95: 0 | AF95: 0 | AJ95: 0 | AL95: 0 | AN95: 0 | AP95: 0 | AR95: 0 | AT95: =+AS95+AQ95+AO95+AM95+AK95+AI95+AG95+AE95+AC95+AA95+Y95+W95+U95+S95+Q95+O95+M95+K95+I95+G95 -> 100000 | AU95: =+E95-AT95 -> 300000 | AV95: =+AT95-AW95 -> 0 | AW95: =SUMIF(AX:AX,C95,AY:AY) -> 100000 | AX95: 00410614 | AY95: 150000
A96: =+A95+1 -> 92 | C96: 04974220 | D96: ЯТТ Абдулхакимов Мамадиёр Алимович хисобварак абон 477702934 | E96: =+SUM(F96:AR96) -> 960000 | F96: 50000 | H96: 50000 | J96: 50000 | L96: 50000 | N96: 50000 | P96: 50000 | R96: 50000 | T96: 50000 | V96: 50000 | X96: 50000 | Z96: 50000 | AB96: 50000 | AD96: 100000 | AF96: 50000 | AH96: 0 | AJ96: 0 | AK96: 50000 | AL96: 40000 | AN96: 40000 | AP96: 40000 | AR96: 40000 | AT96: =+AS96+AQ96+AO96+AM96+AK96+AI96+AG96+AE96+AC96+AA96+Y96+W96+U96+S96+Q96+O96+M96+K96+I96+G96 -> 50000 | AU96: =+E96-AT96 -> 910000 | AV96: =+AT96-AW96 -> 0 | AW96: =SUMIF(AX:AX,C96,AY:AY) -> 50000 | AX96: 04927464 | AY96: 150000
A97: =+A96+1 -> 93 | C97: 00294084 | D97: YAGONA KRISTAL XUSUSIY KORXONASI 302872805 | E97: =+SUM(F97:AR97) -> 960000 | F97: 50000 | H97: 50000 | J97: 50000 | L97: 50000 | N97: 50000 | P97: 50000 | R97: 50000 | T97: 50000 | V97: 50000 | X97: 50000 | Z97: 50000 | AB97: 50000 | AD97: 150000 | AF97: 50000 | AH97: 0 | AJ97: 0 | AL97: 40000 | AN97: 40000 | AP97: 40000 | AR97: 40000 | AT97: =+AS97+AQ97+AO97+AM97+AK97+AI97+AG97+AE97+AC97+AA97+Y97+W97+U97+S97+Q97+O97+M97+K97+I97+G97 -> 0 | AU97: =+E97-AT97 -> 960000 | AV97: =+AT97-AW97 -> 0 | AW97: =SUMIF(AX:AX,C97,AY:AY) -> 0 | AX97: 04151792 | AY97: 150000
A98: =+A97+1 -> 94 | C98: 00269479 | D98: ЯТТ Гаппаров Темур ХР абонент тулови 602613659 | E98: =+SUM(F98:AR98) -> 960000 | F98: 50000 | H98: 50000 | J98: 50000 | L98: 50000 | N98: 50000 | P98: 50000 | R98: 50000 | T98: 50000 | V98: 0 | X98: 0 | Z98: 150000 | AB98: 50000 | AD98: 150000 | AF98: 50000 | AH98: 0 | AJ98: 0 | AL98: 40000 | AN98: 40000 | AP98: 40000 | AR98: 40000 | AT98: =+AS98+AQ98+AO98+AM98+AK98+AI98+AG98+AE98+AC98+AA98+Y98+W98+U98+S98+Q98+O98+M98+K98+I98+G98 -> 0 | AU98: =+E98-AT98 -> 960000 | AV98: =+AT98-AW98 -> 0 | AW98: =SUMIF(AX:AX,C98,AY:AY) -> 0 | AX98: 00297038 | AY98: 150000
A99: =+A98+1 -> 95 | C99: 00402301 | D99: YATT MAXMUDOV JAMSHID Хисобланган бошка фоизсиз да 603235598 | E99: =+SUM(F99:AR99) -> 350000 | F99: 50000 | H99: 50000 | J99: 50000 | L99: 50000 | N99: 50000 | P99: 50000 | R99: 50000 | T99: 0 | V99: 0 | X99: 0 | Z99: 0 | AB99: 0 | AD99: 0 | AF99: 0 | AJ99: 0 | AL99: 0 | AN99: 0 | AP99: 0 | AR99: 0 | AT99: =+AS99+AQ99+AO99+AM99+AK99+AI99+AG99+AE99+AC99+AA99+Y99+W99+U99+S99+Q99+O99+M99+K99+I99+G99 -> 0 | AU99: =+E99-AT99 -> 350000 | AV99: =+AT99-AW99 -> 0 | AW99: =SUMIF(AX:AX,C99,AY:AY) -> 0 | AX99: 00537669 | AY99: 150000
A100: =+A99+1 -> 96 | C100: 00410614 | D100: ЯТТ Муродов Шавкат Маманович 509532457 | E100: =+SUM(F100:AR100) -> 600000 | F100: 0 | G100: 50000 | H100: 50000 | J100: 50000 | L100: 50000 | N100: 50000 | P100: 50000 | R100: 50000 | T100: 50000 | V100: 50000 | X100: 50000 | Z100: 0 | AA100: 50000 | AB100: 0 | AC100: 50000 | AD100: 0 | AF100: 0 | AH100: 0 | AJ100: 0 | AL100: 0 | AN100: 0 | AP100: 0 | AR100: 0 | AT100: =+AS100+AQ100+AO100+AM100+AK100+AI100+AG100+AE100+AC100+AA100+Y100+W100+U100+S100+Q100+O100+M100+K100+I100+G100 -> 150000 | AU100: =+E100-AT100 -> 450000 | AV100: =+AT100-AW100 -> 0 | AW100: =SUMIF(AX:AX,C100,AY:AY) -> 150000 | AX100: 00518032 | AY100: 150000
A101: =+A100+1 -> 97 | C101: 00379254 | D101: ADHAM-AZIZ МЧЖ Хисобланган бошка фоизсиз даромадла 303021328 | E101: =+SUM(F101:AR101) -> 450000 | F101: 50000 | H101: 50000 | J101: 50000 | L101: 50000 | N101: 50000 | P101: 50000 | R101: 50000 | T101: 50000 | V101: 0 | W101: 50000 | X101: 0 | Z101: 0 | AB101: 0 | AD101: 0 | AF101: 0 | AJ101: 0 | AL101: 0 | AN101: 0 | AP101: 0 | AR101: 0 | AT101: =+AS101+AQ101+AO101+AM101+AK101+AI101+AG101+AE101+AC101+AA101+Y101+W101+U101+S101+Q101+O101+M101+K101+I101+G101 -> 50000 | AU101: =+E101-AT101 -> 400000 | AV101: =+AT101-AW101 -> 50000 | AW101: =SUMIF(AX:AX,C101,AY:AY) -> 0 | AX101: 05007437 | AY101: 150000
A102: =+A101+1 -> 98 | C102: 04665383 | D102: "Хидирбоев Хайрулла" хусусий корхонаси Хисобварак 300640059 | E102: =+SUM(F102:AR102) -> 1010000 | F102: 50000 | H102: 50000 | J102: 50000 | L102: 50000 | N102: 50000 | P102: 50000 | R102: 50000 | T102: 50000 | V102: 50000 | X102: 50000 | Z102: 50000 | AB102: 50000 | AD102: 150000 | AF102: 50000 | AH102: 0 | AJ102: 50000 | AL102: 40000 | AN102: 40000 | AP102: 40000 | AR102: 40000 | AT102: =+AS102+AQ102+AO102+AM102+AK102+AI102+AG102+AE102+AC102+AA102+Y102+W102+U102+S102+Q102+O102+M102+K102+I102+G102 -> 0 | AU102: =+E102-AT102 -> 1010000 | AV102: =+AT102-AW102 -> -50000 | AW102: =SUMIF(AX:AX,C102,AY:AY) -> 50000 | AX102: 05008225 | AY102: 150000
...

Sheet 5.омборхона
M1: 5-жадвал
A2: =""&(Шаблон!B1)&"нинг "&(Шаблон!B2)&" вилояти "&(Шаблон!B3)&" филиалида 19921-''омбордаги КБ ва ТЭБ'' ҳамда 16561-''Омбордаги асосий воситалар''ни 2016 йил 2 ноябр ҳолатига хатлов натижалари тўғрисида" -> АТ "Халқ банк"нинг Фаргона вилояти вилояти Бешариқ филиали филиалида 19921-''омбордаги КБ ва ТЭБ'' ҳамда 16561-''Омбордаги асосий воситалар''ни 2016 йил 2 ноябр ҳолатига хатлов натижалари тўғрисида
A3: М А Ъ Л У М О Т
M4: (сўмда)
A5: Т/Р | B5: Бойликлар номи | C5: Ўлчов бирлиги | D5: 2017 йил 16 январ ҳолатига баланс бўйича қолдиқ | G5: 2017 йил 09 феврал ҳолатига хатловдан кейинги қолдиқ | J5: Фарқи | M5: Изоҳ
D6: сони | E6: баҳоси | F6: жами суммаси | G6: сони | H6: баҳоси | I6: жами суммаси | J6: сони | K6: баҳоси | L6: жами суммаси
A7: А | B7: Б | C7: 1 | D7: 2 | E7: 3 | F7: 4 | G7: 5 | H7: 6 | I7: 7 | J7: 8 | K7: 9 | L7: 10 | M7: 11
A8: 1 | B8: А 4 форматдаги ок когоз олиш учун утказилди | C8: КИЛОГРАММ | D8: 80 | E8: 5000 | F8: 400000 | G8: =+D8*E8-F8 -> 0 | H8: 5000 | I8: =+G8*H8 -> 0 | J8: =+D8-G8 -> 80 | K8: =+E8-H8 -> 0 | L8: =+F8-I8 -> 400000
A9: =+A8+1 -> 2 | B9: Скоросшиватель олиш учун уткащзилди | C9: ШТУКА | D9: 300 | E9: 100 | F9: 30000 | G9: =+D9*E9-F9 -> 0 | H9: 100 | I9: =+G9*H9 -> 0 | J9: =+D9-G9 -> 300 | K9: =+E9-H9 -> 0 | L9: =+F9-I9 -> 30000
A10: =+A9+1 -> 3 | B10: Иш журнали олиш учун утказилди | C10: ШТУКА | D10: 4 | E10: 5000 | F10: 20000 | G10: =+D10*E10-F10 -> 0 | H10: 5000 | I10: =+G10*H10 -> 0 | J10: =+D10-G10 -> 4 | K10: =+E10-H10 -> 0 | L10: =+F10-I10 -> 20000
A11: =+A10+1 -> 4 | B11: Рулон когозолиш учун утказилди | C11: КИЛОГРАММ | D11: 100 | E11: 3800 | F11: 380000 | G11: =+D11*E11-F11 -> 0 | H11: 3800 | I11: =+G11*H11 -> 0 | J11: =+D11-G11 -> 100 | K11: =+E11-H11 -> 0 | L11: =+F11-I11 -> 380000
A12: =+A11+1 -> 5 | B12: Ручка олиш учун утказилди | C12: ШТУКА | D12: 100 | E12: 600 | F12: 60000 | G12: =+D12*E12-F12 -> 0 | H12: 600 | I12: =+G12*H12 -> 0 | J12: =+D12-G12 -> 100 | K12: =+E12-H12 -> 0 | L12: =+F12-I12 -> 60000
A13: =+A12+1 -> 6 | B13: Шартномага асосан оракол хизмати учун утказилди | C13: ШТУКА | D13: 5 | E13: 34000 | F13: 170000 | G13: =+D13*E13-F13 -> 0 | H13: 34000 | I13: =+G13*H13 -> 0 | J13: =+D13-G13 -> 5 | K13: =+E13-H13 -> 0 | L13: =+F13-I13 -> 170000
A14: =+A13+1 -> 7 | B14: Информационные таблички | C14: ШТУКА | D14: 1 | E14: 12000 | F14: 12000 | G14: =+D14*E14-F14 -> 0 | H14: 12000 | I14: =+G14*H14 -> 0 | J14: =+D14-G14 -> 1 | K14: =+E14-H14 -> 0 | L14: =+F14-I14 -> 12000
A15: =+A14+1 -> 8 | B15: Тадбиркорлик фаолияти конунчилиги 1-том | C15: ШТУКА | D15: 2 | E15: 8000 | F15: 16000 | G15: =+D15*E15-F15 -> 0 | H15: 8000 | I15: =+G15*H15 -> 0 | J15: =+D15-G15 -> 2 | K15: =+E15-H15 -> 0 | L15: =+F15-I15 -> 16000
A16: =+A15+1 -> 9 | B16: Тадбиркорлик фаолияти конунчилиги 2-том | C16: ШТУКА | D16: 2 | E16: 8000 | F16: 16000 | G16: =+D16*E16-F16 -> 0 | H16: 8000 | I16: =+G16*H16 -> 0 | J16: =+D16-G16 -> 2 | K16: =+E16-H16 -> 0 | L16: =+F16-I16 -> 16000
A17: =+A16+1 -> 10 | B17: квартальный календарь + лак (сетка 80гр.,28,7*67см) | C17: ШТУКА | D17: 3 | E17: 22000 | F17: 66000 | G17: =+D17*E17-F17 -> 0 | H17: 22000 | I17: =+G17*H17 -> 0 | J17: =+D17-G17 -> 3 | K17: =+E17-H17 -> 0 | L17: =+F17-I17 -> 66000
A18: =+A17+1 -> 11 | B18: книга "Бош максадимиз-иктисодиётимизда олиб борилаётган..." И.Каримов | C18: ШТУКА | D18: 3 | E18: 1740 | F18: 5220 | G18: =+D18*E18-F18 -> 0 | H18: 1740 | I18: =+G18*H18 -> 0 | J18: =+D18-G18 -> 3 | K18: =+E18-H18 -> 0 | L18: =+F18-I18 -> 5220
A19: =+A18+1 -> 12 | B19: конверт дарчасиз | C19: ШТУКА | D19: 1000 | E19: 160 | F19: 160000 | G19: =+D19*E19-F19 -> 0 | H19: 160 | I19: =+G19*H19 -> 0 | J19: =+D19-G19 -> 1000 | K19: =+E19-H19 -> 0 | L19: =+F19-I19 -> 160000
A20: =+A19+1 -> 13 | B20: настенный календарь (А1,200гр, 4+0,лак) | C20: ШТУКА | D20: 3 | E20: 4000 | F20: 12000 | G20: =+D20*E20-F20 -> 0 | H20: 4000 | I20: =+G20*H20 -> 0 | J20: =+D20-G20 -> 3 | K20: =+E20-H20 -> 0 | L20: =+F20-I20 -> 12000
... A22: =+A21+1 -> 15 | B22: папка с карманом (А4,4+0,300гр.лак) | C22: ШТУКА | D22: 3 | E22: 2000 | F22: 6000 | G22: =+D22*E22-F22 -> 0 | H22: 2000 | I22: =+G22*H22 -> 0 | J22: =+D22-G22 -> 3 | K22: =+E22-H22 -> 0 | L22: =+F22-I22 -> 6000
A23: =+A22+1 -> 16 | B23: пенсионные книжки | C23: ШТУКА | D23: 2100 | E23: 1659 | F23: 3483900 | G23: 2085 | H23: 1659 | I23: =+G23*H23 -> 3459015 | J23: =+D23-G23 -> 15 | K23: =+E23-H23 -> 0 | L23: =+F23-I23 -> 24885
A24: =+A23+1 -> 17 | B24: МПК клиент | C24: ШТУКА | D24: 100 | E24: 11267.62 | F24: 1126762 | G24: 0 | H24: 11267.62 | I24: =+G24*H24 -> 0 | J24: =+D24-G24 -> 100 | K24: =+E24-H24 -> 0 | L24: =+F24-I24 -> 1126762
B25: Жами 19921 ҳисобварағи | C25: х | D25: =SUM(D8:D24) -> 3809 | E25: =SUM(E8:E24) -> 130826.62 | F25: =SUM(F8:F24) -> 5998382 | G25: =SUM(G8:G24) -> 2085 | H25: =SUM(H8:H24) -> 130826.62 | I25: =SUM(I8:I24) -> 3459015 | J25: =SUM(J8:J24) -> 1724 | K25: =SUM(K8:K24) -> 0 | L25: =SUM(L8:L24) -> 2539367 | M25: х
B28: =""&(Шаблон!B1)&"нинг Ички Аудит" -> АТ "Халқ банк"нинг Ички Аудит
B29: Департаменти бош мутахассиси: | I29: =Шаблон!B13 -> А.Ҳазратқулов
B31: =""&(Шаблон!B1)&" "&(Шаблон!B2)&" вилояти " -> АТ "Халқ банк" Фаргона вилояти вилояти
B32: =""&(Шаблон!B3)&" филиал бошқарувчиси:" -> Бешариқ филиали филиал бошқарувчиси: | I32: =Шаблон!B5 -> _____________
B34: Бош бухгалтери: | I34: =Шаблон!B8 -> _____________

Sheet 7,ВАШ
H1: 7-жадвал
A2: =""&(Шаблон!B1)&"нинг "&(Шаблон!B2)&" вилоят бошқармаси "&(Шаблон!B3)&" филиалида ташкил этилган №"&(Шаблон!B12)&"-сонли валюта айирбошлаш шахобчаси фаолиятининг қонунчилик талабларига мутаносиблигини текшириш" -> АТ "Халқ банк"нинг Фаргона вилояти вилоят бошқармаси Бешариқ филиали филиалида ташкил этилган №________-сонли валюта айирбошлаш шахобчаси фаолиятининг қонунчилик талабларига мутаносиблигини текшириш
A3: ДАЛОЛАТНОМАСИ
B5: 11 июн 2013 йил
C7: Текшириш жараёнида қайд этилди:
C9: 1. Миллий валютада
A10: Банк кассасидан олинган бўнак | B10: Кун давомида текшириш вақтигача бўлган операция | F10: Текшириш вақтида мавжуд сумма
B12: Олинган | D12: Ишлатилган
C15: 2. Накд хорижий валюта
A16: Банк кассасидан олинган бўнак | B16: Кун давомида текшириш вақтигача бўлган операция | F16: Текшириш вақтида мавжуд чет эл валютаси
B18: Олинган | D18: Ишлатилган
C22: 3. Катъий хисобда турувчи бланклар
A23: Форма № | B23: Қатъий ҳисобда турувчи бланкалар | E23: Текширув охирида мавжуд бўлган бланкалар
B24: Олинган | C24: Ишлатилган | D24: Бузилган
A25: 09002
A26: 09006
A27: 09007
A30: Қатъий ҳисобда турувчи бланкалар ва моддий бойликларни сақлаш қоидаларига амал қилиниши, реестрларни ўз вақтида ва тўғри тўлдирилиши, № 09002 ва № 09007 шаклдаги маълумотнома ва бошқа ҳужжатларни тузилишининг тўғрилиги:
A32: №09002 ва №09007-шакл бланкалар текшириш кунига ВАШ да мавжудлиги аниқланди. Чет эл валюталарини сотиш ва сотиб олишда фойдаланиладиган №09002 ва №09007-шакл сертификат бланкалари лотин алифбосида компютерда тўлдирилган.
A34: Валюта айирбошлаш шахобчасининг Ўзбекистон Республикаси Марказий банки томонидан тасдиқланган 2002 йил 21 февралдаги № 505-сонли "Валюта айирбошлаш шахобчаси тўғрисида"ги Низом талабларига мувофиқлиги:
A35: т\р | B35: Жихоз ва талаблар | F35: Изох
A36: 1 | B36: Компъютер
A37: 2 | B37: Принтер
A38: 3 | B38: Калькулятор
A39: 4 | B39: Пул санаш машинкаси
A40: 5 | B40: Детектор
A41: 6 | B41: Телефон тармоғи
A42: 7 | B42: Икки ярусли темир сейф
A43: 8 | B43: Ўт ўчириш системаси
A44: 9 | B44: Фавқулотта ҳолат ташвиш тугмачаси
A45: 10 | B45: VPN Client дастури
A46: 11 | B46: Мижозлар учун маълумот пештахтаси
A47: 12 | B47: Меъёрий ҳужжатлар тўплами
... A52: 17 | B52: Нусха кўчириш апарати
A54: Текширув натижаси:
B57: =""&([1]Шаблон!B1)&"нинг Ички Аудит" -> "Агробанк" ОАТБнинг Ички Аудит
B58: Департаменти бош мутахассиси: | G58: =[1]Шаблон!B13 -> У.Р.Очилов
B60: =""&(Шаблон!B1)&" "&(Шаблон!B2)&" вилоят бошқармаси" -> АТ "Халқ банк" Фаргона вилояти вилоят бошқармаси
B61: =""&([1]Шаблон!B3)&" филиал бошқарувчиси:" -> Ҳудудий филиал бошқарувчиси: | G61: А.Х.Бўронов
B63: Бош бухгалтери: | G63: У.Б.Тўрақулов
B65: ВАШ кассири:

Sheet Юридек хужжат
B7: № | C7: УК | D7: Мижознинг номи | E7: санаси | F7: Ариза | G7: Низоми | H7: Гувохномаси | I7: Паспорт нусхаси рахбар | J7: Паспорт нусхаси бухгалтер
A8: 20208000800424370001 | B8: 1 | C8: 00424370 | D8: "Dang''ara otsenka" масъуляти чекланган жамияти | E8: 42032
A9: 20208000404959848001 | B9: =+B8+1 -> 2 | C9: 04959848 | D9: "Дангара мукаммал инвест савдо" МЧЖ | E9: 42032
A10: 20208000200426663001 | B10: =+B9+1 -> 3 | C10: 00426663 | D10: "Qo''qon ziyo nuri" масъуляти чекланган жамияти | E10: 42035 | F10: Мижоз имзоси
A11: 20208000300393580001 | B11: =+B10+1 -> 4 | C11: 00393580 | D11: "МАШХУРАХОН РУХШОНА" МАСЪУЛИЯТИ ЧЕКЛАНГАН ЖАМИЯТИ | E11: 42039 | F11: санаси ва бошкарувчи имзоси куйилмаган
A12: 20208000704591829001 | B12: =+B11+1 -> 5 | C12: 04591829 | D12: "Навкирон Вали Сохиб " мчж | E12: 42047
A13: 20208000600442044001 | B13: =+B12+1 -> 6 | C13: 00442044 | D13: "ДАНГАРА ОЗИК ОВКАТ САВДО" МАСЪУЛЯТИ ЧЕКЛАНГАН ЖАМИЯТИ | E13: 42060
A14: 20208000900442231001 | B14: =+B13+1 -> 7 | C14: 00442231 | D14: "Demand trans servis" МЧЖ | E14: 42060
A15: 20208000600449675001 | B15: =+B14+1 -> 8 | C15: 00449675 | D15: "Sevinch kimyo trans" масъуляти чекланган жамияти | E15: 42082 | F15: санаси ва бошкарувчи имзоси куйилмаган
A16: 20208000804746588001 | B16: =+#REF!+1 -> #REF! | C16: 04746588 | D16: "УЛУГБЕК МЕГА ТРАНС" масъулияти чекланган жамият | E16: 42228
A17: 20208000300484425001 | B17: =+B16+1 -> #REF! | C17: 00484425 | D17: "САДОРБЕК ЁШЛАР ФАХРИ" ОИЛАВИЙ КОРХОНАСИ | E17: 42240 | F17: санаси ва бошкарувчи имзоси куйилмаган
A18: 20208000900280433001 | B18: =+B17+1 -> #REF! | C18: 00280433 | D18: SUPER SPORT SERVIS МЧЖ | E18: 42244
A19: 20208000900493085001 | B19: =+B18+1 -> #REF! | C19: 00493085 | D19: "Нон тўкинлик гарови" хусусий корхонаси | E19: 42244 | F19: санаси ва бошкарувчи имзоси куйилмаган
A20: 20208000900411170001 | B20: =+B19+1 -> #REF! | C20: 00411170 | D20: "ORIGINAL PREMIUM TRANS" масъуляти чекланган жамияти | E20: 42250
A21: 20208000000494079001 | B21: =+B20+1 -> #REF! | C21: 00494079 | D21: "Qo''qon tong shabnami" масъуляти чекланган жамияти | E21: 42254
A22: 20208000904976035001 | B22: =+#REF!+1 -> #REF! | C22: 04976035 | D22: "Iskandar Raxmon" хусусий корхонаси | E22: 42285
A23: 20208000004007723001 | B23: =+#REF!+1 -> #REF! | C23: 04007723 | D23: Мирзакаримхожи хсичф | E23: 42311
A24: 20208000900211569001 | B24: =+#REF!+1 -> #REF! | C24: 00211569 | D24: "ТАЙЁРЛОВСАВДО" масъулияти чекланган жамияти | E24: 42334 | F24: 1
A25: 20208000900522659001 | B25: =+#REF!+1 -> #REF! | C25: 00522659 | D25: "Мухриддин Иродахон зийнати" оилавий корхонаси | E25: 42348
A26: 20208000200552491001 | B26: =+#REF!+1 -> #REF! | C26: 00552491 | D26: "Bicycle trading invest" масъуляти чекланган жамияти | E26: 42377
A27: 20208000300562685001 | B27: =+B26+1 -> #REF! | C27: 00562685 | D27: "Xolis tarafdori" адвакатлик бюроси | E27: 42387 | F27: санаси ва бошкарувчи имзоси куйилмаган
A28: 20208000700573582001 | B28: =+#REF!+1 -> #REF! | C28: 00573582 | D28: "Dang'ara chorva ko'zgusi " МЧЖ шаклидаги Агрофирма | E28: 42394
A29: 20208000900290628001 | B29: =+B28+1 -> #REF! | C29: 00290628 | D29: "ZO''R TAKSI" масъулияти чекланган жамияти | E29: 42408
A30: 20208000904193940001 | B30: =+B29+1 -> #REF! | C30: 04193940 | D30: "Адолат шамчироги" адвакатлик фирмаси | E30: 42408
A31: 20208000905013538001 | B31: =+B30+1 -> #REF! | C31: 05013538 | D31: ABDULLAEV SHOXRUX FAYZI ОИЛАВИЙ КОРХОНАСИ | E31: 42412
A32: 20208000400224473002 | B32: =+B31+1 -> #REF! | C32: 00224473 | D32: DANG`ARA CHORVA OZUQA SERVIS МАЪСУЛЯТИ ЧЕКЛАНГАН ЖАМИЯТ | E32: 42415
A33: 20208000300402419001 | B33: =+B32+1 -> #REF! | C33: 00402419 | D33: "IDEAL BARAKA APPOLON" МЧЖ | E33: 42415
A34: 20208000600392426001 | B34: =+B33+1 -> #REF! | C34: 00392426 | D34: "ANTARES TRADE" масъулияти чекланган жамияти | E34: 42422 | F34: бошкарувчи имзоси
A35: 20208000804987183001 | B35: =+B34+1 -> #REF! | C35: 04987183 | D35: DANGARA DOCTOR TRANS маъсуляти чекланган жамият | E35: 42439
A36: 20208000904518860001 | B36: =+#REF!+1 -> #REF! | C36: 04518860 | D36: Дил Мехр Дилкаш дехкон хужалиги | E36: 42444
A37: 20208000400606847001 | B37: =+#REF!+1 -> #REF! | C37: 00606847 | D37: "Durdona ziyo" масъуляти чекланган жамияти | E37: 42472
A38: 20208000900606848001 | B38: =+B37+1 -> #REF! | C38: 00606848 | D38: "Ismoiljon Abdulaziz" масъуляти чекланган жамияти | E38: 42472
A39: 20208000000405424001 | B39: =+B38+1 -> #REF! | C39: 00405424 | D39: DANGARA PROPAN МЧЖ | E39: 42474
A40: 20208000400401313001 | B40: =+B39+1 -> #REF! | C40: 00401313 | D40: Кукон чорва насл сервис МЧЖ | E40: 42478
A41: 20208000700206621001 | B41: =+#REF!+1 -> #REF! | C41: 00206621 | D41: Нурматжон Нуриддинжон файзи дехкон хужалиги | E41: 42485
A42: 20208000400611943001 | B42: =+B41+1 -> #REF! | C42: 00611943 | D42: "Хумоюн Мирзи Мебел" оилавий корхонаси | E42: 42485
A43: 20208000300611946001 | B43: =+B42+1 -> #REF! | C43: 00611946 | D43: "ZARRIN NUR SAVDO " масъуляти чекланган жамияти | E43: 42485
A44: 20208000600617444001 | B44: =+B43+1 -> #REF! | C44: 00617444 | D44: "Кароматхон Нурли зиёси" дехкон хужалиги | E44: 42506
A45: 20208000104960728888 | B45: =+B44+1 -> #REF! | C45: 04960728 | D45: DANG`ARA ORIGINAL SERVIS маъсуляти чекланган жамият | E45: 42510 | F45: санаси ва бошкарувчи имзоси
A46: 20208000500619370001 | B46: =+B45+1 -> #REF! | C46: 00619370 | D46: "Umid nur trans" масъуляти чекланган жамияти | E46: 42511
A47: 20208000200230390001 | B47: =+B46+1 -> #REF! | C47: 00230390 | D47: DANG`ARA HOJIAKBAR TRANS маъсуляти чекланган жамият | E47: 42520
A48: 20208000100624667001 | B48: =+#REF!+1 -> #REF! | C48: 00624667 | D48: "Etalon Elite Textile" масъуляти чекланган жамияти | E48: 42528
A49: 20208000300626730001 | B49: =+B48+1 -> #REF! | C49: 00626730 | D49: "Найманча курки" дехкон хужалиги | E49: 42534
A50: 20208000200301020001 | B50: =+B49+1 -> #REF! | C50: 00301020 | D50: "DANG`ARA MUKAMMAL MEBEL" оилавий корхонаси | E50: 42535
A51: 20208000000611616001 | B51: =+B50+1 -> #REF! | C51: 00611616 | D51: DANG`ARA AVTOSHINA SAVDO маъсуляти чекланган жамият | E51: 42537
A52: 20208000900629175001 | B52: =+B51+1 -> #REF! | C52: 00629175 | D52: "Erkinjon bo'stonliq fayzi" dexqon jo'jaliqi | E52: 42539
A53: 20208000600633119001 | B53: =+B52+1 -> #REF! | C53: 00633119 | D53: "Boqiy sharaf" масъуляти чекланган жамияти | E53: 42549 | F53: бошкарувчи имзоси
A54: 20208000900639031001 | B54: =+B53+1 -> #REF! | C54: 00639031 | D54: "Дангара Фар Нихон" дехкон хужалиги | E54: 42565
A55: 20208000904512566001 | B55: =+B54+1 -> #REF! | C55: 04512566 | D55: Дангара икбол файзи дехкон хужалиги | E55: 42566
A56: 20208000904514422001 | B56: =+B55+1 -> #REF! | C56: 04514422 | D56: "Дангара Сохиби Лутф" дехкон хужалиги | E56: 42584
A57: 20208000800648246001 | B57: =+B56+1 -> #REF! | C57: 00648246 | D57: "Иззат Нурия савдо" МЧЖ | E57: 42585
A58: 20208000704822914001 | B58: =+B57+1 -> #REF! | C58: 04822914 | D58: Кукон Хамкор файз маъсулияти чекланган жамияти | E58: 42585
A59: 20208000800656450001 | B59: =+B58+1 -> #REF! | C59: 00656450 | D59: "Ширин чой файзи" оилавий корхонаси | E59: 42604
A60: 20208000305011880005 | B60: =+B59+1 -> #REF! | C60: 05011880 | D60: "REAL RICHMOND INVEST" МЧЖ | E60: 42609
A61: 20208000800661706001 | B61: =+B60+1 -> #REF! | C61: 00661706 | D61: Ozod yurt yog'dusi oilaviy korxonasi | E61: 42621
A62: 20208000900664159001 | B62: =+B61+1 -> #REF! | C62: 00664159 | D62: "Давронжон Жумабоев" дехкон хужалиги | E62: 42627
A63: 20208000704855421001 | B63: =+B62+1 -> #REF! | C63: 04855421 | D63: "Шаркий Орбитал Транс" МЧЖ | E63: 42634
A64: 20208000302855578001 | B64: =+B63+1 -> #REF! | C64: 02855578 | D64: DOVUD хусусий корхонаси | E64: 42636
A65: 20208000000671982001 | B65: =+B64+1 -> #REF! | C65: 00671982 | D65: ADRAS TRADING MCHJ | E65: 42639
... A82: 20218000200424540001 | B82: =+B81+1 -> 4 | C82: 00424540 | D82: Шерматов Абдурасул Абдурахимович | E82: 42032
A83: 20218000300434169001 | B83: =+B82+1 -> 5 | C83: 00434169 | D83: ЯТТ Мирзасобиров Нодирбек Норкузи угли | E83: 42044 | F83: Мижоз имзоси
A84: 20218000700445485001 | B84: =+B83+1 -> 6 | C84: 00445485 | D84: ЯТТ Мадаминов Шарофиддин Кушмуротович | E84: 42069
A85: 20218000000447099001 | B85: =+B84+1 -> 7 | C85: 00447099 | D85: ЯТТ Абдурахимова Махоратхон Мухамадаминовна | E85: 42074
A86: 20218000300447007001 | B86: =+B85+1 -> 8 | C86: 00447007 | D86: ЯТТ БАДАЛОВ КАМОЛИДДИН ВАЛИЕВИЧ | E86: 42089
A87: 20218000700455158001 | B87: =+B86+1 -> 9 | C87: 00455158 | D87: ЯТТ Мовлонова Лолахон Абдирашидовна | E87: 42103 | F87: Санаси ва бошкарувчи имзоси
A88: 20218000200462088001 | B88: =+#REF!+1 -> #REF! | C88: 00462088 | D88: ЯТТ Мамаюсупов Уткиржон Холматович | E88: 42129
A89: 20218000000462527001 | B89: =+B88+1 -> #REF! | C89: 00462527 | D89: ЯТТ Тиллаев Абдурасил Долимович | E89: 42130 | F89: бошкарувчи имзоси
A90: 20218000000465499001 | B90: =+B89+1 -> #REF! | C90: 00465499 | D90: ЯТТ Усмонов Латифжон Аскарали угли | E90: 42135 | F90: бошкарувчи имзоси
A91: 20218000100465503001 | B91: =+B90+1 -> #REF! | C91: 00465503 | D91: ЯТТ Ахмедов Улугбек Муроджон угли | E91: 42135
A92: 20218000200473140001 | B92: =+#REF!+1 -> #REF! | C92: 00473140 | D92: ЯТТ Мелибоев Ботиржон Юнусович | E92: 42159
A93: 20218000300473936001 | B93: =+B92+1 -> #REF! | C93: 00473936 | D93: ЯТТ Имомалиев Баходиржон Хайдарович | E93: 42163
A94: 20218000000479761001 | B94: =+#REF!+1 -> #REF! | D94: ЯТТ Мамажонова Нигора Номоновна | E94: 42192 | H94: 2016 йил 03 майда тугаган
A95: 20218000400479762001 | B95: =+B94+1 -> #REF! | C95: 00479762 | D95: ЯТТ Суюнова Дилноза Муродовна | E95: 42192
A96: 20218000000480953001 | B96: =+B95+1 -> #REF! | C96: 00480953 | D96: ЯТТ Абдурахмонов Хуршиджон Хаётжон угли | E96: 42198 | I96: 1
A97: 20218000500480954001 | B97: =+B96+1 -> #REF! | C97: 00480954 | D97: ЯТТ Аноров Шерали Камбарович | E97: 42220
A98: 20218000804947118001 | B98: =+B97+1 -> #REF! | C98: 04947118 | D98: ЯТТ МАХКАМОВА ГУЛБАХОР НЕЪМАТОВНА | E98: 42220
A99: 20218000100487057001 | B99: =+B98+1 -> #REF! | C99: 00487057 | D99: ЯТТ Олимов Рузибой Неъматович | E99: 42230 | F99: бошкарувчи имзоси
A100: 20218000700487058001 | B100: =+B99+1 -> #REF! | C100: 00487058 | D100: ЯТТ Мирсодикова Сарвиноз Махсудали кизи | E100: 42230 | F100: мижоз имзоси
A101: 20218000200487059001 | B101: =+B100+1 -> #REF! | C101: 00487059 | D101: ЯТТ Йигиталиева Шохзодахон Азамжон кизи | E101: 42230 | F101: бошкарувчи имзоси
A102: 20218000904581961001 | B102: =+B101+1 -> #REF! | C102: 04581961 | D102: ХТ Алиев сайдали султонович | E102: 42241
A103: 20218000700493084001 | B103: =+B102+1 -> #REF! | C103: 00493084 | D103: ЯТТ Кенджаев Расулжон Меликузиевич | E103: 42244 | F103: Санаси ва бошкарувчи имзоси | H103: 2016 йил августда тугаган
A104: 20218000000497139001 | B104: =+#REF!+1 -> #REF! | C104: 00497139 | D104: ЯТТ Ганиев Сайиджон Вахобжон-угли | E104: 42258 | F104: бошкарувчи имзоси
A105: 20218000400502419001 | B105: =+B104+1 -> #REF! | C105: 00502419 | D105: ЯТТ Кучкаров Толибжон Рахимович | E105: 42283
A106: 20218000900503108001 | B106: =+B105+1 -> #REF! | C106: 00503108 | D106: ЯТТ Саттаров Равшан Каххорович | E106: 42285
A107: 20218000900503109001 | B107: =+B106+1 -> #REF! | C107: 00503109 | D107: ЯТТ Исмоилов Темурбек Икболжон угли | E107: 42285 | F107: бошкарувчи имзоси
A108: 20218000100512633001 | B108: =+B107+1 -> #REF! | C108: 00512633 | D108: ЯТТ Усмонов Шавкатжон Гуломович | E108: 42305
A109: 20218000300515162001 | B109: =+B108+1 -> #REF! | C109: 00515162 | D109: ЯТТ Дехконов Бекмурод Меликузиевич | E109: 42317 | F109: бошкарувчи имзоси
A110: 20218000900517627001 | B110: =+B109+1 -> #REF! | C110: 00517627 | D110: ЯТТ Алиев Азиз Аминович | E110: 42321
A111: 20218000900519007001 | B111: =+B110+1 -> #REF! | C111: 00519007 | D111: ЯТТ Орипов Бахромжон Бахтиёр угли | E111: 42341 | F111: мижоз имзоси
A112: 20218000100549268001 | B112: =+#REF!+1 -> #REF! | C112: 00549268 | D112: ЯТТ Гуломов Авазжон Гайратжон угли | E112: 42375 | F112: бошкарувчи имзоси
A113: 20218000700549331001 | B113: =+B112+1 -> #REF! | C113: 00549331 | D113: ЯТТ Содиков Низом Мирномонович | E113: 42375 | F113: Мижоз имзоси ва санаси хамда хисоб раками филиал бош бухгалтерининг имзоси куйилмаган
A114: 20218000900549353001 | B114: =+B113+1 -> #REF! | C114: 00549353 | D114: ЯТТ Абдуллаев Ахроржон Абдусамадович | E114: 42375
A115: 20218000500562312001 | B115: =+#REF!+1 -> #REF! | C115: 00562312 | D115: ЯТТ Тешаева Иродахон Ризиевна | E115: 42384
A116: 20218000100519341001 | B116: =+B115+1 -> #REF! | C116: 00519341 | D116: Муйдинов Икболжон Икромжон угли | E116: 42397
A117: 20218000100578522001 | B117: =+B116+1 -> #REF! | C117: 00578522 | D117: ЯТТ Мелизияев Азизбек Шукуржон угли | E117: 42399 | F117: бошкарувчи имзоси
A118: 20218000000578523001 | B118: =+B117+1 -> #REF! | C118: 00578523 | D118: ЯТТ Мирзалиев Дониёржон Сахобиддин угли | E118: 42399
A119: 20218000100582119001 | B119: =+B118+1 -> #REF! | C119: 00582119 | D119: ЯТТ Джурабоев Азизжон Абдухамидович | E119: 42405
A120: 20218000800582260001 | B120: =+B119+1 -> #REF! | C120: 00582260 | D120: ЯТТ Хайдаров Бокижон Тургунович | E120: 42408
A121: 20218000900585835001 | B121: =+B120+1 -> #REF! | C121: 00585835 | D121: ЯТТ Улугхаджаева Назокат Назировна | E121: 42412
A122: 20218000600404750001 | B122: =+B121+1 -> #REF! | C122: 00404750 | D122: Исроилов Аброржон Исроилжон угли ЯТТ | E122: 42415 | H122: 2016 йил 04 февралда тугаган
...

Sheet 6.Иш хаки
B2: АТ Халк банки Чилонзор филиалида утказилган ички аудит текширувида ходимлар томонидан ортикча олган мехнат хаклари буйича маълумот
A4: № | B4: Ходимнинг ФИШ | C4: Ортикча хисобланган маблаг | D4: Текшириш давомида кайтариб туланган маблаг | E4: Иззох | F4: Баланс хисоб раками
A5: 1 | B5: Соатов Васлиддин | C5: 161212 | D5: 161212 | E5: 2016 январ иш хаки | F5: 56102
A6: =+A5+1 -> 2 | B6: Кориева Шахноза | C6: =427661-427661*16/20 -> 85532.2 | D6: 85532.2 | E6: 2016 январ ойи иш хаки табели 16 кун 20 кунга иш хаки хисобланган | F6: 56102
C7: =85532.2-85532.2*16/20 -> 17106.44 | D7: 17106.44 | E7: 2016 январ ойи иш хаки табели 16 кун 20 кунга надбавка хисобланган | F7: 56102
C8: =213830.5-213830.5*16/20 -> 42766.1 | D8: 42766.1 | E8: 2016 январ ойи иш хаки табели 16 кун 20 кунга выслуга лет хисобланган | F8: 56106
A9: 3 | B9: Рихсиева Саида | C9: =427661-427661*15/20 -> 106915.25 | D9: 106915.3 | E9: 2016 январ ойи иш хаки табели 15 кун 20 кунга иш хаки хисобланган | F9: 56102
C10: =85532.2-85532.2*15/20 -> 21383.05 | D10: 21383.1 | E10: 2016 январ ойи иш хаки табели 15 кун 20 кунга надбавка хисобланган | F10: 56102
C11: =128298.3-128298.3*15/20 -> 32074.575 | D11: 32074.6 | E11: 2016 январ ойи иш хаки табели 15 кун 20 кунга выслуга лет хисобланган | F11: 56106
A12: 4 | B12: Халимов Абдуманнон | C12: =161357.7/3 -> 53785.9 | D12: 53785.9 | E12: 2015 декабр ойи шанба, якшанба табели 1 кун 3 кунга хисобланган | F12: 56102
A13: 5 | B13: Мустафокулов Исроил | C13: =591645-591645*20/22 -> 53785.909 | D13: 53785.9 | E13: 2015 декабр ойи иш хаки табели 20 кун 22 кунга иш хаки хисобланган | F13: 56102
C14: =177493.5-177493.5*20/22 -> 16135.773 | D14: 16135.77 | E14: 2015 декабр ойи иш хаки табели 20 кун 22 кунга надбавка хисобланган | F14: 56102
C15: =59164.5-59164.5*20/22 -> 5378.5909 | D15: 5378.6 | E15: 2015 декабр ойи иш хаки табели 20 кун 22 кунга выслуга лет хисобланган | F15: 56106
A16: 6 | B16: Абдиев Сардор | C16: =209286.08/4 -> 52321.52 | D16: 52321.5 | E16: 2015 ноябр ойи шанба якшанба 3 кун иш куни булсада 4 кунга хисобланган | F16: 56102
A17: 7 | B17: Хамроева Нилуфар | C17: =427661/21 -> 20364.81 | D17: =427661/21 -> 20364.81 | E17: 2015 октябр ойи иш хаки табели 20 кун 21 кунга иш хаки хисобланган | F17: 56102
A18: 8 | B18: Хужаназаров Шахриёр | C18: 29582.25 | D18: 29582.3 | E18: 2015 сентябр ойи шанба, якшанба табелда йук лекин хисобланган | F18: 56102
A19: 13 | B19: Хужаназаров Шахриёр | C19: 56347 | D19: 56347 | E19: 2015 август ойи иш хаки табели 19 кун 21 кунга иш хаки хисобланган | F19: 56102
A20: 14 | B20: Хужаназаров Шахриёр | C20: 22538 | D20: 22538 | E20: 2015 декабр ойи иш хаки табели 19 кун 21 кунга надбавка хисобланган | F20: 56102
A21: 15 | B21: Турсунхужаева Насиба | C21: 112694.3 | D21: 112694.3 | E21: 2015 август ойи иш хаки табели 16 кун 20 кунга иш хаки хисобланган | F21: 56102
C22: =+C21*30/100 -> 33808.29 | D22: =+D21*30/100 -> 33808.29 | E22: 2015 август ойи иш хаки табели 16 кун 20 кунга надбавка хисобланган | F22: 56102
C23: =+C21/2 -> 56347.15 | D23: =+D21/2 -> 56347.15 | E23: 2015 август ойи иш хаки табели 16 кун 20 кунга выслуга лет хисобланган | F23: 56106
A24: 16 | B24: Камилова Дилфуза Кабилжановна | C24: 235446.9 | D24: 235446.9 | E24: 2015 август ойи иш хаки табели 10 кун 19 кунга иш хаки хисобланган | F24: 56102
C25: =+C24*20/100 -> 47089.38 | D25: 47089.38 | E25: 2015 август ойи иш хаки табели 10 кун 19 кунга надбавка хисобланган | F25: 56102
C26: =+C24*30/100 -> 70634.07 | D26: 70694.07 | E26: 2015 август ойи иш хаки табели 10 кун 19 кунга выслуга лет хисобланган | F26: 56106
A27: 17 | B27: Муратов Бахтибек Нуралиевич | C27: 153535.8 | D27: 153535.8 | E27: 2015 август ойи иш хаки табели 16 кун 21 кунга иш хаки хисобланган | F27: 56102
C28: =+C27*50/100 -> 76767.9 | D28: 76767.9 | E28: 2015 август ойи иш хаки табели 16 кун 21 кунга надбавка хисобланган | F28: 56102
C29: =+C27*20/100 -> 30707.16 | D29: 30707.16 | E29: 2015 август ойи иш хаки табели 16 кун 21 кунга выслуга лет хисобланган | F29: 56106
A30: 18 | B30: Хушвактова Илхом | C30: 102193.27 | E30: 2015 июл ойи шанба, якшанба табелда йук лекин хисобланган | F30: 56102
A31: 19 | B31: Ритаева(Шерматова) Мафтуна | C31: =236800*3 -> 710400 | D31: 710000 | E31: 2015 йил 3 ойлик ортикча 2 ёшгача таътили олган | F31: 56118
A32: 20 | B32: Талипова Маъмура Закировна | C32: 855322 | E32: 2015 йилда 4 марта моддий ёрдам беринган(2 марта ортикча берилган) | F32: 56118
A33: 21 | B33: Ахунова Наргиза Ботир кизи | C33: 933228 | E33: 2015 йилда 4 марта моддий ёрдам беринган(2 марта ортикча берилган) | F33: 56118
B34: жами | C34: =SUM(C5:C33) -> 4195403.6 | D34: =SUM(D5:D33) -> 2304320.5
B37: =+'4.а-восита'!B30 -> АТ "Халқ банк"нинг Ички Аудит
B38: =+'4.а-восита'!B31 -> Департаменти бўлим бошлиғи: | E38: А.Норкузиев
B40: =+'4.а-восита'!B33 -> АТ "Халқ банк" Фаргона вилояти вилояти
B41: =+'4.а-восита'!B34 -> Бешариқ филиали филиал бошқарувчиси: | E41: С.Матякубов
B43: =+'4.а-восита'!B36 -> Бош бухгалтери: | E43: Г.Каримова

Sheet 8.19900 х-р
K1: 8-жадвал
A2: =""&(Шаблон!B1)&"нинг "&(Шаблон!B2)&" шахар "&(Шаблон!B3)&" филиалида 19907, 19908, 19909, 19921, 19925 ва 19929-ҳисобварақлари орқали амалга оширилган нотўғри амалиётлар тўғрисида "&(Шаблон!B15)&" ҳолатига" -> АТ "Халқ банк"нинг Фаргона вилояти шахар Бешариқ филиали филиалида 19907, 19908, 19909, 19921, 19925 ва 19929-ҳисобварақлари орқали амалга оширилган нотўғри амалиётлар тўғрисида 2024 йил 1 январ ҳолатига
A3: М А Ъ Л У М О Т
K4: (сўмда)
A5: т\р | B5: Санаси | D5: Маблағ ўтказилган ҳисоб рақам номи | E5: Ҳисоб рақам | F5: Суммаси | G5: МФО | H5: Маблағ ўтган ташкилот | I5: Ҳисоб рақами | J5: Тўлов мақсади | K5: Аниқланган камчиликлар | L5: изох
A6: А | B6: Б | D6: 1 | E6: 2 | F6: 3 | G6: 4 | H6: 5 | I6: 6 | J6: 7 | K6: 8 | L6: 9
A7: 1 | B7: 29.02.2016 | C7: =+MID(B7,4,8) -> 02.2016 | D7: Омбордаги асосий воситалар | E7: 16561 | F7: 800000 | G7: 00708 | H7: Асасий воситаларни сотиб олиш | I7: 19909000000000708300 | J7: № 1 от 29.02.2016 1 дона кресло кирим килинди | K7: Счёт фактураси йўқ
A8: =+A7+1 -> 2 | B8: 30.06.2016 | C8: =+MID(B8,4,8) -> 06.2016 | D8: Омбордаги асосий воситалар | E8: 16561 | F8: 800000 | G8: 00708 | H8: Сотиб олинаётган Товар-моддий кимматликлар (Асосий восита) учун олдиндан тулов | I8: 19909000400000708561 | J8: № 1 от 30.06.2016 10,05,2016й №146 сонли шарт ас-н 2 дона уриндик олиш учун тулов 100% | K8: Счёт фактураси йўқ
A9: =+A8+1 -> 3 | B9: 28.07.2016 | C9: =+MID(B9,4,8) -> 07.2016 | D9: Омбордаги асосий воситалар | E9: 16561 | F9: 1762030.9 | G9: 00708 | H9: Навоий ш.ХБ.Бош банк/филиал-рга туланадиган маблаглар-Товар-моддий кимматликлар | I9: 22205000200000708708 | J9: № 292 от 12.07.2016 Терминал | K9: Счёт фактураси йўқ
A10: =+A9+1 -> 4 | B10: 29.07.2016 | C10: =+MID(B10,4,8) -> 07.2016 | D10: Омбордаги асосий воситалар | E10: 16561 | F10: 7875000 | G10: 00708 | H10: Навоий ш.ХБ.Бош банк/филиал-рга туланадиган маблаглар-Товар-моддий кимматликлар | I10: 22205000200000708708 | J10: № 320 от 29.07.2016 Кандиционер | K10: Счёт фактураси йўқ
A11: =+A10+1 -> 5 | B11: 31.10.2016 | C11: =+MID(B11,4,8) -> 10.2016 | D11: Омбордаги асосий воситалар | E11: 16561 | F11: 3558768 | G11: 00708 | H11: Навоий ш.ХБ.Бош банк/филиал-рга туланадиган маблаглар-Товар-моддий кимматликлар | I11: 22205000200000708708 | J11: № 402 от 17.10.2016 | K11: Счёт фактураси йўқ
A12: =+A11+1 -> 6 | B12: 31.10.2016 | C12: =+MID(B12,4,8) -> 10.2016 | D12: Омбордаги асосий воситалар | E12: 16561 | F12: 7117536.1 | G12: 00708 | H12: Навоий ш.ХБ.Бош банк/филиал-рга туланадиган маблаглар-Товар-моддий кимматликлар | I12: 22205000200000708708 | J12: № 418 от 26.10.2016 4дона терминал | K12: Счёт фактураси йўқ
A13: =+A12+1 -> 7 | B13: 29.11.2016 | C13: =+MID(B13,4,8) -> 11.2016 | D13: Омбордаги асосий воситалар | E13: 16561 | F13: 600000 | G13: 00708 | H13: Сотиб олинаётган Товар-моддий кимматликлар (Асосий восита) учун олдиндан тулов | I13: 19909000400000708561 | J13: № 12 от 29.11.2016 03.11.2016 йилдаги №12 сонли шартномага асосан Навоий шахар Халк банкига Лотария столи олиш учун тулов | K13: Счёт фактураси йўқ
A14: =+A13+1 -> 8 | B14: 15.12.2016 | C14: =+MID(B14,4,8) -> 12.2016 | D14: Омбордаги асосий воситалар | E14: 16561 | F14: 1811411.9 | G14: 00708 | H14: Навоий ш.ХБ.Бош банк/филиал-рга туланадиган маблаглар-Товар-моддий кимматликлар | I14: 22205000200000708708 | J14: № 491 от 15.12.2016 1 терминал суммаси | K14: Счёт фактураси йўқ
A15: =+A14+1 -> 9 | B15: 15.12.2016 | C15: =+MID(B15,4,8) -> 12.2016 | D15: Омбордаги асосий воситалар | E15: 16561 | F15: 307459.17 | G15: 00708 | H15: Навоий ш.ХБ.Бош банк/филиал-рга туланадиган маблаглар-Товар-моддий кимматликлар | I15: 22205000200000708708 | J15: № 489 от 14.12.2016 3 дона термопринтер суммаси | K15: Счёт фактураси йўқ
A16: =+A15+1 -> 10 | B16: 29.01.2017 | C16: =+MID(B16,4,8) -> 01.2017 | D16: Омбордаги асосий воситалар | E16: 16561 | F16: 136000 | G16: 00708 | H16: КБТЭБ-бошкалар | I16: 19909000900000708290 | J16: № 1 от 29.01.2017 23.01.2017 йилдаги №55 сонли шартномага асосан Ат Халк банки Навоий щахар филиали учун калонка ва микрофон олиш учун тулов | K16: Счёт фактураси йўқ
A17: =+A16+1 -> 11 | B17: 31.01.2017 | C17: =+MID(B17,4,8) -> 01.2017 | D17: Омбордаги асосий воситалар | E17: 16561 | F17: 672468.01 | G17: 00708 | H17: Навоий ш.ХБ.Бош банк/филиал-рга туланадиган маблаглар-Товар-моддий кимматликлар | I17: 22205000200000708708 | J17: № 3 от 17.01.2017 1 дона омад лотто сканери суммаси | K17: Счёт фактураси йўқ
A18: =+A17+1 -> 12 | B18: 18.02.2017 | C18: =+MID(B18,4,8) -> 02.2017 | D18: Омбордаги асосий воситалар | E18: 16561 | F18: 2528665.5 | G18: 00708 | H18: Навоий ш.ХБ.Бош банк/филиал-рга туланадиган маблаглар-Товар-моддий кимматликлар | I18: 22205000200000708708 | J18: № 42 от 13.02.2017 Планшет наушник китоблар суммаси МПК | K18: Счёт фактураси йўқ
A19: =+A18+1 -> 13 | B19: 13.03.2017 | C19: =+MID(B19,4,8) -> 03.2017 | D19: Омбордаги асосий воситалар | E19: 16561 | F19: 3688782.8 | G19: 00708 | H19: Навоий ш.ХБ.Бош банк/филиал-рга туланадиган маблаглар-Товар-моддий кимматликлар | I19: 22205000200000708708 | J19: № 98 от 13.03.2017 2 дона терминал ва 200 дона МПК суммаси | K19: Счёт фактураси йўқ
... A50: =+A49+1 -> 44 | B50: 12.10.2017 | C50: =+MID(B50,4,8) -> 10.2017 | D50: Омбордаги асосий воситалар | E50: 16561 | F50: 1495164.8 | G50: 00708 | H50: Нав.ш.ХБФ.Бош банк/филиаллардан олинадиган маблаглар-Товар-моддий кимматликлар. | I50: 16104000400000708001 | J50: За ТМЦ (НАКЛАДНАЯ СЧЕТ - ФАКТУРА) № 3 от 12.10.2017 12.10.2017й №3 счет фактурага ас-н Кармана филиалига асосий воситалар берилди | K50: Асосий воситани олиб кетиш учун ишончнома
A51: =+A50+1 -> 45 | B51: 23.02.2017 | C51: =+MID(B51,4,8) -> 02.2017 | D51: Хизматлар учун олдиндан килинган харажатлар | E51: 19907 | F51: 500000 | G51: 00491 | H51: РКП УзРТСБ | I51: 20208000000600257044 | J51: 2016 йи 27 июаи Уз. Рес. ВМ 242 сони карорига асосан Узбекистон Республикаси товар хом-ашё биржасида иштирок этиш учун ку
A52: =+A51+1 -> 46 | B52: 26.08.2016 | C52: =+MID(B52,4,8) -> 08.2016 | D52: Хизматлар учун олдиндан килинган харажатлар | E52: 19907 | F52: 797187.6 | G52: 00206 | H52: ОА Навоийавтотеххизмат | I52: 20210000600177892001 | J52: Согласно договора 194 от 22.08.2016 (Банк балансида булган дамас русумли автомашинани ремонт килиш учун тулов)
A53: =+A52+1 -> 47 | B53: 26.12.2016 | C53: =+MID(B53,4,8) -> 12.2016 | D53: Хизматлар учун олдиндан килинган харажатлар | E53: 19907 | F53: 390000 | G53: 00703 | H53: "Ербобоев Алпомиш" хусусий корхонаси | I53: 22626000504635779001 | J53: Согласно договора 45 от 21.12.2016 (21.12.2016 ЙИЛДАГИ №45 СОНЛИ ШАРТНОМАГА АСОСАН Навоий Ш ХБ балансдаги дамас авто маши
A54: =+A53+1 -> 48 | B54: 27.09.2017 | C54: =+MID(B54,4,8) -> 09.2017 | D54: Хизматлар учун олдиндан килинган харажатлар | E54: 19907 | F54: 321000 | G54: 00211 | H54: "Хуршид авто сервис" МЧЖ | I54: 20208000304839514001 | J54: Согласно договора 102 от 24.08.2017 (24,08,2017 йилдаги 102-сонли шартномага асосан Дамас автомашиналарининг Матор мйи ва
A55: =+A54+1 -> 49 | B55: 27.11.2017 | C55: =+MID(B55,4,8) -> 11.2017 | D55: Хизматлар учун олдиндан килинган харажатлар | E55: 19907 | F55: 1056250 | G55: 00197 | H55: ХСУУА Аброр-98 | I55: 22626000504171589001 | J55: Согласно договора 153 от 28.08.2017 (ПК2826 га асосан пенсия таркатадиган Дамас автомашиналарига 153-сонли ш-ма га асосан
A56: =+A55+1 -> 50 | B56: 17.12.2017 | C56: =+MID(B56,4,8) -> 12.2017 | D56: Хизматлар учун олдиндан килинган харажатлар | E56: 19907 | F56: 1098500 | G56: 00197 | H56: ХСУУА Аброр-98 | I56: 22626000504171589001 | J56: Согласно договора 261 от 29.11.2017 (Уз.рес През.нинг ПК 2826 карори, Бошкарувнинг 28-5 сонли кар
A57: =+A56+1 -> 51 | B57: 23.02.2018 | C57: =+MID(B57,4,8) -> 02.2018 | D57: Хизматлар учун олдиндан килинган харажатлар | E57: 19907 | F57: 184723.76 | G57: 00206 | H57: АО Навоийавтотеххизмат | I57: 20210000600177892001 | J57: Согласно договора 14/Б от 22.02.2018 (За ТО и ремонт автомашины нексия-3 замена масло и фильтр сог дог 14/Б от 22,02,2018
A58: =+A57+1 -> 52 | B58: 17.05.2018 | C58: =+MID(B58,4,8) -> 05.2018 | D58: Хизматлар учун олдиндан килинган харажатлар | E58: 19907 | F58: 745078 | G58: 00206 | H58: АО Навоийавтотеххизмат | I58: 20210000600177892001 | J58: Согласно договора 1480 от 22.09.2016 (22.09.2016 йилги счет фак №1480 ас-н 85 062 LAA дАМАС Автомашина таьмири харажатл
A59: =+A58+1 -> 53 | B59: 04.10.2016 | C59: =+MID(B59,4,8) -> 10.2016 | D59: Хизматлар учун олдиндан килинган харажатлар | E59: 19907 | F59: 516300 | G59: 00202 | H59: ЧП Бозорова Г | I59: 20218000904971307001 | J59: Согласно договора 256 от 14.09.2016 (14.09.2016 йилдаги №256 сонли шартномага асосан Халк банки Навоий шахар филиалининг
A60: =+A59+1 -> 54 | B60: 26.01.2016 | C60: =+MID(B60,4,8) -> 01.2016 | D60: Хизматлар учун олдиндан килинган харажатлар | E60: 19907 | F60: 145768.91 | G60: 00196 | H60: ЖКУ НГМК | I60: 20210000900305623001 | J60: Согласно договора 564 от 01.01.2014 (30.11.2015 йилдаги №4/86487 сонли фактурага асосан 2015 йил декабр ойи коммунал туло
A61: =+A60+1 -> 55 | B61: 27.01.2016 | C61: =+MID(B61,4,8) -> 01.2016 | D61: Хизматлар учун олдиндан килинган харажатлар | E61: 19907 | F61: 147993 | G61: 00205 | H61: Навоий ОГФС | I61: 20204000200306055002 | J61: Согласно договора 15 от 20.12.2015 (20.12.2015 йилдаги №15 сонли фактурага асосан 2015 йил декабр ойи фелд связ хизмати у
A62: =+A61+1 -> 56 | B62: 06.04.2018 | C62: =+MID(B62,4,8) -> 04.2018 | D62: Хизматлар учун олдиндан килинган харажатлар | E62: 19907 | F62: 287627 | G62: 00205 | H62: АО Страх.комп Кафолат | I62: 20210000000305986021 | J62: Согласно договора 6/ОСГ-013 от 06.04.2018 (шартнома №6/ОСГОР-013 ас-н Иш берувчининг фукаролик жавобгарлигини мажбурий су
... A366: =+A365+1 -> 360 | B366: 30.09.2017 | C366: =+MID(B366,4,8) -> 09.2017 | D366: Омбордаги кам баҳоли ва тез эскирувчи буюмлар ҳамда бошқа қимматликлар | E366: 19921 | F366: 195000 | G366: 00708 | H366: Сотиб олинаётган Товар-моддий кимматликлар (КБТЭБ) учун олдиндан тулов | I366: 19909000000000708921 | J366: № 1 от 30.09.2017 25,08,2017 йилдаги 115-сонли шартномага асосан олинадиган канцелярия моллари учун тулов ККСсиз
D367: Жами | F367: =SUM(F7:F366) -> 7.7101093e+08
D369: =+'5.омборхона'!B32 -> Бешариқ филиали филиал бошқарувчиси: | K369: =+'5.омборхона'!I32 -> _____________
D371: =+'5.омборхона'!B34 -> Бош бухгалтери: | K371: =+'5.омборхона'!I34 -> _____________

Sheet 10.омонот фоиз 
J1: 10-жадвал
A2: =""&(Шаблон!B1)&"нинг "&(Шаблон!B2)&" вилоят бошқармаси "&(Шаблон!B3)&" филиалида банк омонатларига қабул қилинган аҳоли омонатлари бўйича текширув давомида аниқланган ортиқча ёки кам фоиз ҳисобланган ҳолатлар бўйича" -> АТ "Халқ банк"нинг Фаргона вилояти вилоят бошқармаси Бешариқ филиали филиалида банк омонатларига қабул қилинган аҳоли омонатлари бўйича текширув давомида аниқланган ортиқча ёки кам фоиз ҳисобланган ҳолатлар бўйича
E3: МАЪЛУМОТ
J4: ( сўмда)
A5: т/р | B5: Омонат тури | C5: Омонатчининг номи | D5: Маблағ қабул қилинган сана | E5: Омонат суммаси | F5: Фоиз хисобланиши | J5: Изоҳ
F6: белгиланган фоиз ставкаси | G6: ҳисобланиши лозим бўлган фоиз суммаси | H6: ҳақиқатда ҳисобланган фоиз суммаси | I6: фарқи (+;-)
A7: А | B7: Б | C7: И | D7: 1 | E7: 2 | F7: 4 | G7: 5 | H7: 6 | I7: 7 | J7: 8
A8: 1 | I8: =+G8-H8 -> 0
A9: =+A8+1 -> 2 | I9: =+G9-H9 -> 0
A10: =+A9+1 -> 3 | I10: =+G10-H10 -> 0
A11: =+A10+1 -> 4 | I11: =+G11-H11 -> 0
A12: =+A11+1 -> 5 | I12: =+G12-H12 -> 0
B13: Жами: | C13: х | E13: =SUM(E8:E12) -> 0 | F13: х | G13: =SUM(G8:G12) -> 0 | H13: =SUM(H8:H12) -> 0 | I13: =SUM(I8:I12) -> 0 | J13: х
B16: =""&(Шаблон!B1)&"нинг Ички Аудит" -> АТ "Халқ банк"нинг Ички Аудит
B17: Департаменти бош мутахассиси: | G17: =Шаблон!B13 -> А.Ҳазратқулов
B19: =""&(Шаблон!B1)&" "&(Шаблон!B2)&" вилоят бошқармаси" -> АТ "Халқ банк" Фаргона вилояти вилоят бошқармаси
B20: =""&(Шаблон!B3)&" филиали бошқарувчиси:" -> Бешариқ филиали филиали бошқарувчиси: | G20: =Шаблон!B5 -> _____________
B22: Бош бухгалтери в.в.б.: | G22: =Шаблон!B8 -> _____________
G35: =((C35*5%)/365)*E35 -> 0 | H35: =((C35*5%)/360)*E35 -> 0

Sheet 11.Омонатдан ун-маган дар-д
K1: 11-жадвал
A2: =""&(Шаблон!B1)&"нинг "&(Шаблон!B2)&" вилоят бошқармаси "&(Шаблон!B3)&" филиалида нақд пулсиз шаклда банк омонатларига қабул қилинган аҳоли омонатларидан Банк бошқаруви томонидан тасдиқланган Банк тарифларига асосан ундирилиши лозим бўлган, лекин ундирилмаган ёки кам ундирилган даромадлар тўғрисида 2013 йил 1 июн холатига" -> АТ "Халқ банк"нинг Фаргона вилояти вилоят бошқармаси Бешариқ филиали филиалида нақд пулсиз шаклда банк омонатларига қабул қилинган аҳоли омонатларидан Банк бошқаруви томонидан тасдиқланган Банк тарифларига асосан ундирилиши лозим бўлган, лекин ундирилмаган ёки кам ундирилган даромадлар тўғрисида 2013 йил 1 июн холатига
E3: МАЪЛУМОТ
K4: ( сўмда)
A5: т/р | B5: Омонат тури | C5: Омонатчининг И.Ш.Ф.си | D5: Маблағ қабул қилинган сана | E5: Жамғарма суммаси | F5: Тўлов мақсади | G5: Фоиз хисобланиши | K5: Изоҳ
G6: белгиланган фоиз стафкаси | H6: ҳисобланиши лозим бўлган фоиз суммаси | I6: ҳақиқатда ҳисобланган фоиз суммаси | J6: фарқи (+;-)
A7: А | B7: Б | C7: И | D7: 1 | E7: 2 | F7: 3 | G7: 4 | H7: 5 | I7: 6 | J7: 7 | K7: 8
A8: 1
B10: Жами: | C10: х | E10: =SUM(E8:E9) -> 0 | G10: х | H10: =SUM(H8:H9) -> 0 | I10: =SUM(I8:I9) -> 0 | J10: =SUM(J8:J9) -> 0 | K10: х
B13: =""&(Шаблон!B1)&"нинг Ички Аудит" -> АТ "Халқ банк"нинг Ички Аудит
B14: Департаменти бош мутахассиси: | H14: =Шаблон!B13 -> А.Ҳазратқулов
B16: =""&(Шаблон!B1)&" "&(Шаблон!B2)&" вилоят бошқармаси" -> АТ "Халқ банк" Фаргона вилояти вилоят бошқармаси
B17: =""&(Шаблон!B3)&" филиали бошқарувчиси:" -> Бешариқ филиали филиали бошқарувчиси: | H17: =Шаблон!B5 -> _____________
B19: Бош бухгалтери: | H19: =Шаблон!B8 -> _____________
H32: =((C32*5%)/365)*E32 -> 0 | I32: =((C32*5%)/360)*E32 -> 0

Sheet 12.Бух_кунлик
J1: 12-жадвал
A2: "Агробанк" ОАТБнинг Жиззах вилоят бошқармаси Жиззах филиалида тикилган кунлик бухгатерия ҳужжатлари йиғмажилдлари ва унга тикилган ҳужжатларнинг расмийлаштирилиши бўйича аудит текшируви давомида аниқланган камчиликлар рўйхати
J3: (сўмда)
A4: № | B4: Санаси | C4: Тўлов ҳужжати рақами № | D4: Тўловчи номи | E4: Мижознинг тўлов ўтган ҳисоб рақами | F4: Тўлов суммаси | G4: Маблағ олувчи | H4: Тўлов мақсади | I4: Камчиликлар | J4: Изоҳ
A5: А | B5: 1 | C5: 2 | D5: 3 | E5: 4 | F5: 5 | H5: 6 | I5: 7 | J5: 8
A6: 1 | B6: 08.08.2012 | C6: 4 | D6: Termiz Obod Ko'kllam хусусий уй жой мулкдорлар ширкати | E6: 15201000504916277001 | F6: 3000000 | G6: Элбек Термиз Сервис ПБТ МЧЖ | H6: ..06.08.2012 йилдаги № 1/06-08-сонли шартномага асосан 6-дона темир эшик олиш учун утказилди. | I6: Тўлов топшириқномаси мавжуд эмас | J6: Бартараф этилди
A7: 2 | B7: 10.08.2012 | C7: 2129 | D7: Сурхонпахтасаноат ХАБ | E7: 12701000100427048037 | F7: 1500000000 | G7: Узпахтасаноат | H7: Айланма маблаг тулдириш учун олинган тиж. кре. хисобидан моддий техника ресурслари учун тулов 100% | I7: Тўлов топшириқномаси мавжуд эмас | J7: Бартараф этилди
A8: 3 | B8: 14.08.2012 | C8: 1 | D8: ЯТТ МАМАСАИДОВА ДИЛАФРУЗ ЙУЛДОШЕВНА | E8: 15001000704063472003 | F8: 2200000 | G8: ООО "ELEKTRON O'LCHASH USKUNALSRI" | H8: 30.07.2012 йилдаги №52-сонли шартномага а-н АСКУЭ тизимига утиш учун тулов | I8: Тўлов топшириқномасида сана куйилмаган, топширикномага ижрочи ва назоратчи ходимларнинг имзолари хамда банкнинг турт бурчак мухри куйилмаган | J8: Бартараф этилди
A9: 4 | B9: 14.08.2012 | C9: 2 | D9: ЯТТ МАМАСАИДОВА ДИЛАФРУЗ ЙУЛДОШЕВНА | E9: 15001000704063472003 | F9: 26800000 | G9: ООО TASHKENT GREAT | H9: 10.08.2012 йилдаги №10/08-сонли шартномага а-н миллий ширинликлар нон ишлаб чикариш учун ускуна сотиб олиш учун | J9: Бартараф этилди
A10: 5 | B10: 06.09.2012 | C10: 1 | D10: ЯТТ Хамракулов Фаридун Умедович | E10: 15001000704992946002 | F10: 20000000 | G10: OOO PRONTO BULDING SERVICE | H10: 2012 йил 28 августдаги № 577 сонли шаротномага асосан Алюмин профил ва ускина сотиб олиш учун утказилди | I10: Тўлов топшириқномаси мавжуд эмас | J10: Бартараф этилди
A11: 6 | B11: 19.10.2012 | C11: 914 дан 920 гача | D11: Cурхондонмахсулотлари ОАЖ | E11: 15101000900193989015 | F11: 350000000 | G11: OOO DONMAHSULOTPLAST | H11: Оинган кредит хисобидан 14.04.2012 йилдаги № В/04 шартномага асосан WACHTEL CAMPAKT 1/10 маркали нон печи олиш учун тулов. | I11: 7 та холатда Тўлов топшириқномаси мавжуд эмас | J11: Бартараф этилди
A12: 7 | B12: 19.10.2012 | C12: 88 | D12: Иброхим Термизий ф\х | E12: 13101000004949272002 | F12: 3412500 | G12: Термиз туманлараро Агрокиметаъминот базаси | H12: Шартномга асосан 2013 йил галла хосилини озукаси учун калийли ва фосфорли минерал угит олиш учун тулов | I12: Тўлов топшириқномаси мавжуд эмас | J12: Бартараф этилди
A13: 8 | B13: 19.10.2012 | C13: 76 | D13: Давлатов Асадбек ф\х | E13: 13101000104578335010 | F13: 3465000 | G13: Термиз туманлараро Агрокиметаъминот базаси | H13: Шартномга асосан 2013 йил галла хосилини озукаси учун калийли ва фосфорли минерал угит олиш учун тулов | I13: Тўлов топшириқномаси мавжуд эмас | J13: Бартараф этилди
A14: 9 | B14: 19.10.2012 | C14: 78 | D14: Камол Мехнатобод ф\х | E14: 13101000404952110002 | F14: 6740000 | G14: Термиз туманлараро Агрокиметаъминот базаси | H14: Шартномга асосан 2013 йил галла хосилини озукаси учун калийли ва фосфорли минерал угит олиш учун тулов | I14: Тўлов топшириқномаси мавжуд эмас | J14: Бартараф этилди
A15: 10 | B15: 24.10.2012 | C15: 3275 | D15: Сурхонпахтасаноат ХАБ | E15: 20210000800427048001 | F15: 2000000 | G15: Пахтсаноатсотиш ХАБнинг СПК маблаглари | H15: Бирлашма ходимлари Исломов А 500 минг сум Бегимов Б 500 м с Жураев Т 500 м с Кулбоев А 500 мс хизмат сафари харажати ПКга утказилд | I15: Тўлов топшириқномаси мавжуд эмас
C16: 3280 | F16: 30000000 | G16: Сурхондарё Пахтасаноат ХАБ | H16: Иктисод килинган маблаг хисобидан махсус хисоб ракамга утказилди | I16: Тўлов топшириқномаси мавжуд эмас
C17: 3276 | F17: 43540000 | G17: Турон хиссадорлик жамияти | H17: Ортилган пахта толаси хисобидан солик тулови учун устама ва жаримадан ташкари | I17: Тўлов топшириқномаси мавжуд эмас
A18: 11 | B18: 24.10.2012 | C18: 940 | D18: Cурхондонмахсулотлари ОАЖ | E18: 20210000900193989001 | F18: 509465 | G18: Сурхондарёдонмахсулотлари АЖ СПК маблаглари | H18: Бронга асосан Умбаров Уткир Ваитовичнинг 2012 й. август сентябр ойи иш хаки ПК.га утказилди | I18: Тўлов топшириқномаларида Доннинг бош бухгалтери имзоси мавжуд эмас | J18: Бартараф этилди
C19: 933 | F19: 2800000 | G19: Севинч Сабина Файз МЧЖ | H19: 5% зарурий эхтиёж хисобидан 2010 йилдаги шартномага асосан брокерлик хизмати учун тулов
C20: 932 | F20: 4200000 | G20: Севинч Сабина Файз МЧЖ
A21: 12 | B21: 02.11.2012 | C21: 73 | D21: Сурхон ф\х | E21: 15501000904115695006 | F21: 49000000 | G21: Шарбатбиби фх | H21: 2012 й. 20 октябрдаги 20/10-1 шартномага асосан МТЗ 80 трактори олиш учун тулов | I21: Тўлов топшириқномаси мавжуд эмас | J21: Бартараф этилди
A22: 13 | B22: 29.12.2012 | C22: 386 | D22: Сурхондаре вилоят кишлокхужаликкиме ОАЖ | E22: 12701000800427037021 | F22: 60000000 | G22: С В Кишлокхужаликкиме оаж | H22: Айланма маблагларини тулдириш учун | I22: Тўлов топшириқномаси мавжуд эмас | J22: Бартараф этилди
A23: 14 | B23: 29.12.2012 | C23: 28 | D23: Иброхим Термизий ф/х | E23: 15501000604949272001 | F23: 6260000 | G23: ЯТТ Худойбердиев Фуркат Ибрагимович | H23: .17.12.2012 йилдаги 17/12-сон шарт-га а-н кишлок хужалиг техникасига култеватция сотиб олиш учун | I23: Тўлов топшириқномаси мавжуд эмас | J23: Бартараф этилди
A24: 15 | B24: 31.01.2013 | C24: 3 | D24: Иброхим Термизий ф/х | E24: 15501000604949272001 | F24: 7240000 | G24: Шавкатжон Мехрузахон Термиз хусусий корхонаси | H24: 2012 йил 20/12 сонли шартномага асосан кишлок хужалиги техникасига прецеп сотиб олиш учун утказилди | I24: Тўлов топшириқномаси мавжуд эмас | J24: Бартараф этилди
A25: 16 | B25: 07.02.2013 | C25: 100 | D25: Cурхондонмахсулотлари ОАЖ | E25: 12701000000193989093 | F25: 14000000 | G25: Сурхондарё ТехПД | H25: Айланма маблагни тулдириш учун олинган кредит хисобидан 2012 йил шартномага асосан темир йул хизмати учун тулов | I25: Тўлов топшириқномаси мавжуд эмас | J25: Бартараф этилди
A26: 17 | B26: 07.02.2013 | C26: 91 | D26: Cурхондонмахсулотлари ОАЖ | E26: 12701000000193989093 | F26: 36000000 | G26: Кизирик автохизмат МЧЖ | H26: Айланма маблагни тулдириш учун олинган кредит хисобидан 2012 йил 01.02 шартномага асосан автоулов хизмати учун тулов | I26: Тўлов топшириқномаси мавжуд эмас | J26: Бартараф этилди
A27: 18 | B27: 07.02.2013 | C27: 90 | D27: Cурхондонмахсулотлари ОАЖ | E27: 12701000000193989093 | F27: 100000000 | G27: 'ООО Прогрес Азия Ангор' | H27: Айланма маблагни тулдириш учун олинган кредит хисобидан 2012 йил шартномага асосан курилиш ишлари учун тулов | I27: Тўлов топшириқномаси мавжуд эмас | J27: Бартараф этилди
A28: 19 | B28: 25.02.2013 | C28: 1 | D28: Ашур Жалил ф/х | E28: 13101000104328639006 | F28: 2250000 | G28: Термиз туманлараро Агрокиметаъминот базаси | H28: Галла 2013 йил хосилини кушимча минерал угит олиш учун тулов | I28: Тўлов топшириқномаси мавжуд эмас | J28: Бартараф этилди
A29: 20 | B29: 25.02.2013 | C29: 1 | D29: Хаитмуродбобо ф\х | E29: 13101000204234250017 | F29: 940000 | G29: Термиз туманлараро Агрокиметаъминот базаси | H29: Галла 2013 йил хосилини кушимча минерал угит олиш учун тулов | I29: Тўлов топшириқномаси мавжуд эмас | J29: Бартараф этилди
A30: 21 | B30: 25.02.2013 | C30: 1 | D30: Хужа Ф/Х | E30: 13101000404037931012 | F30: 1200000 | G30: Термиз туманлараро Агрокиметаъминот базаси | H30: Галла 2013 йил хосилини кушимча минерал угит олиш учун тулов | I30: Тўлов топшириқномаси мавжуд эмас | J30: Бартараф этилди
A31: 22 | B31: 25.02.2013 | C31: 1 | D31: Сурхон ф\х | E31: 13101000404115695015 | F31: 1363000 | G31: Термиз туманлараро Агрокиметаъминот базаси | H31: Галла 2013 йил хосилини кушимча минерал угит олиш учун тулов | I31: Тўлов топшириқномаси мавжуд эмас | J31: Бартараф этилди
A32: 23 | B32: 11.04.2013 | C32: 791, 816 ва 817 | D32: Сурхонпахтасаноат ХАБ | E32: 12701000900427048085 | F32: хар бири 1000000000 сумдан | G32: Узпахтасаноат уюшмаси | H32: Олинган кредит хисобидан моддий техника таъминоти ресурслари учун тулов | I32: Тўлов топшириқномалари мавжуд эмас 3 та холатда
B35: "Агробанк" ОАТБнинг Ички Аудит
B36: Департаменти бўлими бош мутахассиси: | F36: У.Р.Очилов
B38: "Агробанк" ОАТБ Жиззах вилояти бошқармаси
B39: Жиззах филиали бошқарувчиси: | F39: Ш.А.Игамназаров
B41: Бош бухгалтери: | F41: С.Р.Юсупов

Sheet 13.2342-йур
H1: 13-жадвал
A2: Адлия Вазирлигида 2012 йил 15 мартда 2342-сон билан рўйхатга олинган
A3: "Хўжалик юритувчи субъектларнинг банклардаги ҳисобварақларидан пул маблағларини ҳисобдан
A4: чиқариш тартиб тўғрисида"ги йўриқнома талабларининг бузилиш ҳолатлари бўйича
A5: М А Ъ Л У М О Т
H6: (минг сўмда)
A7: Т/Р | B7: Мижоз номи | C7: Маблағ чиққан кун | D7: Нотўғри тақсимланган сумма | E7: Маблағ кимга тўланиши керак | F7: Маблағ кимга тўланган | G7: Қўлланилган жариманинг сабаби | H7: Солиқ идоралари томонидан текширув натижасида қўлланилган жарима
A12: А | B12: Б | C12: 1 | D12: 2 | E12: 3 | F12: 4 | G12: 5 | H12: 6
A13: 1 | B13: Гулистон Мадад Қурилиш ХК | C13: 05,03,11 | D13: 66225.9 | E13: ДСИ | G13: 4 кунга кечиктирилган | H13: =+D13*0.5%*4 -> 1324.518
C14: 10,03,11 | D14: 4465.2 | E14: ДСИ | G14: 21 кунга кечиктирилган | H14: =+D14*0.5%*21 -> 468.846
C15: 31,03,11 | D15: 740.3 | E15: ДСИ | G15: 21 кунга кечиктирилган | H15: =+D15*0.5%*21 -> 77.7315
C16: 21,04,11 | D16: 40316.6 | E16: ДСИ | G16: 3 кунга кечиктирилган | H16: =+D16*0.5%*3 -> 604.749
C17: 04,05,11 | D17: 379.6 | E17: ДСИ | G17: 3 кунга кечиктирилган | H17: =+D17*0.5%*3 -> 5.694
C18: 07,05,11 | D18: 28145.7 | E18: ДСИ | G18: 3 кунга кечиктирилган | H18: =+D18*0.5%*3 -> 422.1855
C19: 11,05,11 | D19: 8145.7 | E19: ДСИ | G19: 2 кунга кечиктирилган | H19: =+D19*0.5%*2 -> 81.457
C20: 13,05,11 | D20: 6603.8 | E20: ДСИ | G20: 12 кунга кечиктирилган | H20: =+D20*0.5%*12 -> 396.228
C21: 25,05,11 | D21: 13072.9 | E21: ДСИ | G21: 3 кунга кечиктирилган | H21: =+D21*0.5%*3 -> 196.0935
C22: 25,06,11 | D22: 1130 | E22: ДСИ | G22: 11 кунга кечиктирилган | H22: =+D22*0.5%*11 -> 62.15
C23: 06,07,11 | D23: 858.6 | E23: ДСИ | G23: 2 кунга кечиктирилган | H23: =+D23*0.5%*2 -> 8.586
C24: 08,07,11 | D24: 6163.6 | E24: ДСИ | G24: 2 кунга кечиктирилган | H24: =+D24*0.5%*2 -> 61.636
B25: Жами: | D25: =SUM(D13:D24) -> 176247.9 | H25: =SUM(H13:H24) -> 3709.8745
A26: 2 | B26: Рамазон-Сервис ХФ | C26: 25,02,11 | D26: 109.3 | E26: ДСИ | G26: 2 кунга кечиктирилган | H26: =+D26*0.5%*2 -> 1.093
C27: 02,03,11 | D27: 141.6 | E27: ДСИ | G27: 7 кунга кечиктирилган | H27: =+D27*0.5%*7 -> 4.956
C28: 04,03,11 | D28: 6 | E28: ДСИ | G28: 9 кунга кечиктирилган | H28: =+D28*0.5%*9 -> 0.27
C29: 09,03,11 | D29: 2.9 | E29: ДСИ | G29: 14 кунга кечиктирилган | H29: =+D29*0.5%*14 -> 0.203
C30: 10,03,11 | D30: 30.8 | E30: ДСИ | G30: 15 кунга кечиктирилган | H30: =+D30*0.5%*15 -> 2.31
B31: Жами: | D31: =SUM(D26:D30) -> 290.6 | H31: =SUM(H26:H30) -> 8.832
A32: 3 | B32: Расул Диёр Хамкор ХК | C32: 27,08,11 | D32: 133.5 | E32: ДСИ | G32: 1 кунга кечиктирилган | H32: =+D32*0.5%*1 -> 0.6675
C33: 05,09,11 | D33: 130 | E33: ДСИ | G33: 10 кунга кечиктирилган | H33: =+D33*0.5%*10 -> 6.5
C34: 15,09,11 | D34: 45.7 | E34: ДСИ | G34: 20 кунга кечиктирилган | H34: =+D34*0.5%*20 -> 4.57
B35: Жами: | D35: =SUM(D32:D34) -> 309.2 | H35: =SUM(H32:H34) -> 11.7375
A36: 4 | B36: Рауф-Рахмон Хамкор ХК | C36: 07,05,11 | D36: 124.9 | E36: ДСИ | G36: 1 кунга кечиктирилган | H36: =+D36*0.5%*1 -> 0.6245
C37: 17,05,11 | D37: 148 | E37: ДСИ | G37: 11 кунга кечиктирилган | H37: 8.6
C38: 18,05,11 | D38: 48 | E38: ДСИ | G38: 12 кунга кечиктирилган | H38: =+D38*0.5%*12 -> 2.88
C39: 19,05,11 | D39: 56 | E39: ДСИ | G39: 13 кунга кечиктирилган | H39: =+D39*0.5%*13 -> 3.64
C40: 20,05,11 | D40: 55.3 | E40: ДСИ | G40: 14 кунга кечиктирилган | H40: =+D40*0.5%*14 -> 3.871
C41: 20,05,11 | D41: 148 | E41: ДСИ | G41: 194 кунга кечиктирилган | H41: 143.7
B42: Жами: | D42: =SUM(D36:D41) -> 580.2 | H42: =SUM(H36:H41) -> 163.3155
B43: Ҳаммаси: | C43: 0 | D43: =+D42+D35+D31+D25 -> 177427.9 | E43: х | F43: х | G43: х | H43: =+H42+H35+H31+H25 -> 3893.7595
B46: =""&(Шаблон!B1)&"нинг Ички Аудит" -> АТ "Халқ банк"нинг Ички Аудит
B47: Департаменти бош мутахассиси: | G47: =Шаблон!B13 -> А.Ҳазратқулов
B49: =""&(Шаблон!B1)&" "&(Шаблон!B2)&" вилоят бошқармаси" -> АТ "Халқ банк" Фаргона вилояти вилоят бошқармаси
B50: =""&(Шаблон!B3)&" филиал бошқарувчиси в.в.б.:" -> Бешариқ филиали филиал бошқарувчиси в.в.б.: | G50: =Шаблон!B5 -> _____________
B52: Бош бухгалтери в.в.б.: | G52: =Шаблон!B8 -> _____________

Sheet 14.29801(29896)
J1: 14-жадвал
A2: ="'"&(Шаблон!B1)&"нинг "&(Шаблон!B2)&" вилоят бошқармаси "&(Шаблон!B3)&" филиалида 29801 ва 29896 ҳисоб рақамлари орқали бажарилган нотўғри ўтказмалар тўғрисида" -> 'АТ "Халқ банк"нинг Фаргона вилояти вилоят бошқармаси Бешариқ филиали филиалида 29801 ва 29896 ҳисоб рақамлари орқали бажарилган нотўғри ўтказмалар тўғрисида
A3: М А Ъ Л У М О Т
J4: (минг сўмда)
A5: т\р | B5: Санаси | C5: Маблағ ўтказилган ҳисоб рақам номи | D5: Ҳисоб рақами | E5: Суммаси | F5: МФО | G5: Маблағ ўтган ташкилот | H5: Ҳисоб рақами | I5: Тўлов мақсади | J5: Аниқланган камчиликлар
A6: А | B6: Б | C6: 1 | D6: 2 | E6: 3 | F6: 4 | G6: 5 | H6: 6 | I6: 7 | J6: 8
A7: 1
A8: 2
A9: 3
A10: 4
A11: 5
A12: 6
B15: =""&(Шаблон!B1)&"нинг Ички Аудит" -> АТ "Халқ банк"нинг Ички Аудит
B16: Департаменти бош мутахассиси: | G16: =Шаблон!B13 -> А.Ҳазратқулов
B18: =""&(Шаблон!B1)&" "&(Шаблон!B2)&" вилоят бошқармаси" -> АТ "Халқ банк" Фаргона вилояти вилоят бошқармаси
B19: =""&(Шаблон!B3)&" филиали бошқарувчиси:" -> Бешариқ филиали филиали бошқарувчиси: | G19: =Шаблон!B5 -> _____________
B21: Бош бухгалтери в.в.б.: | G21: =Шаблон!B8 -> _____________

Sheet 16.Дивидент
I1: 16-жадвал
A2: =""&(Шаблон!B1)&"нинг "&(Шаблон!B2)&" вилоят бошқармаси "&(Шаблон!B3)&" филиали томонидан Банк акционерларига 2009 йил учун ҳисобланган дивидент суммаларининг тўланишида аниқланган камчиликлар тўғрисида" -> АТ "Халқ банк"нинг Фаргона вилояти вилоят бошқармаси Бешариқ филиали филиали томонидан Банк акционерларига 2009 йил учун ҳисобланган дивидент суммаларининг тўланишида аниқланган камчиликлар тўғрисида
A3: МАЪЛУМОТ
I4: (минг сўмда)
A5: Т/р | B5: Банк акционерлари номи | C5: Сотилган акция | F5: Дивидент | I5: Изоҳ
C6: тури | D6: сони | E6: суммаси | F6: ҳисобланган | G6: акционерларга тўланган | H6: фарқи (+; -)
A7: А | B7: Б | C7: 1 | D7: =+C7+1 -> 2 | E7: =+D7+1 -> 3 | F7: =+E7+1 -> 4 | G7: =+F7+1 -> 5 | H7: =+G7+1 -> 6 | I7: 7
A8: 1 | H8: =+F8-G8 -> 0
A9: =+A8+1 -> 2 | H9: =+F9-G9 -> 0
A10: =+A9+1 -> 3 | H10: =+F10-G10 -> 0
A11: =+A10+1 -> 4 | H11: =+F11-G11 -> 0
B12: жами | C12: =SUM(C8:C11) -> 0 | D12: =SUM(D8:D11) -> 0 | E12: =SUM(E8:E11) -> 0 | F12: =SUM(F8:F11) -> 0 | G12: =SUM(G8:G11) -> 0 | H12: =SUM(H8:H11) -> 0
B15: =""&(Шаблон!B1)&"нинг Ички Аудит" -> АТ "Халқ банк"нинг Ички Аудит
B16: Департаменти бош мутахассиси: | H16: =Шаблон!B13 -> А.Ҳазратқулов
B18: =""&(Шаблон!B1)&" "&(Шаблон!B2)&" вилоят бошқармаси" -> АТ "Халқ банк" Фаргона вилояти вилоят бошқармаси
B19: =""&(Шаблон!B3)&" филиали бошқарувчиси:" -> Бешариқ филиали филиали бошқарувчиси: | H19: =Шаблон!B5 -> _____________
B21: Бош бухгалтери в.в.б.: | H21: =Шаблон!B8 -> _____________

Sheet 18.харажат
I1: 18-жадвал
A2: =""&(Шаблон!B1)&"нинг "&(Шаблон!B2)&" шахар "&(Шаблон!B3)&" филиалида харажат ҳисоб рақамларидан амалга оширилган нотўғри амалиётлар тўғрисида" -> АТ "Халқ банк"нинг Фаргона вилояти шахар Бешариқ филиали филиалида харажат ҳисоб рақамларидан амалга оширилган нотўғри амалиётлар тўғрисида
A3: М А Ъ Л У М О Т
I4: (минг сўмда)
A5: т\р | B5: Санаси | D5: Харажат ҳисоб рақами | E5: Ўтган суммаси | F5: Маблағ ўтган ҳисоб рақам | G5: Ҳисоб рақам номи | H5: Тўлов мақсади | I5: Аниқланган камчилик | J5: Иззох
A6: А | B6: Б | D6: 1 | E6: 2 | F6: 3 | G6: 4 | H6: 5 | I6: 6 | J6: 7
A7: =+#REF!+1 -> #REF! | B7: 30.03.2018 | C7: =+MID(B7,4,8) -> 03.2018 | D7: 56710/268 | E7: 558000 | F7: 29802000500000793003 | G7: Авто таъмири учун | H7: № 02 от 30.03.2018 20.03.17й №11/13-07 ОСОГО шартномага асосан согирта полиси учун утказилди
B8: 05.02.2016 | C8: =+MID(B8,4,8) -> 02.2016 | D8: 56202/201 | E8: 600000 | F8: 29802000100000708201 | G8: Ижара тулови | H8: № 9 от 05.02.2016 01.03.2015 йилдаги №1 сонли шартномага асосан Янги хаёт Мини банкининг 2015 йил декабр ойи ижара тулови
B9: 16.03.2016 | C9: =+MID(B9,4,8) -> 03.2016 | D9: 56202/201 | E9: 1200000 | F9: 29802000100000708201 | G9: Ижара тулови | H9: № 9 от 16.03.2016 01.03.2015 йилдаги №1 сонли шартномага асосан Янги хаёт Мини банкининг 2016 йил январ феврал ойлари ижара тулови
B10: 03.06.2016 | C10: =+MID(B10,4,8) -> 06.2016 | D10: 56202/201 | E10: 600000 | F10: 29802000100000708201 | G10: Ижара тулови | H10: № 1 от 03.06.2016 янги хаёт мини банки март ойи ижарта тулови
B11: 27.01.2017 | C11: =+MID(B11,4,8) -> 01.2017 | D11: 56202/201 | E11: 1540000 | F11: 29802000100000708201 | G11: Ижара тулови | H11: № 27 от 27.01.2017 06.01.2016 й №187 сонли шартномага асосан Янги хаёт мини банкининг 2016 йил сентябр ойидан 2016-й декабр ойигача ижара тулови
B12: 27.03.2017 | C12: =+MID(B12,4,8) -> 03.2017 | D12: 56202/601 | E12: 1155000 | F12: 29802000300000708202 | G12: Ижара туловлари | H12: № 63 от 27.03.2017 05.01.2017й илдаги №Г/188 сонли ш-га асосан Янги хаёт мини банкининг 2017 йил январ феврал март ойлари ижара тулови кучирилди
B13: 27.04.2017 | C13: =+MID(B13,4,8) -> 04.2017 | D13: 56202/601 | E13: 385000 | F13: 29802000300000708202 | G13: Ижара туловлари | H13: № 21 от 27.04.2017 05.01.2017 йилдаги №Г/188 сонли шартномага асосан Янги хаёт мини банкининг 2017 йил апрел ойи ижара тулови кучирилди
B14: 31.07.2017 | C14: =+MID(B14,4,8) -> 07.2017 | D14: 56202/601 | E14: 385000 | F14: 29802000300000708202 | G14: Ижара туловлари | H14: № 1 от 31.07.2017 4 каватли савдо мажмуасидаги 187 гдуконнинг май июн ойлари ижара хакки "Янги хает" мини банки
B15: 31.07.2017 | C15: =+MID(B15,4,8) -> 07.2017 | D15: 56202/601 | E15: 770000 | F15: 29802000300000708202 | G15: Ижара туловлари | H15: № 1 от 31.07.2017 4 каватли савдо мажмуасидаги 187 гдуконнинг май июн ойлари ижара хакки "Янги хает" мини банки
B16: 23.10.2017 | C16: =+MID(B16,4,8) -> 10.2017 | D16: 56202/601 | E16: 1155000 | F16: 29802000300000708202 | G16: Ижара туловлари | H16: № 1 от 23.10.2017
B17: 13.12.2017 | C17: =+MID(B17,4,8) -> 12.2017 | D17: 56202/601 | E17: 770000 | F17: 29802000700000708100 | G17: Товар-моддий кимматликлар ва курсатилган хизматлар учун туланадиган маблаглар (бошкалар) | H17: № 1 от 13.12.2017
B18: 29.01.2018 | C18: =+MID(B18,4,8) -> 01.2018 | D18: 56202/601 | E18: 385000 | F18: 29802000700000708100 | G18: Товар-моддий кимматликлар ва курсатилган хизматлар учун туланадиган маблаглар (бошкалар) | H18: № 1 от 29.01.2018 27.01.2018 йиллдаги 4- сонли сч фактурага асосан Янги хает мини банки учун 4 каватли савдо мажмуасидаги 187- сонли дуконнинг 2018 й январ ойига ижара тулови
B19: 22.02.2018 | C19: =+MID(B19,4,8) -> 02.2018 | D19: 56202/601 | E19: 385000 | F19: 29802000700000708100 | G19: Товар-моддий кимматликлар ва курсатилган хизматлар учун туланадиган маблаглар (бошкалар) | H19: № 1 от 22.02.2018 20.02.2018 йилдаги 5- сонли сч фактурага асосан 4 каватли савдо мажмуасидаги 187 сонли дуконнинг 2018 й феврал ойи ижараси учун тулов
... B296: 22.12.2016 | C296: =+MID(B296,4,8) -> 12.2016 | D296: 56410/257 | E296: 446663.38 | F296: 29802000100000708257 | G296: Уяли алока хизмати | H296: № 25 от 22.12.2016 30.11.2016 йилдаги №00029360010083/D сонли хисоб фактурага асосан АТ Халк банки Навоий шахар филиалининг 2016 йил декабр ойи аълока тулови
B297: Жами:- | E297: =SUM(E7:E7) -> 558000
B300: =""&(Шаблон!B1)&"нинг Самарқанд вилоят филиали" -> АТ "Халқ банк"нинг Самарқанд вилоят филиали
B301: Якуний назорат бўлим бош мутахассиси: | H301: =Шаблон!B13 -> А.Ҳазратқулов
B303: =""&(Шаблон!B1)&" "&(Шаблон!B2)&" вилояти" -> АТ "Халқ банк" Фаргона вилояти вилояти
B304: =""&(Шаблон!B3)&" филиал бошқарувчиси:" -> Бешариқ филиали филиал бошқарувчиси: | H304: =Шаблон!B5 -> _____________
B306: Бош бухгалтери: | H306: =Шаблон!B8 -> _____________

Sheet 22812
A2: АТ Халқ банки Навоий шахар филиалида 22812-хисоб рақамида ассосиз бошқа мижозларнинг кредит қарздорликларини сундирилганлиги бўйича 2018 йил 1 сентябр холатига маълумот
A4: № | B4: Хисоб раками | C4: Маблаг эгасининг номи | D4: Нотўғри ўтказилган санаси | E4: Ассоссиз ўндирилган кредит ва фоиз хисоб рақами | G4: Кредит ва фоизи сундирилган қарздор номи | H4: Ассосиз ундирилган сумма
A5: 1 | B5: 22812000899003284001 | C5: Ярошова Аноргул Косимовна | D5: 31.10.2016 | E5: 12505000799000041001 | F5: 99000041 | G5: Муминов Санъат Жахонгирович | H5: 270808
A6: =+A5+1 -> 2 | B6: 22812000899003284001 | C6: Ярошова Аноргул Косимовна | D6: 31.10.2016 | E6: 16377000299000041001 | F6: 99000041 | G6: Муминов Санъат Жахонгирович | H6: 1485.36
A7: =+A6+1 -> 3 | B7: 22812000899003284001 | C7: Ярошова Аноргул Косимовна | D7: 31.10.2016 | E7: 16309000699000041001 | F7: 99000041 | G7: Муминов Санъат Жахонгирович | H7: 28581.52
A8: =+A7+1 -> 4 | B8: 22812000899003284001 | C8: Ярошова Аноргул Косимовна | D8: 31.10.2016 | E8: 16377000499000041002 | F8: 99000041 | G8: Муминов Санъат Жахонгирович | H8: 53939.91
H9: =SUM(H5:H8) -> 354814.79
A10: 5 | B10: 22812000999002972001 | C10: Pузикулов Абдумалик Одилович | D10: 27.07.2017 | E10: 14901000699003356001 | F10: 99003356 | G10: Очилов Хусниддин Рузимуродович | H10: 119016
A11: =+A10+1 -> 6 | B11: 22812000899003284001 | C11: Ярошова Аноргул Косимовна | D11: 31.10.2016 | E11: 12505000099003062001 | F11: 99003062 | G11: Муминов Жахонгир Рамазонович | H11: 8390
A12: =+A11+1 -> 7 | B12: 22812000999006882001 | C12: Йулдошев Сохиб Кахрамонович | D12: 05.02.2016 | E12: 22812000199006886001 | G12: КАДИРОВ АКРАМ ЧАРИБОЕВИЧ | H12: 33200
A14: 8 | B14: 22812000799003050001 | C14: Авезов Феруз Фазлиддинович | D14: 31.10.2016 | E14: 16377000699002986004 | F14: 99002986 | G14: Авезов Фаррух Фазлиддинович | H14: 7762.45
A15: =+A14+1 -> 9 | B15: 22812000799003050001 | C15: Авезов Феруз Фазлиддинович | D15: 31.10.2016 | E15: 16377000199002986007 | F15: 99002986 | G15: Авезов Фаррух Фазлиддинович | H15: 219.14
A16: =+A15+1 -> 10 | B16: 22812000799003050001 | C16: Авезов Феруз Фазлиддинович | D16: 31.10.2016 | E16: 16309000499002986001 | F16: 99002986 | G16: Авезов Фаррух Фазлиддинович | H16: 4657.46
A17: =+A16+1 -> 11 | B17: 22812000799003050001 | C17: Авезов Феруз Фазлиддинович | D17: 31.10.2016 | E17: 12505000599002986001 | F17: 99002986 | G17: Авезов Фаррух Фазлиддинович | H17: 25481.06
A18: =+A17+1 -> 12 | B18: 22812000799003050001 | C18: Авезов Феруз Фазлиддинович | D18: 23.11.2016 | E18: 16309000499002986001 | F18: 99002986 | G18: Авезов Фаррух Фазлиддинович | H18: 11468.94
A19: =+A18+1 -> 13 | B19: 22812000799003050001 | C19: Авезов Феруз Фазлиддинович | D19: 23.11.2016 | E19: 16377000699002986004 | F19: 99002986 | G19: Авезов Фаррух Фазлиддинович | H19: 410.95
H20: =SUM(H14:H19) -> 50000
A21: 14 | B21: 22812000399000152001 | C21: Давронова Юлдуз Юнус кизи | D21: 19.01.2018 | E21: 16309000299000246002 | F21: 99000246 | G21: Акабиров Фазлиддин Садуллаевич | H21: 35.34
A22: =+A21+1 -> 15 | B22: 22812000999000162001 | C22: Жураев Аминжон Олим угли | D22: 19.01.2018 | E22: 16309000299000246002 | F22: 99000246 | G22: Акабиров Фазлиддин Садуллаевич | H22: 40.09
A23: =+A22+1 -> 16 | B23: 22812000099000222001 | C23: Турдиева Мамура Марданкуловна | D23: 19.01.2018 | E23: 16309000299000246002 | F23: 99000246 | G23: Акабиров Фазлиддин Садуллаевич | H23: 0.17
A24: =+A23+1 -> 17 | B24: 22812000899000235001 | C24: Бекназарова Феруза Акабоевна | D24: 19.01.2018 | E24: 16309000299000246002 | F24: 99000246 | G24: Акабиров Фазлиддин Садуллаевич | H24: 0.34
A25: =+A24+1 -> 18 | B25: 22812000399002970001 | C25: Халимова Дилдора Одиловна | D25: 19.01.2018 | E25: 16309000299000246002 | F25: 99000246 | G25: Акабиров Фазлиддин Садуллаевич | H25: 2.78
A26: =+A25+1 -> 19 | B26: 22812000999002972001 | C26: Pузикулов Абдумалик Одилович | D26: 19.01.2018 | E26: 14901000899000246002 | F26: 99000246 | G26: Акабиров Фазлиддин Садуллаевич | H26: 1027.11
A27: =+A26+1 -> 20 | B27: 22812000599002976001 | C27: Бозоров Садирдин Шералиевич | D27: 19.01.2018 | E27: 16309000299000246002 | F27: 99000246 | G27: Акабиров Фазлиддин Садуллаевич | H27: 246.33
A28: =+A27+1 -> 21 | B28: 22812000999002992001 | C28: Маматназаров Абдужабар Базарбаевич | D28: 19.01.2018 | E28: 16309000299000246002 | F28: 99000246 | G28: Акабиров Фазлиддин Садуллаевич | H28: 32.29
A29: =+A28+1 -> 22 | B29: 22812000699002995001 | C29: Хамидова Гулшода Турдиевна | D29: 19.01.2018 | E29: 16309000299000246002 | F29: 99000246 | G29: Акабиров Фазлиддин Садуллаевич | H29: 558.65
A30: =+A29+1 -> 23 | B30: 22812000799003003001 | C30: Хужамова Дилбар Нуритдиновна | D30: 19.01.2018 | E30: 16309000299000246002 | F30: 99000246 | G30: Акабиров Фазлиддин Садуллаевич | H30: 93.61
A31: =+A30+1 -> 24 | B31: 22812000999003036001 | C31: Турдиев Гафур Нуриддинович | D31: 19.01.2018 | E31: 16309000299000246002 | F31: 99000246 | G31: Акабиров Фазлиддин Садуллаевич | H31: 73.91
A32: =+A31+1 -> 25 | B32: 22812000299003051001 | C32: Жураев Хусниддин Нуриллаевич | D32: 19.01.2018 | E32: 16309000299000246002 | F32: 99000246 | G32: Акабиров Фазлиддин Садуллаевич | H32: 21.67
A33: =+A32+1 -> 26 | B33: 22812000699003062001 | C33: Муминов Жахонгир Рамазонович | D33: 19.01.2018 | E33: 16309000299000246002 | F33: 99000246 | G33: Акабиров Фазлиддин Садуллаевич | H33: 40.1
... A141: =+A140+1 -> 134 | B141: 22812000099020970001 | C141: SHARIPOV OTABEK DANIYAROVICH | D141: 19.01.2018 | E141: 14901000899000246002 | F141: 99000246 | G141: Акабиров Фазлиддин Садуллаевич | H141: 870.64
H142: =SUM(H21:H141) -> 55692.09
H143: =+H142+H20+H12+H11+H10+H9 -> 621112.88

Sheet актив
G1: 1-жадвал
A2: АТ "Халқ банк"нинг Тошкент вилоят Чиноз филиали бўйича 2021 йил 1 январ ҳолатига активлар ТАҲЛИЛИ
G3: (минг сўмда)
A4: Т/р | B4: Активлар таркиби | C4: 2020 йил 1 январ ҳолатига | E4: 2021 йил 1 январ ҳолатига | G4: фарқи (+;-)
C5: Сумма | D5: фоиз | E5: Сумма | F5: фоиз
A6: I. | B6: Даромад келтирувчи активлар | C6: =C7+C8+C10+C9+C12+C13+C14+C11 -> 45149658 | D6: =+(C6)*100/C30 -> 87.661218 | E6: =E7+E8+E10+E9+E12+E13+E14+E11 -> 70001671 | F6: =+(E6)*100/E30 -> 80.763072 | G6: =G7+G8+G10+G9+G12+G13+G14+G11 -> 25518680 | H6: 24852013
A7: а | B7: - факторинг | C7: 0 | D7: =C7/C6*100 -> 0 | E7: 0 | F7: =E7/E6*100 -> 0 | G7: 0
A8: б | B8: - қисқа муддатли ва муддати утган ссудалар | C8: 4223809.1 | D8: =C8/C6*100 -> 9.3551298 | E8: 15577290 | F8: =E8/E6*100 -> 22.25274 | G8: 11353481
A9: в | B9: - узоқ муддатли ссудалар | C9: =28068466.3335+3416666.669 -> 31485133 | D9: =(C9)/C6*100 -> 69.735042 | E9: =39843470.31571+2749999.33400001 -> 42593470 | F9: =(E9)/E6*100 -> 60.846361 | G9: 11775004 | H9: 11108337
A10: г | B10: - лизинг | C10: 0 | D10: =C10/C6*100 -> 0 | E10: 0 | F10: =E10/E6*100 -> 0 | G10: 0
A11: д | B11: -Суд жараёнидаги кредитлар ва лизинг | C11: 0 | D11: =+C11/C6*100 -> 0 | E11: 581247.36 | F11: =+E11/E6*100 -> 0.83033355 | G11: 581247.36
A12: е | B12: - сўндириш муддатигача сакланадиган карз кимматли когозларга килинган инвестициялар | C12: 0 | D12: =C12/C6*100 -> 0 | E12: 0 | F12: =E12/E6*100 -> 0 | G12: 0
A13: ж | B13: - қўшма корхоналарга инвестиция | C13: 0 | D13: =C13/C6*100 -> 0 | E13: 0 | F13: =E13/E6*100 -> 0 | G13: 0
A14: ё | B14: - банк филиалларига берилган молиявий ёрдам ва ресурслар | C14: 9440716.1 | D14: =C14/C6*100 -> 20.909828 | E14: 11249665 | F14: =E14/E6*100 -> 16.070566 | G14: 1808948.6
A15: II. | B15: Даромад келтирмайдиган активлар | C15: =SUM(C16:C23) -> 6355054.4 | D15: =C15/C30*100 -> 12.338782 | E15: =SUM(E16:E23) -> 16673674 | F15: =E15/E30*100 -> 19.236928 | G15: =SUM(E15-C15) -> 10318620
A16: а | B16: - бош офисдан товар материал олиш учун ўтказилган маблағлар | C16: 0 | D16: =C16/C15*100 -> 0 | E16: 0 | F16: =E16/E15*100 -> 0 | G16: 0
A17: б | B17: - ҳисобланган, лекин ундирилмаган фоизлар | C17: 378298.25 | D17: =C17/C15*100 -> 5.9527146 | E17: 3437405 | F17: =E17/E15*100 -> 20.615762 | G17: 3059106.7
A18: в | B18: - банк мулклари | C18: 3615916.3 | D18: =C18/C15*100 -> 56.898275 | E18: 5590229.7 | F18: =E18/E15*100 -> 33.527282 | G18: 1974313.4
A19: г | B19: - чет эл валюталарининг сўмдаги қиймати | C19: 33984.466 | D19: =C19/C15*100 -> 0.53476279 | E19: 17179.425 | F19: =E19/E15*100 -> 0.10303323 | G19: -16805.041
A20: д | B20: - транзит счетлар | C20: 199999.48 | D20: =C20/C15*100 -> 3.1470932 | E20: 176406.14 | F20: =E20/E15*100 -> 1.057992 | G20: -23593.338
A21: е | B21: - давлат ҳисоб рақамлари | C21: 0 | D21: =C21/C15*100 -> 0 | E21: 0 | F21: =E21/E15*100 -> 0 | G21: 0
A22: ё | B22: - бошқа активлар | C22: 827525.55 | D22: =C22/C15*100 -> 13.021534 | E22: 34286.6 | F22: =E22/E15*100 -> 0.20563314 | G22: -793238.95
